Workbook

Sheet 集計
A1: cpp_shuffle | C1: 調査件数 | D1: csharp_shuffle | F1: 調査件数 | G1: java_shuffle | I1: 調査件数 | J1: javascript_shuffle | L1: 調査件数 | M1: php_shuffle | O1: 調査件数 | P1: ruby_shuffle | R1: 調査件数
B2: =SUM(B3:B7) -> 0 | C2: =SUM(C3:C7) -> 0 | E2: =SUM(E3:E7) -> 58 | F2: =SUM(F3:F7) -> 50 | H2: =SUM(H3:H7) -> 56 | I2: =SUM(I3:I7) -> 50 | K2: =SUM(K3:K7) -> 0 | L2: =SUM(L3:L7) -> 0 | N2: =SUM(N3:N7) -> 0 | O2: =SUM(O3:O7) -> 0 | Q2: =SUM(Q3:Q7) -> 24 | R2: =SUM(R3:R7) -> 23
A3: {=code!$A$1:$A$5} -> 差し戻し | B3: =COUNTIF(INDIRECT(A$1 & "!G2:G1000"), A3) -> 0 | C3: =IFERROR(__xludf.DUMMYFUNCTION("IF(NOT(REGEXMATCH(A3, ""誤検出|調査不能"")), B3, 0)"),0.0) -> 0 | D3: {=code!$A$1:$A$5} -> 差し戻し | E3: =COUNTIF(INDIRECT(D$1 & "!G2:G1000"), D3) -> 10 | F3: =IFERROR(__xludf.DUMMYFUNCTION("IF(NOT(REGEXMATCH(D3, ""誤検出|調査不能"")), E3, 0)"),10.0) -> 10 | G3: {=code!$A$1:$A$5} -> 差し戻し | H3: =COUNTIF(INDIRECT(G$1 & "!G2:G1000"), G3) -> 14 | I3: =IFERROR(__xludf.DUMMYFUNCTION("IF(NOT(REGEXMATCH(G3, ""誤検出|調査不能"")), H3, 0)"),14.0) -> 14 | J3: {=code!$A$1:$A$5} -> 差し戻し | K3: =COUNTIF(INDIRECT(J$1 & "!G2:G1000"), J3) -> 0 | L3: =IFERROR(__xludf.DUMMYFUNCTION("IF(NOT(REGEXMATCH(J3, ""誤検出|調査不能"")), K3, 0)"),0.0) -> 0 | M3: {=code!$A$1:$A$5} -> 差し戻し | N3: =COUNTIF(INDIRECT(M$1 & "!G2:G1000"), M3) -> 0 | O3: =IFERROR(__xludf.DUMMYFUNCTION("IF(NOT(REGEXMATCH(M3, ""誤検出|調査不能"")), N3, 0)"),0.0) -> 0 | P3: {=code!$A$1:$A$5} -> 差し戻し | Q3: =COUNTIF(INDIRECT(P$1 & "!G2:G1000"), P3) -> 2 | R3: =IFERROR(__xludf.DUMMYFUNCTION("IF(NOT(REGEXMATCH(P3, ""誤検出|調査不能"")), Q3, 0)"),2.0) -> 2
A4: 機能変更 | B4: =COUNTIF(INDIRECT(A$1 & "!G2:G1000"), A4) -> 0 | C4: =IFERROR(__xludf.DUMMYFUNCTION("IF(NOT(REGEXMATCH(A4, ""誤検出|調査不能"")), B4, 0)"),0.0) -> 0 | D4: 機能変更 | E4: =COUNTIF(INDIRECT(D$1 & "!G2:G1000"), D4) -> 34 | F4: =IFERROR(__xludf.DUMMYFUNCTION("IF(NOT(REGEXMATCH(D4, ""誤検出|調査不能"")), E4, 0)"),34.0) -> 34 | G4: 機能変更 | H4: =COUNTIF(INDIRECT(G$1 & "!G2:G1000"), G4) -> 27 | I4: =IFERROR(__xludf.DUMMYFUNCTION("IF(NOT(REGEXMATCH(G4, ""誤検出|調査不能"")), H4, 0)"),27.0) -> 27 | J4: 機能変更 | K4: =COUNTIF(INDIRECT(J$1 & "!G2:G1000"), J4) -> 0 | L4: =IFERROR(__xludf.DUMMYFUNCTION("IF(NOT(REGEXMATCH(J4, ""誤検出|調査不能"")), K4, 0)"),0.0) -> 0 | M4: 機能変更 | N4: =COUNTIF(INDIRECT(M$1 & "!G2:G1000"), M4) -> 0 | O4: =IFERROR(__xludf.DUMMYFUNCTION("IF(NOT(REGEXMATCH(M4, ""誤検出|調査不能"")), N4, 0)"),0.0) -> 0 | P4: 機能変更 | Q4: =COUNTIF(INDIRECT(P$1 & "!G2:G1000"), P4) -> 20 | R4: =IFERROR(__xludf.DUMMYFUNCTION("IF(NOT(REGEXMATCH(P4, ""誤検出|調査不能"")), Q4, 0)"),20.0) -> 20
A5: 機能削除 | B5: =COUNTIF(INDIRECT(A$1 & "!G2:G1000"), A5) -> 0 | C5: =IFERROR(__xludf.DUMMYFUNCTION("IF(NOT(REGEXMATCH(A5, ""誤検出|調査不能"")), B5, 0)"),0.0) -> 0 | D5: 機能削除 | E5: =COUNTIF(INDIRECT(D$1 & "!G2:G1000"), D5) -> 6 | F5: =IFERROR(__xludf.DUMMYFUNCTION("IF(NOT(REGEXMATCH(D5, ""誤検出|調査不能"")), E5, 0)"),6.0) -> 6 | G5: 機能削除 | H5: =COUNTIF(INDIRECT(G$1 & "!G2:G1000"), G5) -> 9 | I5: =IFERROR(__xludf.DUMMYFUNCTION("IF(NOT(REGEXMATCH(G5, ""誤検出|調査不能"")), H5, 0)"),9.0) -> 9 | J5: 機能削除 | K5: =COUNTIF(INDIRECT(J$1 & "!G2:G1000"), J5) -> 0 | L5: =IFERROR(__xludf.DUMMYFUNCTION("IF(NOT(REGEXMATCH(J5, ""誤検出|調査不能"")), K5, 0)"),0.0) -> 0 | M5: 機能削除 | N5: =COUNTIF(INDIRECT(M$1 & "!G2:G1000"), M5) -> 0 | O5: =IFERROR(__xludf.DUMMYFUNCTION("IF(NOT(REGEXMATCH(M5, ""誤検出|調査不能"")), N5, 0)"),0.0) -> 0 | P5: 機能削除 | Q5: =COUNTIF(INDIRECT(P$1 & "!G2:G1000"), P5) -> 1 | R5: =IFERROR(__xludf.DUMMYFUNCTION("IF(NOT(REGEXMATCH(P5, ""誤検出|調査不能"")), Q5, 0)"),1.0) -> 1
A6: 誤検出 | B6: =COUNTIF(INDIRECT(A$1 & "!G2:G1000"), A6) -> 0 | C6: =IFERROR(__xludf.DUMMYFUNCTION("IF(NOT(REGEXMATCH(A6, ""誤検出|調査不能"")), B6, 0)"),0.0) -> 0 | D6: 誤検出 | E6: =COUNTIF(INDIRECT(D$1 & "!G2:G1000"), D6) -> 8 | F6: =IFERROR(__xludf.DUMMYFUNCTION("IF(NOT(REGEXMATCH(D6, ""誤検出|調査不能"")), E6, 0)"),0.0) -> 0 | G6: 誤検出 | H6: =COUNTIF(INDIRECT(G$1 & "!G2:G1000"), G6) -> 5 | I6: =IFERROR(__xludf.DUMMYFUNCTION("IF(NOT(REGEXMATCH(G6, ""誤検出|調査不能"")), H6, 0)"),0.0) -> 0 | J6: 誤検出 | K6: =COUNTIF(INDIRECT(J$1 & "!G2:G1000"), J6) -> 0 | L6: =IFERROR(__xludf.DUMMYFUNCTION("IF(NOT(REGEXMATCH(J6, ""誤検出|調査不能"")), K6, 0)"),0.0) -> 0 | M6: 誤検出 | N6: =COUNTIF(INDIRECT(M$1 & "!G2:G1000"), M6) -> 0 | O6: =IFERROR(__xludf.DUMMYFUNCTION("IF(NOT(REGEXMATCH(M6, ""誤検出|調査不能"")), N6, 0)"),0.0) -> 0 | P6: 誤検出 | Q6: =COUNTIF(INDIRECT(P$1 & "!G2:G1000"), P6) -> 1 | R6: =IFERROR(__xludf.DUMMYFUNCTION("IF(NOT(REGEXMATCH(P6, ""誤検出|調査不能"")), Q6, 0)"),0.0) -> 0
A7: 調査不能 | B7: =COUNTIF(INDIRECT(A$1 & "!G2:G1000"), A7) -> 0 | C7: =IFERROR(__xludf.DUMMYFUNCTION("IF(NOT(REGEXMATCH(A7, ""誤検出|調査不能"")), B7, 0)"),0.0) -> 0 | D7: 調査不能 | E7: =COUNTIF(INDIRECT(D$1 & "!G2:G1000"), D7) -> 0 | F7: =IFERROR(__xludf.DUMMYFUNCTION("IF(NOT(REGEXMATCH(D7, ""誤検出|調査不能"")), E7, 0)"),0.0) -> 0 | G7: 調査不能 | H7: =COUNTIF(INDIRECT(G$1 & "!G2:G1000"), G7) -> 1 | I7: =IFERROR(__xludf.DUMMYFUNCTION("IF(NOT(REGEXMATCH(G7, ""誤検出|調査不能"")), H7, 0)"),0.0) -> 0 | J7: 調査不能 | K7: =COUNTIF(INDIRECT(J$1 & "!G2:G1000"), J7) -> 0 | L7: =IFERROR(__xludf.DUMMYFUNCTION("IF(NOT(REGEXMATCH(J7, ""誤検出|調査不能"")), K7, 0)"),0.0) -> 0 | M7: 調査不能 | N7: =COUNTIF(INDIRECT(M$1 & "!G2:G1000"), M7) -> 0 | O7: =IFERROR(__xludf.DUMMYFUNCTION("IF(NOT(REGEXMATCH(M7, ""誤検出|調査不能"")), N7, 0)"),0.0) -> 0 | P7: 調査不能 | Q7: =COUNTIF(INDIRECT(P$1 & "!G2:G1000"), P7) -> 0 | R7: =IFERROR(__xludf.DUMMYFUNCTION("IF(NOT(REGEXMATCH(P7, ""誤検出|調査不能"")), Q7, 0)"),0.0) -> 0

Sheet cpp_shuffle
B1: name_with_owner | C1: insert url | D1: delete url | E1: replacement_msg | F1: delete_msg | G1: coding | H1: insert commit | I1: insert src file | J1: insert src start pos | K1: insert dst file | L1: insert dst start pos | M1: delete commit | N1: delete src file | O1: delete src start pos | P1: delete dst file | Q1: delete dst start pos | R1: insert src file content | S1: insert dst file content | T1: delete src file content
A2: 0 | B2: kingsamchen_Eureka | C2: https://github.com/kingsamchen/Eureka/commit/a61aa11e56be33dda5cbcbc1f461652515d94a4b | E2: himsw: basically work | F2: himsw: use pure win32 gui | H2: 16965166a1f6d03434296da844a73fc09b0e0770 | I2: hey-i-am-still-working/himsw/main.cpp | J2: (8, 12) | K2: hey-i-am-still-working/himsw/main.cpp | L2: (45, 34) | M2: a61aa11e56be33dda5cbcbc1f461652515d94a4b | N2: hey-i-am-still-working/himsw/main.cpp | O2: (90, 23) | P2: hey-i-am-still-working/himsw/main.cpp | R2: { while (true) { himsw::labor_monitor::instance().tick(); std::this_thread::sleep_for(std::chrono::seconds(60)); } return 0; } | S2: { this->caption("Hey I AM Still Working"); lbl_info_.size(this->size()); lbl_info_.caption("monitoring..."); timer_.elapse([] { himsw::labor_monitor::instance().tick(); }); timer_.interval(std::chrono::seconds(30)); timer_.start(); } | T2: [] { himsw::labor_monitor::instance().tick(); }
A3: 1 | B3: apple_swift | C3: https://github.com/apple/swift/commit/bb067f4d6827f9be36df8779552cfc6c595e1c00 | D3: https://github.com/apple/swift/commit/8b926af49a2aad883cb358812aa67137e8199222 | E3: Revert "EscapeAnalysis: add node flags and change the meaning of "escaping"" | F3: EscapeAnalysis: Add PointerKind and interior/reference flags Categorize three kinds of pointers: NoPointer (don't create a node) ReferenceOnly (safe to make normal assumptions) AnyPointer (may have addresses, rawpointers, or any mix of thoses with references) Flag ConnectionGraph nodes as - hasReferenceOnly - isInterior An interior node always has an additional content node. All sorts of arbitrary node merging is supported. Nodes with totally different properties can be safely merged. Interior nodes can safely be merged with their field content (which does happen surprisingly often). Alias analysis will use these flags to safely make assumptions about properties of the connection graph. | H3: bb067f4d6827f9be36df8779552cfc6c595e1c00 | I3: lib/SILOptimizer/Analysis/EscapeAnalysis.cpp | J3: (914, 3) | K3: lib/SILOptimizer/Analysis/EscapeAnalysis.cpp | L3: (1570, 3) | M3: 8b926af49a2aad883cb358812aa67137e8199222 | N3: lib/SILOptimizer/Analysis/EscapeAnalysis.cpp | O3: (1570, 16) | P3: lib/SILOptimizer/Analysis/EscapeAnalysis.cpp | R3: bool contentHasReferenceOnly = EA->hasReferenceOnly(addrVal->getType().getObjectType(), *F); | S3: auto hasRC = [&](){ return mustContainReference(baseAddr->getType(), *F) || mustContainReference(addrVal->getType(), *F); }; | T3: [&](){ return mustContainReference(baseAddr->getType(), *F) || mustContainReference(addrVal->getType(), *F); }
A4: 2 | B4: apple_swift | C4: https://github.com/apple/swift/commit/9dbd5829debeca41abe8035393ba9f493408c54d | D4: https://github.com/apple/swift/commit/927cf42ba656051cb51007293c19349b60ddd965 | E4: [CodeCompletion] Support type checking attributes even if they are not part of the AST The code completion might occur inside an attriubte that isn’t part of the AST because it’s missing a `VarDecl` that it could be attached to. In these cases, record the `CustomAttr` and type check it standalone, pretending it was part of a `DeclContext`. This also fixes a few issues where code completion previously wouldn’t find the attribute constructor call and thus wasn’t providing code completion inside the property wrapper. rdar://92842803 | F4: [CodeCompletion] Move implementation of solver-based completions to their own functions This has the benefit that in case of a code completion crash, we can see what kind of completion crashed without having to symbolicate the stack trace using LLDB. It also made `trySolverCompletion` small enough that we can inline it into `doneParsing`, which makes debugging easier because you won’t accidentally step over the call to `trySolverCompletion`, which actually performs the completion. | H4: 9dbd5829debeca41abe8035393ba9f493408c54d | I4: lib/IDE/CodeCompletion.cpp | J4: (1326, 75) | K4: lib/IDE/CodeCompletion.cpp | L4: (1337, 75) | M4: 927cf42ba656051cb51007293c19349b60ddd965 | N4: lib/IDE/CodeCompletion.cpp | O4: (1458, 30) | P4: lib/IDE/CodeCompletion.cpp | R4: { assert(ParsedExpr || CurDeclContext); SourceLoc CompletionLoc = ParsedExpr ? ParsedExpr->getLoc() : CurDeclContext->getASTContext().SourceMgr.getCodeCompletionLoc(); switch (Kind) { case CompletionKind::DotExpr: { assert(CodeCompleteTokenExpr); assert(CurDeclContext); DotExprTypeCheckCompletionCallback Lookup(CodeCompleteTokenExpr, CurDeclContext); llvm::SaveAndRestore<TypeCheckCompletionCallback*> CompletionCollector(Context.CompletionCallback, &Lookup); typeCheckContextAt(CurDeclContext, CompletionLoc); // This (hopefully) only happens in cases where the expression isn't // typechecked during normal compilation either (e.g. member completion in a // switch case where there control expression is invalid). Having normal // typechecking still resolve even these cases would be beneficial for // tooling in general though. if (!Lookup.gotCallback()) Lookup.fallbackTypeCheck(CurDeclContext); addKeywords(CompletionContext.getResultSink(), MaybeFuncBody); Expr *CheckedBase = CodeCompleteTokenExpr->getBase(); Lookup.deliverResults(CheckedBase, CurDeclContext, DotLoc, isInsideObjCSelector(), CompletionContext, Consumer); return true; } | S4: { assert(ParsedExpr || CurDeclContext); SourceLoc CompletionLoc = ParsedExpr ? ParsedExpr->getLoc() : CurDeclContext->getASTContext().SourceMgr.getCodeCompletionLoc(); auto typeCheckWithLookup = [this, &CompletionLoc]( TypeCheckCompletionCallback &Lookup) { llvm::SaveAndRestore<TypeCheckCompletionCallback*> CompletionCollector(Context.CompletionCallback, &Lookup); if (AttrWithCompletion) { /// The attribute might not be attached to the AST if there is no var decl /// it could be attached to. Type check it standalone. ASTNode Call = CallExpr::create( CurDeclContext->getASTContext(), AttrWithCompletion->getTypeExpr(), AttrWithCompletion->getArgs(), /*implicit=*/true); typeCheckContextAt( TypeCheckASTNodeAtLocContext::node(CurDeclContext, Call), CompletionLoc); } | T4: [this, &CompletionLoc]( TypeCheckCompletionCallback &Lookup) { llvm::SaveAndRestore<TypeCheckCompletionCallback*> CompletionCollector(Context.CompletionCallback, &Lookup); if (AttrWithCompletion) { /// The attribute might not be attached to the AST if there is no var /// decl it could be attached to. Type check it standalone. // First try to check it as an attached macro. auto resolvedMacro = evaluateOrDefault( CurDeclContext->getASTContext().evaluator, ResolveMacroRequest{AttrWithCompletion, CurDeclContext}, ConcreteDeclRef()); // If that fails, type check as a call to the attribute's type. This is // how, e.g., property wrappers are modelled. if (!resolvedMacro) { ASTNode Call = CallExpr::create( CurDeclContext->getASTContext(), AttrWithCompletion->getTypeExpr(), AttrWithCompletion->getArgs(), /*implicit=*/true); typeCheckContextAt( TypeCheckASTNodeAtLocContext::node(CurDeclContext, Call), CompletionLoc); } } else { typeCheckContextAt( TypeCheckASTNodeAtLocContext::declContext(CurDeclContext), CompletionLoc); } // This (hopefully) only happens in cases where the expression isn't // typechecked during normal compilation either (e.g. member completion in a // switch case where there control expression is invalid). Having normal // typechecking still resolve even these cases would be beneficial for // tooling in general though. if (!Lookup.gotCallback()) { if (Context.TypeCheckerOpts.DebugConstraintSolver) { llvm::errs() << "--- Fallback typecheck for code completion ---\n"; } Lookup.fallbackTypeCheck(CurDeclContext); } }
A5: 3 | B5: ElunaLuaEngine_ElunaTrinityWotlk | C5: https://github.com/ElunaLuaEngine/ElunaTrinityWotlk/commit/14c2b2d6cd2303609f1a1859e727ace7b8ea649c | D5: https://github.com/ElunaLuaEngine/ElunaTrinityWotlk/commit/3d3d0492ab8dad40d5590e80f45bdfbdbcbe7497 | E5: Core/Spell: added some helpers to SpellInfo to reduce code duplication | F5: Core/Spells: Check both main and offhand weapons if spell attributes require that (see Stormstrike) * This restores the check probably unintentionally dropped in 14c2b2d6cd2303609f1a1859e727ace7b8ea649c * Build fix | H5: 14c2b2d6cd2303609f1a1859e727ace7b8ea649c | I5: src/server/game/Spells/Spell.cpp | J5: (6589, 13) | K5: src/server/game/Spells/Spell.cpp | L5: (6554, 9) | M5: 3d3d0492ab8dad40d5590e80f45bdfbdbcbe7497 | N5: src/server/game/Spells/Spell.cpp | O5: (6554, 35) | P5: src/server/game/Spells/Spell.cpp | R5: Item* item = m_caster->ToPlayer()->GetWeaponForAttack(OFF_ATTACK); | S5: SpellCastResult itemRes = [this]() -> SpellCastResult { switch (m_attackType) { case BASE_ATTACK: // main hand weapon required if (!m_spellInfo->HasAttribute(SPELL_ATTR3_MAIN_HAND)) return SPELL_CAST_OK; case OFF_ATTACK: // offhand hand weapon required if (!m_spellInfo->HasAttribute(SPELL_ATTR3_REQ_OFFHAND)) return SPELL_CAST_OK; default: return SPELL_CAST_OK; } Item const* item = m_caster->ToPlayer()->GetWeaponForAttack(m_attackType); | T5: [this]() -> SpellCastResult { switch (m_attackType) { case BASE_ATTACK: // main hand weapon required if (!m_spellInfo->HasAttribute(SPELL_ATTR3_MAIN_HAND)) return SPELL_CAST_OK; break; case OFF_ATTACK: // offhand hand weapon required if (!m_spellInfo->HasAttribute(SPELL_ATTR3_REQ_OFFHAND)) return SPELL_CAST_OK; break; default: return SPELL_CAST_OK; } Item const* item = m_caster->ToPlayer()->GetWeaponForAttack(m_attackType)
A6: 4 | B6: apple_swift | C6: https://github.com/apple/swift/commit/0beddca9e93643a245e2b374fa364659ed4d122e | D6: https://github.com/apple/swift/commit/41cdfb04adfe13839af9e9867f775559ee307296 | E6: Unify diagnose invalid attr producing | F6: Introduce a proper TypeAttribute class hierarchy. The old TypeAttributes reprsentation wasn't too bad for a small number of simple attributes. Unfortunately, the number of attributes has grown over the years by quite a bit, which makes TypeAttributes fairly bulky even at just a single SourceLoc per attribute. The bigger problem is that we want to carry more information than that on some of these attributes, which is all super ad hoc and awkward. And given that we want to do some things for each attribute we see, like diagnosing unapplied attributes, the linear data structure does require a fair amount of extra work. I switched around the checking logic quite a bit in order to try to fit in with the new representation better. The most significant change here is the change to how we handle implicit noescape, where now we're passing the escaping attribute's presence down in the context instead of resetting the context anytime we see any attributes at all. This should be cleaner overall. The source range changes around some of the @escaping checking is really a sort of bugfix --- the existing code was really jumping from the @ sign all the way past the autoclosure keyword in a way that I'm not sure always works and is definitely a little unintentional-feeling. I tried to make the parser logic more consistent around recognizing these parameter specifiers; it seems better now, at least. | H6: 0beddca9e93643a245e2b374fa364659ed4d122e | I6: lib/Sema/TypeCheckType.cpp | J6: (2421, 9) | K6: lib/Sema/TypeCheckType.cpp | L6: (2414, 5) | M6: 41cdfb04adfe13839af9e9867f775559ee307296 | N6: lib/Sema/TypeCheckType.cpp | O6: (3376, 38) | P6: lib/Sema/TypeCheckType.cpp | R6: auto diag = diagnoseInvalid(repr, attrs.getLoc(i), diag::escaping_optional_type_argument); | S6: const auto diagnoseInvalidAttr = [&](TypeAttrKind kind) { if (kind == TAK_escaping) { Type optionalObjectType = ty->getOptionalObjectType(); if (optionalObjectType && optionalObjectType->is<AnyFunctionType>()) { return diagnoseInvalid(repr, attrs.getLoc(kind), diag::escaping_optional_type_argument); } } return diagnoseInvalid(repr, attrs.getLoc(kind), diag::attribute_requires_function_type, TypeAttributes::getAttrName(kind)); }; | T6: [&](TypeAttrKind kind) { if (kind == TAK_escaping) { Type optionalObjectType = ty->getOptionalObjectType(); if (optionalObjectType && optionalObjectType->is<AnyFunctionType>()) { return diagnoseInvalid(repr, attrs.getLoc(kind), diag::escaping_optional_type_argument); } } return diagnoseInvalid(repr, attrs.getLoc(kind), diag::attribute_requires_function_type, TypeAttributes::getAttrName(kind)); }
A7: 5 | B7: apple_swift | C7: https://github.com/apple/swift/commit/10fc3fa54677a7023079f70f0600a209777edffe | D7: https://github.com/apple/swift/commit/3d5ca29993eb4b2f11f502cd0c812d1238a72557 | E7: [GenericSig Builder] Make resolve() less representative-dependent. `GenericSignatureBuilder::resolve()` was always jumping to the representative, to treat typealias representatives as special. However, doing this means that we put the same-type constraint on the wrong potential archetype (with the wrong source). Eliminate the use of `getRepresentative()`. This unfortunately causes us to need recursive resolution, because we can't always depend on jumping to the representative to avoid it. | F7: GSB: Dump conformance and same-type requirement sources in EquivalenceClass::dump() | H7: 10fc3fa54677a7023079f70f0600a209777edffe | I7: lib/AST/GenericSignatureBuilder.cpp | J7: (902, 3) | K7: lib/AST/GenericSignatureBuilder.cpp | L7: (900, 3) | M7: 3d5ca29993eb4b2f11f502cd0c812d1238a72557 | N7: lib/AST/GenericSignatureBuilder.cpp | O7: (2171, 7) | P7: lib/AST/GenericSignatureBuilder.cpp | R7: builder.addSameTypeRequirement(nestedPA, witnessType, source); | S7: builder.addSameTypeRequirement(nestedPA, witnessType, source, [&](Type type1, Type type2) { builder.getASTContext().Diags.diagnose( source->getLoc(), diag::requires_same_type_conflict, nestedPA->getDependentType(/*FIXME: */{ }, true), type1, type2); }); | T7: [&](const Constraint<Type> &constraint) { out << "\n " << constraint.getSubjectDependentType({}) << " == " << constraint.value; if (constraint.source->isDerivedRequirement()) out << " [derived]"; }
A8: 6 | B8: eosforce_eosforce | C8: https://github.com/eosforce/eosforce/commit/4a588b479f292c0b29ecc41f1679f914326f4174 | D8: https://github.com/eosforce/eosforce/commit/7a084347167d752c4a9509e79ebad809f398bf75 | E8: Avoid tying up a thread to wait on transaction future. Also removes likely safe but undefined behavior. | F8: Revert to 1.8.1 version of signature recovery | H8: 4a588b479f292c0b29ecc41f1679f914326f4174 | I8: plugins/producer_plugin/producer_plugin.cpp | J8: (351, 150) | K8: plugins/producer_plugin/producer_plugin.cpp | L8: (351, 150) | M8: 7a084347167d752c4a9509e79ebad809f398bf75 | N8: plugins/producer_plugin/producer_plugin.cpp | O8: (415, 16) | P8: plugins/producer_plugin/producer_plugin.cpp | R8: { chain::controller& chain = chain_plug->chain(); const auto max_trx_time_ms = _max_transaction_time_ms.load(); fc::microseconds max_trx_cpu_usage = max_trx_time_ms < 0 ? fc::microseconds::maximum() : fc::milliseconds( max_trx_time_ms ); auto& tp = *_thread_pool; // use chain thread pool for sig recovery so that future wait below is not in the same thread pool preventing progress transaction_metadata::create_signing_keys_future( trx, tp, chain.get_chain_id(), max_trx_cpu_usage ); boost::asio::post( tp, [self = this, trx, persist_until_expired, next]() { if( trx->signing_keys_future.valid() ) trx->signing_keys_future.wait(); app().post(priority::low, [self, trx, persist_until_expired, next]() { self->process_incoming_transaction_async( trx, persist_until_expired, next ); }); }); } | S8: { chain::controller& chain = chain_plug->chain(); const auto max_trx_time_ms = _max_transaction_time_ms.load(); fc::microseconds max_trx_cpu_usage = max_trx_time_ms < 0 ? fc::microseconds::maximum() : fc::milliseconds( max_trx_time_ms ); auto& tp = *_thread_pool; // use chain thread pool for sig recovery so that future wait below is not in the same thread pool preventing progress transaction_metadata::create_signing_keys_future( trx, chain.get_thread_pool(), chain.get_chain_id(), max_trx_cpu_usage, [self = this, trx, persist_until_expired, next{std::move(next)} | T8: [self = this, trx, persist_until_expired, next{std::move(next)
A9: 7 | B9: apple_swift | C9: https://github.com/apple/swift/commit/0a1f7c09dfc4af6b856b45058d20118039ef1b4d | D9: https://github.com/apple/swift/commit/5ead9764bd79b91ec973c4964488330f6aa69958 | E9: Revert "Fix unreachable code handling to properly diagnose things like:" This reverts commit 28678. It broke the IDE/complete_exception.swift test. Swift SVN r28679 | F9: Fix unreachable code handling to properly diagnose things like: throw x whatever() as being unreachable after the throw. Swift SVN r28678 | H9: 0a1f7c09dfc4af6b856b45058d20118039ef1b4d | I9: lib/Parse/ParseStmt.cpp | J9: (650, 3) | K9: lib/Parse/ParseStmt.cpp | L9: (90, 3) | M9: 5ead9764bd79b91ec973c4964488330f6aa69958 | N9: lib/Parse/ParseStmt.cpp | O9: (90, 28) | P9: lib/Parse/ParseStmt.cpp | R9: SourceLoc throwLoc = consumeToken(tok::kw_throw); | S9: auto parseTopLevelExpr = [&](Diag<> ID) { return (Tok.is(tok::kw_throw) ? parseExprThrow(ID) : parseExpr(ID)); }; | T9: [&](Diag<> ID) { return (Tok.is(tok::kw_throw) ? parseExprThrow(ID) : parseExpr(ID)); }
A10: 8 | B10: apple_swift | C10: https://github.com/apple/swift/commit/63dc900f91498a439738dee6de58e55629c01fd0 | D10: https://github.com/apple/swift/commit/bfbc6142c16b26c9839f8c5da3e329f1a06ea652 | E10: Pattern processing cleanups, NFC: Introduce a new Pattern::forEachVariable that takes a lambda and iterates over all the variables encompassed by the pattern (the ones found by collectVariables) and runs the lambda on it. Use this to implement collectVariables, so we only have one copy of the code. Convert several places to use this, removing a bunch of duplicated code for walking the pattern structure and extracting decls. Convert a few uses of collectVariables to forEachVariable, leading to more clear code without a temporary smallvector. Remove simplifyPatternTypes in CSApply.cpp, which is dead. Swift SVN r13545 | F10: rework CleanupIllFormedExpression some more. It now makes sure to find typevars hiding withing TypeLocs in expressions as well, and handles closures with a simpler model. Swift SVN r30026 | H10: 63dc900f91498a439738dee6de58e55629c01fd0 | I10: lib/Sema/TypeCheckConstraints.cpp | J10: (468, 9) | K10: lib/Sema/TypeCheckConstraints.cpp | L10: (467, 9) | M10: bfbc6142c16b26c9839f8c5da3e329f1a06ea652 | N10: lib/Sema/TypeCheckConstraints.cpp | O10: (838, 45) | P10: lib/Sema/TypeCheckConstraints.cpp | R10: closure->getParams()->collectVariables(Params); | S10: closure->getParams()->forEachVariable([&](VarDecl *VD) { if (VD->hasType()) { Type T = VD->getType(); if (cs) T = cs->simplifyType(T); if (T->hasTypeVariable()) { T = ErrorType::get(context); VD->setInvalid(); } VD->overwriteType(T); } else { VD->setType(ErrorType::get(context)); VD->setInvalid(); } }); | T10: [&](VarDecl *VD) { if (VD->hasType() && !VD->getType()->hasTypeVariable()) return; VD->overwriteType(ErrorType::get(context)); VD->setInvalid(); }
A11: 9 | B11: apple_swift | C11: https://github.com/apple/swift/commit/0a1f7c09dfc4af6b856b45058d20118039ef1b4d | D11: https://github.com/apple/swift/commit/e517ad91828ae7e552a4fb3dbb9ac28833d76091 | E11: Revert "Fix unreachable code handling to properly diagnose things like:" This reverts commit 28678. It broke the IDE/complete_exception.swift test. Swift SVN r28679 | F11: Fix unreachable code handling to properly diagnose things like: throw x whatever() as being unreachable after the throw. Swift SVN r28680 | H11: 0a1f7c09dfc4af6b856b45058d20118039ef1b4d | I11: lib/Parse/ParseStmt.cpp | J11: (650, 3) | K11: lib/Parse/ParseStmt.cpp | L11: (90, 3) | M11: e517ad91828ae7e552a4fb3dbb9ac28833d76091 | N11: lib/Parse/ParseStmt.cpp | O11: (90, 28) | P11: lib/Parse/ParseStmt.cpp | R11: SourceLoc throwLoc = consumeToken(tok::kw_throw); | S11: auto parseTopLevelExpr = [&](Diag<> ID) { return (Tok.is(tok::kw_throw) ? parseExprThrow(ID) : parseExpr(ID)); }; | T11: [&](Diag<> ID) { return (Tok.is(tok::kw_throw) ? parseExprThrow(ID) : parseExpr(ID)); }
A12: 10 | B12: eosforce_eosforce | C12: https://github.com/eosforce/eosforce/commit/cf6e9ca9685b1ec60c296af5fb87f141d1f27267 | D12: https://github.com/eosforce/eosforce/commit/7a084347167d752c4a9509e79ebad809f398bf75 | E12: Avoid tying up a thread to wait on transaction future. Also removes likely safe but undefined behavior. | F12: Revert to 1.8.1 version of signature recovery | H12: cf6e9ca9685b1ec60c296af5fb87f141d1f27267 | I12: plugins/producer_plugin/producer_plugin.cpp | J12: (358, 83) | K12: plugins/producer_plugin/producer_plugin.cpp | L12: (358, 91) | M12: 7a084347167d752c4a9509e79ebad809f398bf75 | N12: plugins/producer_plugin/producer_plugin.cpp | O12: (416, 45) | P12: plugins/producer_plugin/producer_plugin.cpp | R12: { if( trx->signing_keys_future.valid() ) trx->signing_keys_future.wait(); app().post(priority::low, [self, trx, persist_until_expired, next]() { self->process_incoming_transaction_async( trx, persist_until_expired, next ); }); } | S12: { app().post(priority::low, [self, trx{std::move(trx)}, persist_until_expired, next{std::move(next)}]() { self->process_incoming_transaction_async( trx, persist_until_expired, next ); }); } | T12: [self, trx{std::move(trx)}
A13: 11 | B13: apple_swift | C13: https://github.com/apple/swift/commit/54ccdc67e7df313a8cfa6cac461602f8b59cf06b | D13: https://github.com/apple/swift/commit/2ebb1234217498f4629ef5887b4cadcba3ed762a | E13: AssociatedTypeInference: Delay substitutions into abstract type witnesses until after they have been computed | F13: AssociatedTypeInference: Properly substitute into tentative type witnesses in inferAbstractTypeWitnesses() A regular type.subst() is not enough, because tentative type witnesses may contain type parameters, and we have to substitute them as well, recursively, e.g A := G<B>, B := G<C>, C := Never. Avoiding subst() here also eliminates a use case of the getSubstOptionsWithCurrentTypeWitnesses() hack. | H13: 54ccdc67e7df313a8cfa6cac461602f8b59cf06b | I13: lib/Sema/TypeCheckProtocolInference.cpp | J13: (854, 3) | K13: lib/Sema/TypeCheckProtocolInference.cpp | L13: (1168, 9) | M13: 2ebb1234217498f4629ef5887b4cadcba3ed762a | N13: lib/Sema/TypeCheckProtocolInference.cpp | O13: (1162, 11) | P13: lib/Sema/TypeCheckProtocolInference.cpp | R13: defaultType = defaultType.subst( QueryTypeSubstitutionMap{substitutions}, LookUpConformanceInModule(dc->getParentModule())); | S13: type = type.subst( [&](SubstitutableType *type) { if (type->isEqual(proto->getSelfInterfaceType())) return adoptee; return Type(); }, LookUpConformanceInModule(dc->getParentModule()), getSubstOptionsWithCurrentTypeWitnesses()); | T13: [&](SubstitutableType *type) { if (type->isEqual(proto->getSelfInterfaceType())) return adoptee; return Type(); }
A14: 12 | B14: eosforce_eosforce | C14: https://github.com/eosforce/eosforce/commit/0a95f98c3ca94dacce8bfa487b74d749fd6aaee1 | D14: https://github.com/eosforce/eosforce/commit/ae6142aca837cf39a8da19e5dde3f0711d3fa217 | E14: issue 3497 - add new config to limit the number of client connections accepted from any one host IP address | F14: merge eos | H14: 0a95f98c3ca94dacce8bfa487b74d749fd6aaee1 | I14: plugins/net_plugin/net_plugin.cpp | J14: (1976, 7) | K14: plugins/net_plugin/net_plugin.cpp | L14: (1978, 7) | M14: ae6142aca837cf39a8da19e5dde3f0711d3fa217 | N14: plugins/net_plugin/net_plugin.cpp | O14: (1989, 40) | P14: plugins/net_plugin/net_plugin.cpp | R14: acceptor->async_accept( *socket, [socket,this]( boost::system::error_code ec ) { if( !ec ) { uint32_t visitors = 0; for (auto &conn : connections) { if(conn->socket->is_open() && conn->peer_addr.empty()) { visitors++; } } if (num_clients != visitors) { ilog ("checking max client, visitors = ${v} num clients ${n}",("v",visitors)("n",num_clients)); num_clients = visitors; } if( max_client_count == 0 || num_clients < max_client_count ) { ++num_clients; connection_ptr c = std::make_shared<connection>( socket ); connections.insert( c ); start_session( c ); } else { elog( "Error max_client_count ${m} exceeded", ( "m", max_client_count) ); socket->close( ); } start_listen_loop(); } else { elog( "Error accepting connection: ${m}",( "m", ec.message() ) ); } }); | S14: acceptor->async_accept( *socket, [socket,this]( boost::system::error_code ec ) { if( !ec ) { uint32_t visitors = 0; uint32_t from_addr = 0; auto paddr = socket->remote_endpoint(ec).address().to_v4(); if (ec) { fc_elog(logger,"Error getting remote endpoint: ${m}",("m", ec.message())); return; } | T14: [socket,this]( boost::system::error_code ec ) { if( !ec ) { uint32_t visitors = 0; uint32_t from_addr = 0; auto paddr = socket->remote_endpoint(ec).address().to_v4()
... A165: 163 | B165: apple_swift | C165: https://github.com/apple/swift/commit/83f9ed43c38f65c96cd37dbde05252388276618f | D165: https://github.com/apple/swift/commit/aee4c83467b6cb0444daecf2d3bdb54e6baa83d3 | E165: [Driver] Don't assert when some files /don't/ get rebuilt but we still merge modules. ...or do anything else that depends on the compile commands that get skipped. Fix-up to rdar://problem/21129029 Swift SVN r29816 | F165: [Driver] Move markFinished to PerformJobsState, add logging. | H165: 83f9ed43c38f65c96cd37dbde05252388276618f | I165: lib/Driver/Compilation.cpp | J165: (194, 3) | K165: lib/Driver/Compilation.cpp | L165: (232, 3) | M165: aee4c83467b6cb0444daecf2d3bdb54e6baa83d3 | N165: lib/Driver/Compilation.cpp | O165: (395, 23) | P165: lib/Driver/Compilation.cpp | R165: unsigned InitialBlockingCount = State.BlockingCommands.size(); | S165: auto markFinished = [&] (const Job *Cmd) { State.FinishedCommands.insert(Cmd); auto BlockedIter = State.BlockingCommands.find(Cmd); if (BlockedIter != State.BlockingCommands.end()) { auto AllBlocked = std::move(BlockedIter->second); State.BlockingCommands.erase(BlockedIter); for (auto *Blocked : AllBlocked) scheduleCommandIfNecessaryAndPossible(Blocked); } }; | T165: [&] (const Job *Cmd) { State.FinishedCommands.insert(Cmd); auto BlockedIter = State.BlockingCommands.find(Cmd); if (BlockedIter != State.BlockingCommands.end()) { auto AllBlocked = std::move(BlockedIter->second); State.BlockingCommands.erase(BlockedIter); for (auto *Blocked : AllBlocked) State.scheduleCommandIfNecessaryAndPossible(Blocked); } }

Sheet csharp_shuffle
B1: name_with_owner | C1: insert url | D1: delete url | E1: replacement_msg | F1: delete_msg | G1: coding | H1: insert commit | I1: insert src file | J1: insert src start pos | K1: insert dst file | L1: insert dst start pos | M1: delete commit | N1: delete src file | O1: delete src start pos | P1: delete dst file | Q1: delete dst start pos | R1: insert src file content | S1: insert dst file content | T1: delete src file content
A2: 0 | B2: signumsoftware_framework | C2: https://github.com/signumsoftware/framework/commit/fe7d3ff8826e4f2dfae0a3085882f37f3d990d5c | D2: https://github.com/signumsoftware/framework/commit/eb1b533826ad0b786fe883bdabdda8823e246a1b | E2: elefantes (TFS CS 5989) | F2: Chequinazo entitygroups (TFS CS 6663) | G2: 機能変更 | H2: fe7d3ff8826e4f2dfae0a3085882f37f3d990d5c | I2: Signum.Engine.Extensions/Authorization/EntityGroupAuthLogic.cs | J2: (116, 21) | K2: Signum.Engine.Extensions/Authorization/EntityGroupAuthLogic.cs | L2: (118, 21) | M2: eb1b533826ad0b786fe883bdabdda8823e246a1b | N2: Signum.Engine.Extensions/Authorization/EntityGroupAuthLogic.cs | O2: (133, 54) | P2: Signum.Engine.Extensions/Authorization/EntityGroupAuthLogic.cs | R2: ident.AssertAllowed(TypeAllowedBasic.Create, false); | S2: Transaction.PreRealCommit += () => ident.AssertAllowed(TypeAllowedBasic.Create, false); | T2: () => ident.AssertAllowed(TypeAllowedBasic.Create, Database.UserInterface)
A3: 1 | B3: Ginger-Automation_Ginger | C3: https://github.com/Ginger-Automation/Ginger/commit/58eaea8958fe9336d1c1be586932b7785c4735dd | D3: https://github.com/Ginger-Automation/Ginger/commit/79a02f5bfbdc412bf3872a44306b5d3876b855b3 | E3: Changed async void to task | F3: making AccountReport Logger method async | G3: 機能変更 | H3: 58eaea8958fe9336d1c1be586932b7785c4735dd | I3: Ginger/GingerCoreNET/Run/RunListenerLib/CenteralizedExecutionLogger/AccountReportExecutionLogger.cs | J3: (98, 13) | K3: Ginger/GingerCoreNET/Run/RunListenerLib/CenteralizedExecutionLogger/AccountReportExecutionLogger.cs | L3: (101, 13) | M3: 79a02f5bfbdc412bf3872a44306b5d3876b855b3 | N3: Ginger/GingerCoreNET/Run/RunListenerLib/CenteralizedExecutionLogger/AccountReportExecutionLogger.cs | O3: (119, 22) | P3: Ginger/GingerCoreNET/Run/RunListenerLib/CenteralizedExecutionLogger/AccountReportExecutionLogger.cs | R3: BusinessFlowStartTask(businessFlow); | S3: Task.Run(() => BusinessFlowStartTask(businessFlow)); | T3: () => BusinessFlowStartTask(businessFlow)
A4: 2 | B4: AutoMapper_AutoMapper | C4: https://github.com/AutoMapper/AutoMapper/commit/d8ea3389e0104fad7787964e369a1973697a0445 | D4: https://github.com/AutoMapper/AutoMapper/commit/fb68f979b31f4875d636d18d0e6f6dbd6c74fc7b | E4: Array mapping simplified quite a bit | F4: Instead of using ToArray, which double maps. Find lenth and manualy set. | G4: 機能変更 | H4: d8ea3389e0104fad7787964e369a1973697a0445 | I4: src/AutoMapper/Mappers/ArrayMapper.cs | J4: (46, 13) | K4: src/AutoMapper/Mappers/ArrayMapper.cs | L4: (29, 13) | M4: fb68f979b31f4875d636d18d0e6f6dbd6c74fc7b | N4: src/AutoMapper/Mappers/ArrayMapper.cs | O4: (21, 34) | P4: src/AutoMapper/Mappers/ArrayMapper.cs | R4: return array as TDestination; | S4: return source.Cast<TSourceElement>() .Select(item => (TDestinationElement) itemContext.Map(item, null, typeof(TSourceElement), typeof(TDestinationElement))) .ToArray(); | T4: item => newItemFunc(item, itemContext)
A5: 3 | B5: Ginger-Automation_Ginger | C5: https://github.com/Ginger-Automation/Ginger/commit/58eaea8958fe9336d1c1be586932b7785c4735dd | D5: https://github.com/Ginger-Automation/Ginger/commit/79a02f5bfbdc412bf3872a44306b5d3876b855b3 | E5: Changed async void to task | F5: making AccountReport Logger method async | G5: 機能変更 | H5: 58eaea8958fe9336d1c1be586932b7785c4735dd | I5: Ginger/GingerCoreNET/Run/RunListenerLib/CenteralizedExecutionLogger/AccountReportExecutionLogger.cs | J5: (84, 13) | K5: Ginger/GingerCoreNET/Run/RunListenerLib/CenteralizedExecutionLogger/AccountReportExecutionLogger.cs | L5: (87, 13) | M5: 79a02f5bfbdc412bf3872a44306b5d3876b855b3 | N5: Ginger/GingerCoreNET/Run/RunListenerLib/CenteralizedExecutionLogger/AccountReportExecutionLogger.cs | O5: (105, 22) | P5: Ginger/GingerCoreNET/Run/RunListenerLib/CenteralizedExecutionLogger/AccountReportExecutionLogger.cs | R5: RunnerRunEndTask(gingerRunner); | S5: Task.Run(() => RunnerRunEndTask(gingerRunner)); | T5: () => RunnerRunEndTask(gingerRunner)
A6: 4 | B6: signumsoftware_framework | C6: https://github.com/signumsoftware/framework/commit/058f6bf4968cfb578ba5b41f6b1e9bc1b07f5341 | D6: https://github.com/signumsoftware/framework/commit/9880339ef979a380e89089dacaab00ec86c3c093 | E6: TryToken and QueryTokenDN builder with error message | F6: SubTokens(canAggregate) | G6: 機能変更 | H6: 058f6bf4968cfb578ba5b41f6b1e9bc1b07f5341 | I6: Signum.Web.Extensions/Chart/ChartClient.cs | J6: (225, 13) | K6: Signum.Web.Extensions/Chart/ChartClient.cs | L6: (203, 13) | M6: 9880339ef979a380e89089dacaab00ec86c3c093 | N6: Signum.Web.Extensions/Chart/ChartClient.cs | O6: (202, 82) | P6: Signum.Web.Extensions/Chart/ChartClient.cs | R6: return sb.ToHtml(); | S6: return helper.QueryTokenDNBuilder(chartToken, context, qd.QueryName, t => t.SubTokensChart(qd.Columns, chart.GroupResults && canAggregate)); | T6: t => t.SubTokensChart(qd.Columns, chart.GroupResults && canAggregate)
A7: 5 | B7: rsdn_CodeJam | C7: https://github.com/rsdn/CodeJam/commit/589249fd5376b80b5ce93518ddf4f015e1537303 | D7: https://github.com/rsdn/CodeJam/commit/82bf9506fe7e1b8c4587b048c9762888cc8210d3 | E7: Operator templates: comparison operators | F7: Cleanup | G7: 機能変更 | H7: 589249fd5376b80b5ce93518ddf4f015e1537303 | I7: Main/src/Arithmetic/Operators.cs | J7: (21, 3) | K7: Main/src/Arithmetic/Operators.cs | L7: (21, 3) | M7: 82bf9506fe7e1b8c4587b048c9762888cc8210d3 | N7: Main/src/Arithmetic/Operators.cs | O7: (22, 30) | P7: Main/src/Arithmetic/Operators.cs | R7: public static readonly Func<T, T, int> Compare = GetComparisonCallback<T>(); | S7: private static readonly Lazy<Func<T, T, int>> _compare = new Lazy<Func<T, T, int>>(() => Comparison<T>(), LazyMode); | T7: () => Comparison<T>()
A8: 6 | B8: RomSunZ_StockSharp | C8: https://github.com/RomSunZ/StockSharp/commit/49e74fe59b234e164dfb35ffae702aa359a17519 | D8: https://github.com/RomSunZ/StockSharp/commit/dadfd5b0efa28a36665a8904be4dfd172b767f53 | E8: FIX connector. Client side no longer use QuickFix. Version 4.2.73 | F8: FixServer. No longer use QuickFix. | G8: 誤検出 | H8: 49e74fe59b234e164dfb35ffae702aa359a17519 | I8: Connectors/Quik/Lua/LuaFixTransactionMessageAdapter.cs | J8: (108, 6) | K8: Connectors/Quik/Lua/LuaFixTransactionMessageAdapter.cs | L8: (172, 6) | M8: dadfd5b0efa28a36665a8904be4dfd172b767f53 | N8: Connectors/Quik/Lua/LuaFixTransactionMessageAdapter.cs | O8: (58, 85) | P8: Connectors/Quik/Lua/LuaFixTransactionMessageAdapter.cs | R8: var condition = new QuikOrderCondition { Type = (QuikOrderConditionTypes)fixMsg.Type.Obj, Result = fixMsg.IsSetResult() ? (QuikOrderConditionResults?)fixMsg.Result.Obj : null, StopPriceCondition = (QuikStopPriceConditions)fixMsg.StopPriceCondition.Obj, StopPrice = fixMsg.IsSetStopPx() ? fixMsg.StopPx.Obj : (decimal?)null, StopLimitPrice = fixMsg.IsSetStopLimitPrice() ? fixMsg.StopLimitPrice.Obj : (decimal?)null, IsMarketStopLimit = fixMsg.IsSetIsMarketStopLimit() ? fixMsg.IsMarketStopLimit.Obj : (bool?)null, ConditionOrderId = fixMsg.IsSetConditionOrderId() ? fixMsg.ConditionOrderId.Obj : (long?)null, ConditionOrderSide = (Sides)fixMsg.ConditionOrderSide.Obj, ConditionOrderPartiallyMatched = fixMsg.IsSetConditionOrderPartiallyMatched() ? fixMsg.ConditionOrderPartiallyMatched.Obj : (bool?)null, ConditionOrderUseMatchedBalance = fixMsg.IsSetConditionOrderUseMatchedBalance() ? fixMsg.ConditionOrderUseMatchedBalance.Obj : (bool?)null, LinkedOrderPrice = fixMsg.IsSetLinkedOrderPrice() ? fixMsg.LinkedOrderPrice.Obj : (decimal?)null, LinkedOrderCancel = fixMsg.LinkedOrderCancel.Obj, Offset = fixMsg.IsSetOffset() ? fixMsg.Offset.Obj.ToUnit() : null, Spread = fixMsg.IsSetStopSpread() ? fixMsg.StopSpread.Obj.ToUnit() : null, IsMarketTakeProfit = fixMsg.IsSetIsMarketTakeProfit() ? fixMsg.IsMarketTakeProfit.Obj : (bool?)null, }; | S8: var executions = reader.ReadExecutionMessage(Session, SessionHolder.UtcOffset, tag => { switch ((QuikFixTags)tag) { case QuikFixTags.Type: type = reader.ReadInt(); return true; case QuikFixTags.StopPriceCondition: stopPriceCondition = reader.ReadInt(); return true; case QuikFixTags.ConditionOrderSide: conditionOrderSide = reader.ReadInt(); return true; case QuikFixTags.LinkedOrderCancel: linkedOrderCancel = reader.ReadBool(); return true; case QuikFixTags.Result: result = reader.ReadInt(); return true; case QuikFixTags.OtherSecurityCode: otherSecurityCode = reader.ReadString(); return true; case QuikFixTags.StopPrice: stopPrice = reader.ReadDecimal(); return true; case QuikFixTags.StopLimitPrice: stopLimitPrice = reader.ReadDecimal(); return true; case QuikFixTags.IsMarketStopLimit: isMarketStopLimit = reader.ReadBool(); return true; case QuikFixTags.ActiveTimeFrom: activeTimeFrom = reader.ReadDateTime().ApplyTimeZone(SessionHolder.UtcOffset); return true; case QuikFixTags.ActiveTimeTo: activeTimeTo = reader.ReadDateTime().ApplyTimeZone(SessionHolder.UtcOffset); return true; case QuikFixTags.ConditionOrderId: conditionOrderId = reader.ReadLong(); return true; case QuikFixTags.ConditionOrderPartiallyMatched: conditionOrderPartiallyMatched = reader.ReadBool(); return true; case QuikFixTags.ConditionOrderUseMatchedBalance: conditionOrderUseMatchedBalance = reader.ReadBool(); return true; case QuikFixTags.LinkedOrderPrice: linkedOrderPrice = reader.ReadDecimal(); return true; case QuikFixTags.Offset: offset = reader.ReadString(); return true; case QuikFixTags.StopSpread: stopSpread = reader.ReadString(); return true; case QuikFixTags.IsMarketTakeProfit: isMarketTakeProfit = reader.ReadBool(); return true; default: return false; } }); | T8: tag => { switch ((QuikFixTags)tag) { case QuikFixTags.Type: type = reader.ReadInt(); return true; case QuikFixTags.StopPriceCondition: stopPriceCondition = reader.ReadInt(); return true; case QuikFixTags.ConditionOrderSide: conditionOrderSide = reader.ReadInt(); return true; case QuikFixTags.LinkedOrderCancel: linkedOrderCancel = reader.ReadBool(); return true; case QuikFixTags.Result: result = reader.ReadInt(); return true; case QuikFixTags.OtherSecurityCode: otherSecurityCode = reader.ReadString(); return true; case QuikFixTags.StopPrice: stopPrice = reader.ReadDecimal(); return true; case QuikFixTags.StopLimitPrice: stopLimitPrice = reader.ReadDecimal(); return true; case QuikFixTags.IsMarketStopLimit: isMarketStopLimit = reader.ReadBool(); return true; case QuikFixTags.ActiveTimeFrom: activeTimeFrom = reader.ReadDateTime().ApplyTimeZone(SessionHolder.UtcOffset); return true; case QuikFixTags.ActiveTimeTo: activeTimeTo = reader.ReadDateTime().ApplyTimeZone(SessionHolder.UtcOffset); return true; case QuikFixTags.ConditionOrderId: conditionOrderId = reader.ReadLong(); return true; case QuikFixTags.ConditionOrderPartiallyMatched: conditionOrderPartiallyMatched = reader.ReadBool(); return true; case QuikFixTags.ConditionOrderUseMatchedBalance: conditionOrderUseMatchedBalance = reader.ReadBool(); return true; case QuikFixTags.LinkedOrderPrice: linkedOrderPrice = reader.ReadDecimal(); return true; case QuikFixTags.Offset: offset = reader.ReadString(); return true; case QuikFixTags.StopSpread: stopSpread = reader.ReadString(); return true; case QuikFixTags.IsMarketTakeProfit: isMarketTakeProfit = reader.ReadBool(); return true; default: return false; } }
A9: 7 | B9: signumsoftware_framework | C9: https://github.com/signumsoftware/framework/commit/d5e0bd110c5688280b0ba8565b271f63014e1b4c | D9: https://github.com/signumsoftware/framework/commit/40118cf0ba313e0aaeefb8a7f4a8478a40cc81bc | E9: dqm.RegisterQuery | F9: remove FileRepositoryEntity and add FileTypeAlgorithm.GetPrefixPair lambda instead to maximize flexibility | G9: 誤検出 | H9: d5e0bd110c5688280b0ba8565b271f63014e1b4c | I9: Signum.Engine.Extensions/Files/FilePathLogic.cs | J9: (50, 17) | K9: Signum.Engine.Extensions/Files/FilePathLogic.cs | L9: (50, 17) | M9: 40118cf0ba313e0aaeefb8a7f4a8478a40cc81bc | N9: Signum.Engine.Extensions/Files/FilePathLogic.cs | O9: (96, 65) | P9: Signum.Engine.Extensions/Files/FilePathLogic.cs | R9: dqm[typeof(FileRepositoryDN)] = (from r in Database.Query<FileRepositoryDN>() select new { Entity = r, r.Id, r.Name, r.Active, r.PhysicalPrefix, r.WebPrefix }).ToDynamic(); | S9: dqm.RegisterQuery(typeof(FileRepositoryDN), () => from r in Database.Query<FileRepositoryDN>() select new { Entity = r, r.Id, r.Name, r.Active, r.PhysicalPrefix, r.WebPrefix }); | T9: () => from r in Database.Query<FileRepositoryEntity>() select new { Entity = r, r.Id, r.Name, r.Active, r.PhysicalPrefix, r.WebPrefix }
A10: 8 | B10: Ginger-Automation_Ginger | C10: https://github.com/Ginger-Automation/Ginger/commit/58eaea8958fe9336d1c1be586932b7785c4735dd | D10: https://github.com/Ginger-Automation/Ginger/commit/79a02f5bfbdc412bf3872a44306b5d3876b855b3 | E10: Changed async void to task | F10: making AccountReport Logger method async | G10: 機能変更 | H10: 58eaea8958fe9336d1c1be586932b7785c4735dd | I10: Ginger/GingerCoreNET/Run/RunListenerLib/CenteralizedExecutionLogger/AccountReportExecutionLogger.cs | J10: (187, 13) | K10: Ginger/GingerCoreNET/Run/RunListenerLib/CenteralizedExecutionLogger/AccountReportExecutionLogger.cs | L10: (190, 13) | M10: 79a02f5bfbdc412bf3872a44306b5d3876b855b3 | N10: Ginger/GingerCoreNET/Run/RunListenerLib/CenteralizedExecutionLogger/AccountReportExecutionLogger.cs | O10: (208, 22) | P10: Ginger/GingerCoreNET/Run/RunListenerLib/CenteralizedExecutionLogger/AccountReportExecutionLogger.cs | R10: ActionStartTask(action); | S10: Task.Run(() => ActionStartTask(action)); | T10: () => ActionStartTask(action)
A11: 9 | B11: Ginger-Automation_Ginger | C11: https://github.com/Ginger-Automation/Ginger/commit/58eaea8958fe9336d1c1be586932b7785c4735dd | D11: https://github.com/Ginger-Automation/Ginger/commit/79a02f5bfbdc412bf3872a44306b5d3876b855b3 | E11: Changed async void to task | F11: making AccountReport Logger method async | G11: 機能変更 | H11: 58eaea8958fe9336d1c1be586932b7785c4735dd | I11: Ginger/GingerCoreNET/Run/RunListenerLib/CenteralizedExecutionLogger/AccountReportExecutionLogger.cs | J11: (127, 13) | K11: Ginger/GingerCoreNET/Run/RunListenerLib/CenteralizedExecutionLogger/AccountReportExecutionLogger.cs | L11: (130, 13) | M11: 79a02f5bfbdc412bf3872a44306b5d3876b855b3 | N11: Ginger/GingerCoreNET/Run/RunListenerLib/CenteralizedExecutionLogger/AccountReportExecutionLogger.cs | O11: (148, 22) | P11: Ginger/GingerCoreNET/Run/RunListenerLib/CenteralizedExecutionLogger/AccountReportExecutionLogger.cs | R11: await ActivityStartTask(activity); | S11: Task.Run(() => ActivityStartTask(activity)); | T11: () => ActivityStartTask(activity)
A12: 10 | B12: GridProtectionAlliance_gsf | C12: https://github.com/GridProtectionAlliance/gsf/commit/3f893ab0c9f494a7c017d1d81ec89d95c9824243 | D12: https://github.com/GridProtectionAlliance/gsf/commit/8335962581b65df64d12ab02b663457a074daa2a | E12: PIAdapters: Updated PI adapters to operate in a mode such that high-volume updates will be handled through multiple connections. git-tfs-id: [https://tfs.codeplex.com/tfs/TFS07]$/gsf/Main;C90732 | F12: PIAdapters: Moved all PI-SDK code to the STA operations thread. git-tfs-id: [https://tfs.codeplex.com/tfs/TFS07]$/gsf/Main;C90790 | G12: 機能変更 | H12: 3f893ab0c9f494a7c017d1d81ec89d95c9824243 | I12: Source/Libraries/Adapters/PIAdapters/PIOutputAdapter.cs | J12: (538, 33) | K12: Source/Libraries/Adapters/PIAdapters/PIOutputAdapter.cs | L12: (449, 25) | M12: 8335962581b65df64d12ab02b663457a074daa2a | N12: Source/Libraries/Adapters/PIAdapters/PIOutputAdapter.cs | O12: (510, 44) | P12: Source/Libraries/Adapters/PIAdapters/PIOutputAdapter.cs | R12: point.Data.UpdateValue(measurement.AdjustedValue, new DateTime(measurement.Timestamp).ToLocalTime()); | S12: connection.Execute(server => point.Data.UpdateValue(value, timestamp)); | T12: server => point.Data.UpdateValues(values)
A13: 11 | B13: GridProtectionAlliance_gsf | C13: https://github.com/GridProtectionAlliance/gsf/commit/5ea0dd4cf2052b91f62de9571271c083299201ae | D13: https://github.com/GridProtectionAlliance/gsf/commit/01fa19f073082541954aa85bad297354d6a22912 | E13: GSF.Web: Modified AuthenticationHandler to properly handle authentication and redirect behavior. | F13: GSF.Web: Added logout endpoint for applications using AuthenticationHandler. | G13: 機能変更 | H13: 5ea0dd4cf2052b91f62de9571271c083299201ae | I13: Source/Libraries/GSF.Web/Security/AuthenticationHandler.cs | J13: (162, 13) | K13: Source/Libraries/GSF.Web/Security/AuthenticationHandler.cs | L13: (158, 13) | M13: 01fa19f073082541954aa85bad297354d6a22912 | N13: Source/Libraries/GSF.Web/Security/AuthenticationHandler.cs | O13: (181, 29) | P13: Source/Libraries/GSF.Web/Security/AuthenticationHandler.cs | R13: return base.ApplyResponseChallengeAsync(); | S13: return Task.Run(() => { SecurityPrincipal securityPrincipal = Request.User as SecurityPrincipal; // If the user fails to authenticate, adjust the HTTP response if (!IsAnonymousResource(Request.Path.Value) && securityPrincipal?.Identity.IsAuthenticated != true) { string authFailRedirect = Request.Query["AuthFailRedirect"] ?? "True"; // Determine whether the authentication failure should redirect to login page if (authFailRedirect.ParseBoolean()) Response.Redirect(Options.LoginPage); else Response.StatusCode = (int)HttpStatusCode.Unauthorized; Response.ReasonPhrase = SecurityPrincipal.GetFailureReasonPhrase(securityPrincipal, AuthorizationType); return true; } return false; }); | T13: () => { SecurityPrincipal securityPrincipal = Request.User as SecurityPrincipal; string urlPath = Request.Path.Value; // If request is for an anonymous resource or user is properly authenticated, allow // request to propagate through the Owin pipeline if (Options.IsAnonymousResource(urlPath) || securityPrincipal?.Identity.IsAuthenticated == true) return false; // Let pipeline continue // Abort pipeline with appropriate response if (Options.IsAuthFailureRedirectResource(urlPath) && !IsAjaxCall()) { byte[] pathBytes; string base64Path, encodedPath, referrer = null; if (Request.Headers.TryGetValue("Referer", out string[] values) && values.Length == 1) { pathBytes = Encoding.UTF8.GetBytes(values[0]); base64Path = Convert.ToBase64String(pathBytes); encodedPath = WebUtility.UrlEncode(base64Path); referrer = $"&referrer={encodedPath}"; } string urlQueryString = Request.QueryString.HasValue ? "?" + Request.QueryString.Value : ""; pathBytes = Encoding.UTF8.GetBytes(urlPath + urlQueryString); base64Path = Convert.ToBase64String(pathBytes); encodedPath = WebUtility.UrlEncode(base64Path); Response.Redirect($"{Options.LoginPage}?redir={encodedPath}{referrer}"); } else { Response.StatusCode = (int)HttpStatusCode.Unauthorized; } // Add current identity to unauthorized response header string currentIdentity = securityPrincipal?.Identity.Name ?? "anonymous"; object value; if (Request.Environment.TryGetValue("OriginalPrincipal", out value)) { IPrincipal originalPrincpal = value as IPrincipal; if ((object)originalPrincpal != null && (object)originalPrincpal.Identity != null) currentIdentity = AdjustedUserName(originalPrincpal.Identity.Name); } bool debuggable = Common.GetApplicationType() != ApplicationType.Web && AssemblyInfo.EntryAssembly.Debuggable; Response.Headers.Add("CurrentIdentity", new[] { currentIdentity }); Response.ReasonPhrase = SecurityPrincipal.GetFailureReasonPhrase(securityPrincipal, AuthorizationHeader?.Scheme, debuggable); string failureReason = SecurityPrincipal.GetFailureReasonPhrase(securityPrincipal, AuthorizationHeader?.Scheme, true); Log.Publish(MessageLevel.Info, "AuthenticationFailure", $"Failed to authenticate {currentIdentity} for {Request.Path}: {failureReason}"); return true; // Abort pipeline }
... A59: 57 | B59: gregsdennis_Manatee.Trello | C59: https://github.com/gregsdennis/Manatee.Trello/commit/75018ca467c63c59e64759c6e56a7d252196d37b | D59: https://github.com/gregsdennis/Manatee.Trello/commit/857eb00cebe8ba989499174bfc00fe3e5622b075 | E59: initial efforts | F59: added board background collection | G59: 機能削除 | H59: 75018ca467c63c59e64759c6e56a7d252196d37b | I59: Manatee.Trello.UnitTests/DevTest.cs | J59: (26, 6) | K59: Manatee.Trello.UnitTests/DevTest.cs | L59: (36, 5) | M59: 857eb00cebe8ba989499174bfc00fe3e5622b075 | N59: Manatee.Trello.UnitTests/DevTest.cs | O59: (35, 21) | P59: Manatee.Trello.UnitTests/DevTest.cs | R59: Console.WriteLine($"before: {Environment.GetEnvironmentVariable("TEST_VAR", EnvironmentVariableTarget.User)}"); | S59: card.Updated += (c, list) => OutputCollection("properties", list); | T59: (c, list) => OutputCollection("properties", list)
A60: 58 | B60: openrails_openrails | C60: https://github.com/openrails/openrails/commit/021a2a635626b7c7ba09ea1a2893266b222e1dd0 | D60: https://github.com/openrails/openrails/commit/537214d61aacc637254915299a4bc6dbacb49870 | E60: Preliminary C# scripting framework and scriptable train control system. git-svn-id: http://svn.uktrainsim.com/svn/openrails/trunk@1970 a9f3cfff-6c41-7446-b0ca-052bd761e6eb | F60: A fix in TCS signalling and crash git-svn-id: http://svn.uktrainsim.com/svn/openrails/trunk@1979 a9f3cfff-6c41-7446-b0ca-052bd761e6eb | H60: 021a2a635626b7c7ba09ea1a2893266b222e1dd0 | I60: Source/RunActivity/RollingStock/TrainControlSystem.cs | J60: (191, 25) | K60: Source/RunActivity/RollingStock/TrainControlSystem.cs | L60: (245, 25) | M60: 537214d61aacc637254915299a4bc6dbacb49870 | N60: Source/RunActivity/RollingStock/TrainControlSystem.cs | O60: (247, 58) | P60: Source/RunActivity/RollingStock/TrainControlSystem.cs | R60: nextSpeedLimitMpS = MSTSLocomotive.Train.IsFreight ? SignalSpeed.speed_freight : SignalSpeed.speed_pass; | S60: Script.NextSignalSpeedLimitMpS = () => Locomotive.Train.IsFreight ? SignalSpeed.speed_freight : SignalSpeed.speed_pass; | T60: () => Locomotive.Train.IsFreight ? SignalSpeed.speed_freight : SignalSpeed.speed_pass
A61: 59 | B61: RomSunZ_StockSharp | C61: https://github.com/RomSunZ/StockSharp/commit/f90e77cc6c5ee9b17ea0722d9b7806290e843a4e | D61: https://github.com/RomSunZ/StockSharp/commit/14968937de25184c06bf00e666c589062457a35f | E61: Hydra. Connector's tasks small refactoring. | F61: prev commit fixes. | H61: f90e77cc6c5ee9b17ea0722d9b7806290e843a4e | I61: Hydra/Plugins/Blackwood/BlackwoodTask.cs | J61: (140, 4) | K61: Hydra/Plugins/Blackwood/BlackwoodTask.cs | L61: (140, 4) | M61: 14968937de25184c06bf00e666c589062457a35f | N61: Hydra/Plugins/Blackwood/BlackwoodTask.cs | O61: (141, 85) | P61: Hydra/Plugins/Blackwood/BlackwoodTask.cs | R61: return new MarketDataConnector<BlackwoodTrader>(EntityRegistry.Securities, this, CreateConnector); | S61: return new MarketDataConnector<BlackwoodTrader>(EntityRegistry.Securities, this, () => new BlackwoodTrader { HistoricalDataAddress = _settings.HistoricalDataAddress, MarketDataAddress = _settings.MarketDataAddress, Login = _settings.Login, Password = _settings.Password.To<string>(), }); | T61: () => new BlackwoodTrader { HistoricalDataAddress = _settings.HistoricalDataAddress, MarketDataAddress = _settings.MarketDataAddress, Login = _settings.Login, Password = _settings.Password.To<string>(), }
A62: 60 | B62: Ginger-Automation_Ginger | C62: https://github.com/Ginger-Automation/Ginger/commit/a57b53c679f1e45638a6fec2dfff664fc71ed1b9 | D62: https://github.com/Ginger-Automation/Ginger/commit/9b801948ee394f20efa5725bcbdab165622e98f6 | E62: working feature. need some little checks to be looked in deapth. | F62: Enhancing SR Find usage page to be async | H62: a57b53c679f1e45638a6fec2dfff664fc71ed1b9 | I62: Ginger/Ginger/AutomatePageLib/AddActionMenu/SharedRepositoryLib/RepositoryItemUsagePage.xaml.cs | J62: (299, 33) | K62: Ginger/Ginger/AutomatePageLib/AddActionMenu/SharedRepositoryLib/RepositoryItemUsagePage.xaml.cs | L62: (298, 33) | M62: 9b801948ee394f20efa5725bcbdab165622e98f6 | N62: Ginger/Ginger/AutomatePageLib/AddActionMenu/SharedRepositoryLib/RepositoryItemUsagePage.xaml.cs | O62: (300, 56) | P62: Ginger/Ginger/AutomatePageLib/AddActionMenu/SharedRepositoryLib/RepositoryItemUsagePage.xaml.cs | R62: mRepoItem.UpdateInstance(usage.UsageItem, usage.SelectedItemPart, usage.HostActivity); | S62: this.Dispatcher.Invoke(() => mRepoItem.UpdateInstance(usage.UsageItem, usage.SelectedItemPart, usage.HostActivity)); | T62: () => mRepoItem.UpdateInstance(usage.UsageItem, usage.SelectedItemPart, usage.HostActivity)
A63: 61 | B63: mob-sakai_ParticleEffectForUGUI | C63: https://github.com/mob-sakai/ParticleEffectForUGUI/commit/0d4a5875d130c74a573f713b46e109b7affefb21 | D63: https://github.com/mob-sakai/ParticleEffectForUGUI/commit/b76bf5a5ad378c3c4b16bcf08d21337757557101 | E63: 3.0.0-preview.19 # [3.0.0-preview.19](https://github.com/mob-sakai/ParticleEffectForUGUI/compare/v3.0.0-preview.18...v3.0.0-preview.19) (2020-08-28) ### Bug Fixes * baking camera settings for camera space ([436c5e4](https://github.com/mob-sakai/ParticleEffectForUGUI/commit/436c5e47f75c3e167dcd77c188847e9d7d6ea68d)) * fix local simulation ([7add9de](https://github.com/mob-sakai/ParticleEffectForUGUI/commit/7add9defb70be29ddbe536d854591c2e0d9e83fa)) ### Features * add menu to create UIParticle ([2fa1843](https://github.com/mob-sakai/ParticleEffectForUGUI/commit/2fa18431f0c8c4aeadfdd1cb98eeeef5ac6970a0)) * add play/pause/stop api ([f09a386](https://github.com/mob-sakai/ParticleEffectForUGUI/commit/f09a386bc59fbab8143f7f0b814c8684aea7f27c)) * support for changing rendering orders ([745d4a5](https://github.com/mob-sakai/ParticleEffectForUGUI/commit/745d4a598846b3e77d1071433079fdd5140921a8)) * Support for child ParticleSystem rendering ([4ee90be](https://github.com/mob-sakai/ParticleEffectForUGUI/commit/4ee90be17c68bf405f81f432615a3eebaa022366)) * UIParticle for trail is no longer needed ([466e43c](https://github.com/mob-sakai/ParticleEffectForUGUI/commit/466e43cf931d211907419f804a90776a0d9f4906)) ### BREAKING CHANGES * The child UIParticle is no longer needed. | F63: feat: support 8+ materials Instead of one CanvasRenderer with submeshes, render with multiple CanvasRenderers. This feature allows the number of materials to be unlimited. close #122, close #152, close #186 | H63: 0d4a5875d130c74a573f713b46e109b7affefb21 | I63: Scripts/UIParticle.cs | J63: (241, 13) | K63: Scripts/UIParticle.cs | L63: (228, 13) | M63: b76bf5a5ad378c3c4b16bcf08d21337757557101 | N63: Scripts/UIParticle.cs | O63: (442, 32) | P63: Scripts/UIParticle.cs | R63: CheckMaterials(); | S63: particles.Exec(p => p.GetComponent<ParticleSystemRenderer>().enabled = true); | T63: p => p.GetComponent<ParticleSystemRenderer>().enabled = true
A64: 62 | B64: mikebridge_Liquid.NET | C64: https://github.com/mikebridge/Liquid.NET/commit/eb1884ea62bde7a263908440de2556dc0da63309 | D64: https://github.com/mikebridge/Liquid.NET/commit/3f10c3eb157c8daed8914fa8fc685e0d6aa1d389 | E64: more shopify filters | F64: minor cleanup in filters | H64: eb1884ea62bde7a263908440de2556dc0da63309 | I64: Liquid.NET/src/Filters/Strings/UpCaseFilter.cs | J64: (13, 13) | K64: Liquid.NET/src/Filters/Strings/UpCaseFilter.cs | L64: (10, 13) | M64: 3f10c3eb157c8daed8914fa8fc685e0d6aa1d389 | N64: Liquid.NET/src/Filters/Strings/UpCaseFilter.cs | O64: (11, 86) | P64: Liquid.NET/src/Filters/Strings/UpCaseFilter.cs | R64: return new StringValue(val.ToUpper()); | S64: return StringResult.Eval(objectExpression, x => x.ToLower()); | T64: x => x.ToUpper()
A65: 63 | B65: Ginger-Automation_Ginger | C65: https://github.com/Ginger-Automation/Ginger/commit/b3901ca01150b9c5e333989eab999d2a71c73af6 | D65: https://github.com/Ginger-Automation/Ginger/commit/71c805dce882c1ce7e165b5fedcca33d740f92a7 | E65: Replaced list.Where(condition).FirstOrDefault() with list.FirstOrDefault(condition) | F65: Code changes for Copy paste fixes, Defect no= 26002 | H65: b3901ca01150b9c5e333989eab999d2a71c73af6 | I65: Ginger/GingerCore/GeneralLib/General.cs | J65: (417, 21) | K65: Ginger/GingerCore/GeneralLib/General.cs | L65: (417, 21) | M65: 71c805dce882c1ce7e165b5fedcca33d740f92a7 | N65: Ginger/GingerCore/GeneralLib/General.cs | O65: (437, 112) | P65: Ginger/GingerCore/GeneralLib/General.cs | R65: if ((from x in WorkSpace.Instance.SolutionRepository.GetAllRepositoryItems<ApplicationPOMModel>() where x.Name == resultValue select x).SingleOrDefault() != null) { Reporter.ToUser(eUserMsgKey.StaticWarnMessage, "POM Model with same name: " + "'" + resultValue + "'" + " already exists."); return true; } | S65: if (WorkSpace.Instance.SolutionRepository.GetAllRepositoryItems<ApplicationPOMModel>().Any(x=> x.Name == resultValue)) { Reporter.ToUser(eUserMsgKey.StaticWarnMessage, "POM Model with same name: " + "'" + resultValue + "'" + " already exists."); return true; } | T65: x=> x.Name == resultValue
A66: 64 | B66: warappa_XamlCSS | C66: https://github.com/warappa/XamlCSS/commit/1b81189ad9445483a7c2b028052b5d8039c08f25 | D66: https://github.com/warappa/XamlCSS/commit/26baa6dd2898a30cf814a69f63ae51af3831aadf | E66: Performance, exact tracing with stopwatch | F66: Remove Measure(...) calls for better performance | H66: 1b81189ad9445483a7c2b028052b5d8039c08f25 | I66: XamlCSS.WPF/StyleService.cs | J66: (299, 21) | K66: XamlCSS.WPF/StyleService.cs | L66: (342, 29) | M66: 26baa6dd2898a30cf814a69f63ae51af3831aadf | N66: XamlCSS.WPF/StyleService.cs | O66: (451, 60) | P66: XamlCSS.WPF/StyleService.cs | R66: value = TypeDescriptor.GetConverter(type)?.ConvertFromInvariantString(valueString) ?? value; | S66: value = "GetConverter".Measure(() => TypeDescriptor.GetConverter(type)?.ConvertFromInvariantString(valueString) ?? value); | T66: () => TypeDescriptor.GetConverter(type)?.ConvertFromInvariantString(valueString) ?? value
A67: 65 | B67: ArcadeRenegade_SidebarDiagnostics | C67: https://github.com/ArcadeRenegade/SidebarDiagnostics/commit/2b3dc640c6b4ff8e1ad8a68041ef2b078b2bf50c | D67: https://github.com/ArcadeRenegade/SidebarDiagnostics/commit/d4b4dd870cf9ffd67fa824d51fe3ceeadea8eef7 | E67: During the loading sequence, replaced delegate.BeginInvoke with Task.Run instead. | F67: Loading widget is now removed on sidebar ready rather than just hidden | H67: 2b3dc640c6b4ff8e1ad8a68041ef2b078b2bf50c | I67: SidebarDiagnostics/Sidebar.xaml.cs | J67: (92, 13) | K67: SidebarDiagnostics/Sidebar.xaml.cs | L67: (95, 13) | M67: d4b4dd870cf9ffd67fa824d51fe3ceeadea8eef7 | N67: SidebarDiagnostics/Sidebar.xaml.cs | O67: (95, 28) | P67: SidebarDiagnostics/Sidebar.xaml.cs | R67: new BindModelHandler(BindModel).BeginInvoke(null, null); | S67: await Task.Run(async () => { await BindModel(); }); | T67: async () => { await BindModel(); }
A68: 66 | B68: signumsoftware_framework | C68: https://github.com/signumsoftware/framework/commit/2f429cedfc8a45053cc6398c790bdf9f230d96eb | D68: https://github.com/signumsoftware/framework/commit/ce1be332034042b46828ed0e08ab4203b0ea3f01 | E68: (TFS CS 4096) | F68: .Net Framework 4.0 y Visual Studio 2010 (TFS CS 6278) | H68: 2f429cedfc8a45053cc6398c790bdf9f230d96eb | I68: Signum.Windows.Extensions/Authorization/AuthClient.cs | J68: (39, 21) | K68: Signum.Windows.Extensions/Authorization/AuthClient.cs | L68: (39, 21) | M68: ce1be332034042b46828ed0e08ab4203b0ea3f01 | N68: Signum.Windows.Extensions/Authorization/AuthClient.cs | O68: (38, 43) | P68: Signum.Windows.Extensions/Authorization/AuthClient.cs | R68: typeRules = Server.Service<ITypeAuthServer>().AuthorizedTypes(); | S68: typeRules = Server.Return((ITypeAuthServer s)=>s.AuthorizedTypes()); | T68: (ITypeAuthServer s) => s.AuthorizedTypes()
A69: 67 | B69: AutoMapper_AutoMapper | C69: https://github.com/AutoMapper/AutoMapper/commit/89a331c087dafcf64d0e867f348b9923732dc864 | D69: https://github.com/AutoMapper/AutoMapper/commit/793918a0b0b6b7f0dadc1a807d06ee2cdbea695a | E69: massive updatee | F69: Got config to work with current profile | H69: 89a331c087dafcf64d0e867f348b9923732dc864 | I69: src/UnitTests/ConvensionTest.cs | J69: (29, 13) | K69: src/UnitTests/ConvensionTest.cs | L69: (29, 13) | M69: 793918a0b0b6b7f0dadc1a807d06ee2cdbea695a | N69: src/UnitTests/ConvensionTest.cs | O69: (29, 31) | P69: src/UnitTests/ConvensionTest.cs | R69: Mapper.AddMemberConvention().PropertyPostfix("Transfer"); | S69: Mapper.AddMemberConvention().AddName<PrePostfixName>(_ => _.SetPostfixs("Transfer").SetPrefixs("Trans")); | T69: cfg => { cfg.RecognizePostfixes("Transfer", "Trans"); }
A70: 68 | B70: microsoft_qsharp-compiler | C70: https://github.com/microsoft/qsharp-compiler/commit/ba557ab7df7cd53e44a4fac0671f7783b9f607db | D70: https://github.com/microsoft/qsharp-compiler/commit/f6e34ff33467d44238c9432ebdb2d80aae32616b | E70: Order built-in rewrite steps according to their priority (#421) | F70: Do not serialize syntax tree if compilation failed (#1408) | H70: ba557ab7df7cd53e44a4fac0671f7783b9f607db | I70: src/QsCompiler/Compiler/CompilationLoader.cs | J70: (485, 17) | K70: src/QsCompiler/Compiler/CompilationLoader.cs | L70: (497, 17) | M70: f6e34ff33467d44238c9432ebdb2d80aae32616b | N70: src/QsCompiler/Compiler/CompilationLoader.cs | O70: (614, 68) | P70: src/QsCompiler/Compiler/CompilationLoader.cs | R70: this.CompilationOutput = ExecuteAsAtomicTransformation(rewriteStep, ref this.CompilationStatus.TreeTrimming); | S70: steps.Add((rewriteStep.Priority, () => ExecuteAsAtomicTransformation(rewriteStep, ref this.CompilationStatus.TreeTrimming))); | T70: () => this.ExecuteAsAtomicTransformation(rewriteStep, ref this.compilationStatus.ConvertClassicalControl)
A71: 69 | B71: signumsoftware_framework | C71: https://github.com/signumsoftware/framework/commit/3940517113efa0ffae815c9c031af8e77869f9f2 | D71: https://github.com/signumsoftware/framework/commit/4a65d9cce9b1c59dd8cc14bab51d2aef9c8c6078 | E71: ImportExportHelp | F71: initial Help version | H71: 3940517113efa0ffae815c9c031af8e77869f9f2 | I71: Signum.Engine.Extensions/Help/HelpXml.cs | J71: (120, 17) | K71: Signum.Engine.Extensions/Help/HelpXml.cs | L71: (121, 17) | M71: 4a65d9cce9b1c59dd8cc14bab51d2aef9c8c6078 | N71: Signum.Engine.Extensions/Help/HelpXml.cs | O71: (112, 51) | P71: Signum.Engine.Extensions/Help/HelpXml.cs | R71: entity.Description = element.Element(_Description).Value; | S71: element.Element(_Description).TryDo(d => entity.Description = d.Value); | T71: d => entity.Description = d.Value
... A326: 324 | B326: d60_Cirqus | C326: https://github.com/d60/Cirqus/commit/c7e6cd6227c3104f5e28b371cd5b113bf17a4158 | D326: https://github.com/d60/Cirqus/commit/58d905c9c916d847873c72ce8a038d125ca63f48 | E326: Inheritance support for tests harness | F326: Revert "Inheritance support for tests harness" This reverts commit c7e6cd6227c3104f5e28b371cd5b113bf17a4158. | H326: c7e6cd6227c3104f5e28b371cd5b113bf17a4158 | I326: d60.Cirqus.Testing/CirqusTestsHarness.cs | J326: (287, 13) | K326: d60.Cirqus.Testing/CirqusTestsHarness.cs | L326: (74, 13) | M326: 58d905c9c916d847873c72ce8a038d125ca63f48 | N326: d60.Cirqus.Testing/CirqusTestsHarness.cs | O326: (74, 41) | P326: d60.Cirqus.Testing/CirqusTestsHarness.cs | R326: var lastestOfType = ids.OfType<TypedId<T>>().ToList(); | S326: var emitterType = ids.First(i => i.ToString() == Latest<T>()).GetEmitterType().AssemblyQualifiedName; | T326: i => i.ToString() == Latest<T>()

Sheet java_shuffle
B1: name_with_owner | C1: insert url | D1: delete url | E1: replacement_msg | F1: delete_msg | G1: coding | H1: insert commit | I1: insert src file | J1: insert src start pos | K1: insert dst file | L1: insert dst start pos | M1: delete commit | N1: delete src file | O1: delete src start pos | P1: delete dst file | Q1: delete dst start pos | R1: insert src file content | S1: insert dst file content | T1: delete src file content
A2: 0 | B2: cloudfoundry_uaa | C2: https://github.com/cloudfoundry/uaa/commit/5082fb81a17d1799e0ba23ee34d726b5f96b7917 | D2: https://github.com/cloudfoundry/uaa/commit/208a340f5925336606dff571280c5aaa614ff092 | E2: Simplify automatic IDP redirect [#117270251] https://www.pivotaltracker.com/story/show/117270251 Signed-off-by: Priyata Agrawal <pagrawal@pivotal.io> Signed-off-by: Jonathan Lo <jlo@us.ibm.com> | G2: 機能変更 | H2: 5082fb81a17d1799e0ba23ee34d726b5f96b7917 | I2: server/src/test/java/org/cloudfoundry/identity/uaa/login/LoginInfoEndpointTests.java | J2: (455, 9) | K2: server/src/test/java/org/cloudfoundry/identity/uaa/login/LoginInfoEndpointTests.java | L2: (455, 9) | M2: 208a340f5925336606dff571280c5aaa614ff092 | N2: server/src/test/java/org/cloudfoundry/identity/uaa/login/LoginInfoEndpointTests.java | O2: (764, 57) | P2: server/src/test/java/org/cloudfoundry/identity/uaa/login/LoginInfoEndpointTests.java | R2: assertEquals("my-client-awesome-idp1", clientIdp.getIdpEntityAlias()); | S2: assertThat(idpDefinitions, PredicateMatcher.<SamlIdentityProviderDefinition>has(c -> c.getIdpEntityAlias().equals("my-client-awesome-idp1"))); | T2: c -> c.getIdpEntityAlias().equals("my-client-awesome-idp1")
A3: 1 | B3: web3j_web3j | C3: https://github.com/web3j/web3j/commit/a4ab324a089fc0a5562883b8696dcd50743988e2 | D3: https://github.com/web3j/web3j/commit/79a467011163eaffb53a1b33e880a437cba16cfb | E3: migrate to RxJava2 (no method or class renaming) | F3: Changing the generated code to be Java-6 compatible. | G3: 機能変更 | H3: a4ab324a089fc0a5562883b8696dcd50743988e2 | I3: core/src/main/java/org/web3j/ens/contracts/generated/PublicResolver.java | J3: (78, 9) | K3: core/src/main/java/org/web3j/ens/contracts/generated/PublicResolver.java | L3: (76, 9) | M3: 79a467011163eaffb53a1b33e880a437cba16cfb | N3: core/src/main/java/org/web3j/ens/contracts/generated/PublicResolver.java | O3: (74, 49) | P3: core/src/main/java/org/web3j/ens/contracts/generated/PublicResolver.java | R3: return web3j.ethLogObservable(filter).map(new Func1<Log, AddrChangedEventResponse>() { @Override public AddrChangedEventResponse call(Log log) { EventValues eventValues = extractEventParameters(event, log); AddrChangedEventResponse typedResponse = new AddrChangedEventResponse(); typedResponse.node = (byte[]) eventValues.getIndexedValues().get(0).getValue(); typedResponse.a = (String) eventValues.getNonIndexedValues().get(0).getValue(); return typedResponse; } }); | S3: return web3j.ethLogObservable(filter).map(log -> { EventValues eventValues = extractEventParameters(event, log); AddrChangedEventResponse typedResponse = new AddrChangedEventResponse(); typedResponse.node = (byte[]) eventValues.getIndexedValues().get(0).getValue(); typedResponse.a = (String) eventValues.getNonIndexedValues().get(0).getValue(); return typedResponse; }); | T3: log -> { EventValues eventValues = extractEventParameters(event, log); AddrChangedEventResponse typedResponse = new AddrChangedEventResponse(); typedResponse.node = (byte[]) eventValues.getIndexedValues().get(0).getValue(); typedResponse.a = (String) eventValues.getNonIndexedValues().get(0).getValue(); return typedResponse; }
A4: 2 | B4: cloudfoundry_uaa | C4: https://github.com/cloudfoundry/uaa/commit/2644f537be1d123a4c5db04877070d1a112963c4 | D4: https://github.com/cloudfoundry/uaa/commit/2ffb7af271717920de5e34bdceff3e899f6f9370 | E4: Rework | F4: Fix: performance issue in MySQL * Revert "Merge pull request #2704 from cloudfoundry/fix/optimize-ids-users-endpoint" * This reverts commit 1324a81f8948250e993193f4be62dc5b9854965a, reversing changes made to b8826e1456b98ae179b85cab9e5261a64edc2d25. * The original PR is suspected to cause the performance issues. We will try to bring this change back later. | G4: 差し戻し | H4: 2644f537be1d123a4c5db04877070d1a112963c4 | I4: server/src/test/java/org/cloudfoundry/identity/uaa/scim/endpoints/UserIdConversionEndpointsTests.java | J4: (120, 9) | K4: server/src/test/java/org/cloudfoundry/identity/uaa/scim/endpoints/UserIdConversionEndpointsTests.java | L4: (179, 9) | M4: 2ffb7af271717920de5e34bdceff3e899f6f9370 | N4: server/src/test/java/org/cloudfoundry/identity/uaa/scim/endpoints/UserIdConversionEndpointsTests.java | O4: (180, 29) | P4: server/src/test/java/org/cloudfoundry/identity/uaa/scim/endpoints/UserIdConversionEndpointsTests.java | R4: endpoints.findUsers("groups.display eq \"foo\"", "ascending", 0, 100, false); | S4: assertThatExceptionOfType(ScimException.class) .isThrownBy(() -> endpoints.findUsers(filter, "ascending", 0, 100, false)) .withMessage("Invalid operator."); | T4: () -> endpoints.findUsers(filter, "ascending", 0, 100, false)
A5: 3 | B5: cloudfoundry_uaa | C5: https://github.com/cloudfoundry/uaa/commit/d3a4f68188273f32b6e79f0aacd0c02bde5eb6bf | D5: https://github.com/cloudfoundry/uaa/commit/13737c7c5dbc11a4186c17fbacbc6732d9ccaec9 | E5: Convert XOAuthAuthenticationManagerIT to junit5 Signed-off-by: Bruce Ricard <bricard@pivotal.io> Co-authored-by: Bruce Ricard <bricard@pivotal.io> | F5: Adapt tests for new JWT Bearer behavior [#160462755] https://www.pivotaltracker.com/story/show/160462755 Signed-off-by: Florian Tack <florian.tack@sap.com> | G5: 機能変更 | H5: d3a4f68188273f32b6e79f0aacd0c02bde5eb6bf | I5: server/src/test/java/org/cloudfoundry/identity/uaa/provider/oauth/XOAuthAuthenticationManagerIT.java | J5: (458, 9) | K5: server/src/test/java/org/cloudfoundry/identity/uaa/provider/oauth/XOAuthAuthenticationManagerIT.java | L5: (460, 9) | M5: 13737c7c5dbc11a4186c17fbacbc6732d9ccaec9 | N5: server/src/test/java/org/cloudfoundry/identity/uaa/provider/oauth/XOAuthAuthenticationManagerIT.java | O5: (467, 65) | P5: server/src/test/java/org/cloudfoundry/identity/uaa/provider/oauth/XOAuthAuthenticationManagerIT.java | R5: xoAuthAuthenticationManager .getExternalAuthenticationDetails(xCodeToken); | S5: assertThrows(InsufficientAuthenticationException.class, () -> xoAuthAuthenticationManager.getExternalAuthenticationDetails(xCodeToken)); | T5: () -> xoAuthAuthenticationManager.getExternalAuthenticationDetails(xCodeToken)
A6: 4 | B6: mpusher_mpush | C6: https://github.com/mpusher/mpush/commit/76aa1107551813285d546e538dff1a3bf60309c8 | D6: https://github.com/mpusher/mpush/commit/d0eb910c134b78ba10234787e4e1f25f7848f618 | E6: 增加Netty write-buffer-water-mark 配置 | F6: 增加PushCenter消息流转时间线, 方便监控消息的各个生命周期的耗时PushClient -> GatewayClient -> GatewayServer -> PushCenter -> ConnServer -> Client | G6: 機能変更 | H6: 76aa1107551813285d546e538dff1a3bf60309c8 | I6: mpush-core/src/main/java/com/mpush/core/push/GatewayPushListener.java | J6: (105, 13) | K6: mpush-core/src/main/java/com/mpush/core/push/GatewayPushListener.java | L6: (111, 13) | M6: d0eb910c134b78ba10234787e4e1f25f7848f618 | N6: mpush-core/src/main/java/com/mpush/core/push/GatewayPushListener.java | O6: (111, 40) | P6: mpush-core/src/main/java/com/mpush/core/push/GatewayPushListener.java | R6: ErrorMessage .from(message) .setErrorCode(ROUTER_CHANGE) .setData(message.userId + ',' + message.clientType) .sendRaw(); | S6: message.runInRequestThread(() -> ErrorMessage .from(message) .setErrorCode(ROUTER_CHANGE) .setData(message.userId + ',' + message.clientType) .sendRaw() ); | T6: () -> ErrorMessage .from(message) .setErrorCode(ROUTER_CHANGE) .setData(message.userId + ',' + message.clientType) .sendRaw()
A7: 5 | B7: google_ground-android | C7: https://github.com/google/ground-android/commit/ace2bf815520f0c4ea9a91accfb0162337f70837 | D7: https://github.com/google/ground-android/commit/a9602eb21d119408c6c935ae99869f65e9256137 | E7: Fix back navigation from View Record (WIP). Change-Id: Id4547b2d28658c60b93b4d501c6dbea71c3edb7c | F7: Load project summaries. Change-Id: If51bebcaeb635539776fbae08cc84baddd84604a | G7: 機能変更 | H7: ace2bf815520f0c4ea9a91accfb0162337f70837 | I7: gnd/src/main/java/com/google/android/gnd/ui/browse/BrowseFragment.java | J7: (150, 5) | K7: gnd/src/main/java/com/google/android/gnd/ui/browse/BrowseFragment.java | L7: (154, 5) | M7: a9602eb21d119408c6c935ae99869f65e9256137 | N7: gnd/src/main/java/com/google/android/gnd/ui/browse/BrowseFragment.java | O7: (138, 30) | P7: gnd/src/main/java/com/google/android/gnd/ui/browse/BrowseFragment.java | R7: ProjectSelectorDialogFragment.show(getFragmentManager(), projects); | S7: projects.get().ifPresent(p -> ProjectSelectorDialogFragment.show(getFragmentManager(), p)); | T7: p -> ProjectSelectorDialogFragment.show(getFragmentManager(), p)
A8: 6 | B8: NightscoutFoundation_xDrip | C8: https://github.com/NightscoutFoundation/xDrip/commit/6ed3d27bdab84e787aa77c9d867df6fb235102e6 | D8: https://github.com/NightscoutFoundation/xDrip/commit/5a3c9b7c8744a759401e492e162161531481f52f | E8: Add graph data. Add ratelimit for broadcast receiver command handler | F8: rename WatchBroadcastService to BroadcastService, rename WatchBroadcast namespace to broadcast_service. Extract isEnable function to separate class in order to optimize memory usage. Use function BgGraphBuilder.FUZZER | G8: 誤検出 | H8: 6ed3d27bdab84e787aa77c9d867df6fb235102e6 | I8: app/src/main/java/com/eveningoutpost/dexdrip/wearintegration/WatchBroadcast/WatchBroadcastService.java | J8: (71, 5) | K8: app/src/main/java/com/eveningoutpost/dexdrip/wearintegration/WatchBroadcast/WatchBroadcastService.java | L8: (69, 5) | M8: 5a3c9b7c8744a759401e492e162161531481f52f | N8: app/src/main/java/com/eveningoutpost/dexdrip/wearintegration/WatchBroadcast/WatchBroadcastService.java | O8: (82, 85) | P8: app/src/main/java/com/eveningoutpost/dexdrip/wearintegration/broadcast_service/BroadcastService.java | R8: public static SharedPreferences.OnSharedPreferenceChangeListener prefListener = new SharedPreferences.OnSharedPreferenceChangeListener() { public void onSharedPreferenceChanged(SharedPreferences prefs, String key) { if (key.equals(PREF_ENABLED)) { JoH.startService(WatchBroadcastService.class); } } }; | S8: public static SharedPreferences.OnSharedPreferenceChangeListener prefListener = (prefs, key) -> { if (key.equals(PREF_ENABLED)) { JoH.startService(WatchBroadcastService.class); } }; | T8: (prefs, key) -> { if (key.equals(PREF_ENABLED)) { JoH.startService(WatchBroadcastService.class); } }
A9: 7 | B9: web3j_web3j | C9: https://github.com/web3j/web3j/commit/982f4db12324d1d749c4d5cbf8b73ff7c001b80a | D9: https://github.com/web3j/web3j/commit/3abe159c1279cb59a3b1b9d75da9b15e2ece5364 | E9: Remove leading zeroes for encoded quantities | F9: Fixed leading zeroes Hex quantity not accepted (#1813) * fixed leading zeroes Hex quantity not accepted * regex solution | G9: 差し戻し | H9: 982f4db12324d1d749c4d5cbf8b73ff7c001b80a | I9: utils/src/test/java/org/web3j/utils/NumericTest.java | J9: (75, 9) | K9: utils/src/test/java/org/web3j/utils/NumericTest.java | L9: (74, 9) | M9: 3abe159c1279cb59a3b1b9d75da9b15e2ece5364 | N9: utils/src/test/java/org/web3j/utils/NumericTest.java | O9: (75, 54) | P9: utils/src/test/java/org/web3j/utils/NumericTest.java | R9: assertEquals(Numeric.decodeQuantity("0x0400"), (BigInteger.valueOf(1024L))); | S9: assertThrows(MessageDecodingException.class, () -> Numeric.decodeQuantity("0x0400")); | T9: () -> Numeric.decodeQuantity("0x0400")
A10: 8 | B10: google_ground-android | C10: https://github.com/google/ground-android/commit/063933f902873354e3c79ca7e8e5abaeda1af9a7 | D10: https://github.com/google/ground-android/commit/e8a02d59cc4fb027dcf020f0a587b01846822c90 | E10: Clean up handling of project selection streams Change-Id: I41ddb41d8cf371a5f7cbcd426dd49d287a658ea2 | F10: WIP project activation flow cleanup and ideas | G10: 機能削除 | H10: 063933f902873354e3c79ca7e8e5abaeda1af9a7 | I10: gnd/src/main/java/com/google/android/gnd/ui/projectselector/ProjectSelectorViewModel.java | J10: (65, 5) | K10: gnd/src/main/java/com/google/android/gnd/ui/projectselector/ProjectSelectorViewModel.java | L10: (47, 5) | M10: e8a02d59cc4fb027dcf020f0a587b01846822c90 | N10: gnd/src/main/java/com/google/android/gnd/ui/projectselector/ProjectSelectorViewModel.java | O10: (51, 17) | P10: gnd/src/main/java/com/google/android/gnd/ui/projectselector/ProjectSelectorViewModel.java | R10: disposeOnClear( activeProjectStream.subscribe( Result.unwrap(activeProject::setValue, this::onActiveProjectError))); | S10: disposeOnClear( projectSelections .switchMapSingle( idx -> dataRepository .activateProject(getProjectSummary(idx).getId()) .doOnError(this::onActiveProjectError) .onErrorResumeNext(Single.never())) .subscribe(activeProject::setValue)); | T10: idx -> dataRepository .activateProject(getProjectSummary(idx).getId()) .doOnError(this::onActiveProjectError) .onErrorResumeNext(Single.never())
A11: 9 | B11: freeplane_freeplane | C11: https://github.com/freeplane/freeplane/commit/771ffa76619ffd60a2b6a95a5a80e3b777f7e475 | D11: https://github.com/freeplane/freeplane/commit/128a50e97fb6186f0d390884a30bebf43a1bdc7c | E11: Allow script and formula execution in headless mode | F11: Still support java 7 on 1.6.x | G11: 差し戻し | H11: 771ffa76619ffd60a2b6a95a5a80e3b777f7e475 | I11: freeplane/src/main/java/org/freeplane/main/osgi/ActivatorImpl.java | J11: (232, 7) | K11: freeplane/src/main/java/org/freeplane/main/osgi/ActivatorImpl.java | L11: (225, 4) | M11: 128a50e97fb6186f0d390884a30bebf43a1bdc7c | N11: freeplane/src/main/java/org/freeplane/main/osgi/ActivatorImpl.java | O11: (226, 5) | P11: freeplane/src/main/java/org/freeplane/main/osgi/ActivatorImpl.java | R11: service.installExtension(controller); | S11: runServiceOnce(null, IControllerExtensionProvider.class, service -> service.installExtension(controller)); | T11: service -> service.installExtension(controller)
A12: 10 | B12: web3j_web3j | C12: https://github.com/web3j/web3j/commit/a4ab324a089fc0a5562883b8696dcd50743988e2 | D12: https://github.com/web3j/web3j/commit/408214a9a8633be786a844a3a2a291763e70a12d | E12: migrate to RxJava2 (no method or class renaming) | F12: - Updating all "3.6.0" references to "4.0.0" - Addressing some (not all) PR feedback - Regenerating code | G12: 差し戻し | H12: a4ab324a089fc0a5562883b8696dcd50743988e2 | I12: integration-tests/src/test/java/org/web3j/generated/HumanStandardToken.java | J12: (110, 9) | K12: integration-tests/src/test/java/org/web3j/generated/HumanStandardToken.java | L12: (107, 9) | M12: 408214a9a8633be786a844a3a2a291763e70a12d | N12: integration-tests/src/test/java/org/web3j/generated/HumanStandardToken.java | O12: (258, 49) | P12: integration-tests/src/test/java/org/web3j/generated/HumanStandardToken.java | R12: return web3j.ethLogObservable(filter).map(new Func1<Log, ApprovalEventResponse>() { @Override public ApprovalEventResponse call(Log log) { Contract.EventValuesWithLog eventValues = extractEventParametersWithLog(APPROVAL_EVENT, log); ApprovalEventResponse typedResponse = new ApprovalEventResponse(); typedResponse.log = log; typedResponse._owner = (String) eventValues.getIndexedValues().get(0).getValue(); typedResponse._spender = (String) eventValues.getIndexedValues().get(1).getValue(); typedResponse._value = (BigInteger) eventValues.getNonIndexedValues().get(0).getValue(); return typedResponse; } }); | S12: return web3j.ethLogObservable(filter).map(log -> { EventValuesWithLog eventValues = extractEventParametersWithLog(APPROVAL_EVENT, log); ApprovalEventResponse typedResponse = new ApprovalEventResponse(); typedResponse.log = log; typedResponse._owner = (String) eventValues.getIndexedValues().get(0).getValue(); typedResponse._spender = (String) eventValues.getIndexedValues().get(1).getValue(); typedResponse._value = (BigInteger) eventValues.getNonIndexedValues().get(0).getValue(); return typedResponse; }); | T12: log -> { Contract.EventValuesWithLog eventValues = extractEventParametersWithLog(APPROVAL_EVENT, log); ApprovalEventResponse typedResponse = new ApprovalEventResponse(); typedResponse.log = log; typedResponse._owner = (String) eventValues.getIndexedValues().get(0).getValue(); typedResponse._spender = (String) eventValues.getIndexedValues().get(1).getValue(); typedResponse._value = (BigInteger) eventValues.getNonIndexedValues().get(0).getValue(); return typedResponse; }
A13: 11 | B13: web3j_web3j | C13: https://github.com/web3j/web3j/commit/a4ab324a089fc0a5562883b8696dcd50743988e2 | D13: https://github.com/web3j/web3j/commit/79a467011163eaffb53a1b33e880a437cba16cfb | E13: migrate to RxJava2 (no method or class renaming) | F13: Changing the generated code to be Java-6 compatible. | G13: 機能変更 | H13: a4ab324a089fc0a5562883b8696dcd50743988e2 | I13: core/src/main/java/org/web3j/ens/contracts/generated/PublicResolver.java | J13: (177, 9) | K13: core/src/main/java/org/web3j/ens/contracts/generated/PublicResolver.java | L13: (166, 9) | M13: 79a467011163eaffb53a1b33e880a437cba16cfb | N13: core/src/main/java/org/web3j/ens/contracts/generated/PublicResolver.java | O13: (158, 49) | P13: core/src/main/java/org/web3j/ens/contracts/generated/PublicResolver.java | R13: return web3j.ethLogObservable(filter).map(new Func1<Log, ABIChangedEventResponse>() { @Override public ABIChangedEventResponse call(Log log) { EventValues eventValues = extractEventParameters(event, log); ABIChangedEventResponse typedResponse = new ABIChangedEventResponse(); typedResponse.node = (byte[]) eventValues.getIndexedValues().get(0).getValue(); typedResponse.contentType = (BigInteger) eventValues.getIndexedValues().get(1).getValue(); return typedResponse; } }); | S13: return web3j.ethLogObservable(filter).map(log -> { EventValues eventValues = extractEventParameters(event, log); ABIChangedEventResponse typedResponse = new ABIChangedEventResponse(); typedResponse.node = (byte[]) eventValues.getIndexedValues().get(0).getValue(); typedResponse.contentType = (BigInteger) eventValues.getIndexedValues().get(1).getValue(); return typedResponse; }); | T13: log -> { EventValues eventValues = extractEventParameters(event, log); ABIChangedEventResponse typedResponse = new ABIChangedEventResponse(); typedResponse.node = (byte[]) eventValues.getIndexedValues().get(0).getValue(); typedResponse.contentType = (BigInteger) eventValues.getIndexedValues().get(1).getValue(); return typedResponse; }
A14: 12 | B14: NOVA-Team_NOVA-Core | C14: https://github.com/NOVA-Team/NOVA-Core/commit/f5d41683683746f8cf82aecf279e5fd2f6054429 | D14: https://github.com/NOVA-Team/NOVA-Core/commit/ee48c59943802dffa041b5a52bbdae22916d3220 | E14: Switched Sound system to use factories | F14: Resolved #72 Implemented basic sound system | G14: 差し戻し | H14: f5d41683683746f8cf82aecf279e5fd2f6054429 | I14: src/main/java/nova/core/block/component/BlockProperties.java | J14: (54, 3) | K14: src/main/java/nova/core/block/component/BlockProperties.java | L14: (54, 3) | M14: ee48c59943802dffa041b5a52bbdae22916d3220 | N14: src/main/java/nova/core/block/component/BlockProperties.java | O14: (54, 50) | P14: src/main/java/nova/core/block/component/BlockProperties.java | R14: return setBlockSound(trigger, new ResourceSound("", soundResourceString)); | S14: return setBlockSound(trigger, new SoundFactory(args -> new Sound("", soundResourceString))); | T14: args -> new Sound("", soundResourceString)
... A20: 18 | B20: cloudfoundry_uaa | C20: https://github.com/cloudfoundry/uaa/commit/2644f537be1d123a4c5db04877070d1a112963c4 | D20: https://github.com/cloudfoundry/uaa/commit/2ffb7af271717920de5e34bdceff3e899f6f9370 | E20: Rework | F20: Fix: performance issue in MySQL * Revert "Merge pull request #2704 from cloudfoundry/fix/optimize-ids-users-endpoint" * This reverts commit 1324a81f8948250e993193f4be62dc5b9854965a, reversing changes made to b8826e1456b98ae179b85cab9e5261a64edc2d25. * The original PR is suspected to cause the performance issues. We will try to bring this change back later. | G20: 差し戻し | H20: 2644f537be1d123a4c5db04877070d1a112963c4 | I20: server/src/test/java/org/cloudfoundry/identity/uaa/scim/endpoints/UserIdConversionEndpointsTests.java | J20: (207, 9) | K20: server/src/test/java/org/cloudfoundry/identity/uaa/scim/endpoints/UserIdConversionEndpointsTests.java | L20: (202, 9) | M20: 2ffb7af271717920de5e34bdceff3e899f6f9370 | N20: server/src/test/java/org/cloudfoundry/identity/uaa/scim/endpoints/UserIdConversionEndpointsTests.java | O20: (203, 29) | P20: server/src/test/java/org/cloudfoundry/identity/uaa/scim/endpoints/UserIdConversionEndpointsTests.java | R20: endpoints.findUsers("id co \"foo\"", "ascending", 0, 100, false); | S20: assertThatExceptionOfType(ScimException.class) .isThrownBy(() -> endpoints.findUsers(filter, "ascending", 0, 100, false)) .withMessage("Invalid filter attribute."); | T20: () -> endpoints.findUsers(filter, "ascending", 0, 100, false)
A21: 19 | B21: cloudfoundry_uaa | C21: https://github.com/cloudfoundry/uaa/commit/de537f84a3cad98a6cd98613649bc074498f000a | D21: https://github.com/cloudfoundry/uaa/commit/208a340f5925336606dff571280c5aaa614ff092 | E21: Authenticate with external oauth provider with client context Signed-off-by: Madhura Bhave <mbhave@pivotal.io> | G21: 機能変更 | H21: de537f84a3cad98a6cd98613649bc074498f000a | I21: server/src/test/java/org/cloudfoundry/identity/uaa/config/IdentityProviderBootstrapTest.java | J21: (268, 13) | K21: server/src/test/java/org/cloudfoundry/identity/uaa/config/IdentityProviderBootstrapTest.java | L21: (272, 13) | M21: 208a340f5925336606dff571280c5aaa614ff092 | N21: server/src/test/java/org/cloudfoundry/identity/uaa/config/IdentityProviderBootstrapTest.java | O21: (387, 71) | P21: server/src/test/java/org/cloudfoundry/identity/uaa/config/IdentityProviderBootstrapTest.java | R21: assertEquals(oauthProvider, bootstrapOauthProvider.getConfig()); | S21: assertThat(oauthProviderConfig.values(), PredicateMatcher.<AbstractXOAuthIdentityProviderDefinition>has(c -> c.equals(bootstrapOauthProvider.getConfig()))); | T21: c -> c.equals(bootstrapOauthProvider.getConfig())
A22: 20 | B22: cloudfoundry_uaa | C22: https://github.com/cloudfoundry/uaa/commit/2644f537be1d123a4c5db04877070d1a112963c4 | D22: https://github.com/cloudfoundry/uaa/commit/2ffb7af271717920de5e34bdceff3e899f6f9370 | E22: Rework | F22: Fix: performance issue in MySQL * Revert "Merge pull request #2704 from cloudfoundry/fix/optimize-ids-users-endpoint" * This reverts commit 1324a81f8948250e993193f4be62dc5b9854965a, reversing changes made to b8826e1456b98ae179b85cab9e5261a64edc2d25. * The original PR is suspected to cause the performance issues. We will try to bring this change back later. | G22: 差し戻し | H22: 2644f537be1d123a4c5db04877070d1a112963c4 | I22: server/src/test/java/org/cloudfoundry/identity/uaa/scim/endpoints/UserIdConversionEndpointsTests.java | J22: (99, 9) | K22: server/src/test/java/org/cloudfoundry/identity/uaa/scim/endpoints/UserIdConversionEndpointsTests.java | L22: (81, 9) | M22: 2ffb7af271717920de5e34bdceff3e899f6f9370 | N22: server/src/test/java/org/cloudfoundry/identity/uaa/scim/endpoints/UserIdConversionEndpointsTests.java | O22: (82, 29) | P22: server/src/test/java/org/cloudfoundry/identity/uaa/scim/endpoints/UserIdConversionEndpointsTests.java | R22: endpoints.findUsers("userName eq \"marissa\"", "ascending", 0, 100, false); | S22: assertThatNoException() .isThrownBy(() -> endpoints.findUsers("userName eq \"marissa\"", "ascending", 0, 100, false)); | T22: () -> endpoints.findUsers("userName eq \"marissa\"", "ascending", 0, 100, false)
A23: 21 | B23: apache_jmeter | C23: https://github.com/apache/jmeter/commit/70626d26271af5411b90258658dde55994805992 | D23: https://github.com/apache/jmeter/commit/b9df34f64edf03fa219a54740b70220d0cb69380 | E23: Use Java8 lambdas git-svn-id: https://svn.apache.org/repos/asf/jmeter/trunk@1782596 13f79535-47bb-0310-9956-ffa450edef68 Former-commit-id: b1b0496b60f8e68550885a8b59b431ef9c676a4c | F23: Bug 60687 - Make GUI more responsive when it gets a lot of events Improve errrors indicator management Bugzilla Id: 60687 git-svn-id: https://svn.apache.org/repos/asf/jmeter/trunk@1783153 13f79535-47bb-0310-9956-ffa450edef68 Former-commit-id: cbcfc532248e211dce04aea7da91d605dbafee6d | G23: 機能削除 | H23: 70626d26271af5411b90258658dde55994805992 | I23: src/core/org/apache/jmeter/gui/MainFrame.java | J23: (838, 17) | K23: src/core/org/apache/jmeter/gui/MainFrame.java | L23: (832, 17) | M23: b9df34f64edf03fa219a54740b70220d0cb69380 | N23: src/core/org/apache/jmeter/gui/MainFrame.java | O23: (832, 44) | P23: src/core/org/apache/jmeter/gui/MainFrame.java | R23: SwingUtilities.invokeLater(new Runnable() { @Override public void run() { errorsOrFatalsLabel.setForeground(Color.RED); errorsOrFatalsLabel.setText(Integer.toString(newValue)); } }); | S23: SwingUtilities.invokeLater(() -> { errorsOrFatalsLabel.setForeground(Color.RED); errorsOrFatalsLabel.setText(Long.toString(newValue)); }); | T23: () -> { errorsOrFatalsLabel.setForeground(Color.RED); errorsOrFatalsLabel.setText(Long.toString(newValue)); }
A24: 22 | B24: NOVA-Team_NOVA-Core | C24: https://github.com/NOVA-Team/NOVA-Core/commit/d8ed02faaf078618097b3d68068e6490637c41df | D24: https://github.com/NOVA-Team/NOVA-Core/commit/ca067203b83827562e6708d8f3aacd8dd26493b7 | E24: Swich from Provider to Supplier Signed-off-by: Kubuxu <kubuxu@gmail.com> | F24: Finished up FormattedText, added scissor test for Canvas. | G24: 差し戻し | H24: d8ed02faaf078618097b3d68068e6490637c41df | I24: src/main/java/nova/core/gui/GuiComponent.java | J24: (62, 3) | K24: src/main/java/nova/core/gui/GuiComponent.java | L24: (62, 3) | M24: ca067203b83827562e6708d8f3aacd8dd26493b7 | N24: src/main/java/nova/core/gui/GuiComponent.java | O24: (47, 47) | P24: src/main/java/nova/core/gui/GuiComponent.java | R24: Game.instance.get().guiComponentFactory.applyNativeComponent(this, nativeClass); | S24: Game.instance.get().guiComponentFactory.ifPresent((cf)-> cf.applyNativeComponent(this, nativeClass)); | T24: (cf) -> cf.applyNativeComponent(this, nativeClass)
A25: 23 | B25: mplushnikov_lombok-intellij-plugin | C25: https://github.com/mplushnikov/lombok-intellij-plugin/commit/49c35ac466acaadbf6272d0eaae9bf68c5088430 | D25: https://github.com/mplushnikov/lombok-intellij-plugin/commit/d25ff91428f7569c85c4a026ea02c81f7b7e6c57 | E25: added basic in-memory cache for lombok config discovery | F25: removed invalid cache | G25: 差し戻し | H25: 49c35ac466acaadbf6272d0eaae9bf68c5088430 | I25: src/main/java/de/plushnikov/intellij/plugin/lombokconfig/ConfigDiscovery.java | J25: (37, 7) | K25: src/main/java/de/plushnikov/intellij/plugin/lombokconfig/ConfigDiscovery.java | L25: (45, 7) | M25: d25ff91428f7569c85c4a026ea02c81f7b7e6c57 | N25: src/main/java/de/plushnikov/intellij/plugin/lombokconfig/ConfigDiscovery.java | O25: (46, 9) | P25: src/main/java/de/plushnikov/intellij/plugin/lombokconfig/ConfigDiscovery.java | R25: return discoverProperty(configKey, canonicalPath, psiClass.getProject()); | S25: return easyCache.computeIfAbsent(configKey.ordinal() + canonicalPath, k -> discoverProperty(configKey, canonicalPath, psiClass.getProject())); | T25: k -> discoverProperty(configKey, canonicalPath, psiClass.getProject())
A26: 24 | B26: cloudfoundry_uaa | C26: https://github.com/cloudfoundry/uaa/commit/625c63a9d0f8149f50cedb42d2433c19411dd172 | D26: https://github.com/cloudfoundry/uaa/commit/333ffcc01e07d24f2db509af811c1c433e438555 | E26: Revert "Replace transaction manager usage with Transactional annotation" This reverts commit 10614d4e41b431d798cf8f61f1237992aa834534. | F26: Sonar refactoring - IdentityProviderEndpoints class (#2890) * Sonar refactorings See https://sonarcloud.io/code?id=cloudfoundry-identity-parent&selected=cloudfoundry-identity-parent%3Aserver%2Fsrc%2Fmain%2Fjava%2Forg%2Fcloudfoundry%2Fidentity%2Fuaa%2Fprovider%2FIdentityProviderEndpoints.java * remove dead code * more sonar smell fixes * no log change * revert and allow test endpoint again * warnings * rebase * rebase * test setup | G26: 機能変更 | H26: 625c63a9d0f8149f50cedb42d2433c19411dd172 | I26: server/src/main/java/org/cloudfoundry/identity/uaa/provider/IdentityProviderEndpoints.java | J26: (234, 9) | K26: server/src/main/java/org/cloudfoundry/identity/uaa/provider/IdentityProviderEndpoints.java | L26: (237, 9) | M26: 333ffcc01e07d24f2db509af811c1c433e438555 | N26: server/src/main/java/org/cloudfoundry/identity/uaa/provider/IdentityProviderEndpoints.java | O26: (259, 54) | P26: server/src/main/java/org/cloudfoundry/identity/uaa/provider/IdentityProviderEndpoints.java | R26: final IdentityProvider<?> updatedIdpAfterMirrorHandling = ensureConsistencyOfMirroredIdp(updatedIdp); | S26: final IdentityProvider<?> updatedIdp = transactionTemplate.execute(txStatus -> { final IdentityProvider<?> updatedOriginalIdp = identityProviderProvisioning.update(body, zoneId); return ensureConsistencyOfMirroredIdp(updatedOriginalIdp); }); | T26: txStatus -> { final IdentityProvider<?> updatedOriginalIdp = identityProviderProvisioning.update(body, zoneId); return idpAliasHandler.ensureConsistencyOfAliasEntity(updatedOriginalIdp, existing); }
A27: 25 | B27: google_ground-android | C27: https://github.com/google/ground-android/commit/efdb77743994c6ea557016466fbe03daa851206d | D27: https://github.com/google/ground-android/commit/2b15ff40ed92ef72ef3a4e2dcb6b7631b3ad9304 | E27: Add map features from geoJson in MapContainerViewModel | F27: Add MapGeoJSON model and render GeoJSON using maps SDK | G27: 機能変更 | H27: efdb77743994c6ea557016466fbe03daa851206d | I27: gnd/src/main/java/com/google/android/gnd/ui/home/mapcontainer/MapContainerViewModel.java | J27: (147, 5) | K27: gnd/src/main/java/com/google/android/gnd/ui/home/mapcontainer/MapContainerViewModel.java | L27: (150, 5) | M27: 2b15ff40ed92ef72ef3a4e2dcb6b7631b3ad9304 | N27: gnd/src/main/java/com/google/android/gnd/ui/home/mapcontainer/MapContainerViewModel.java | O27: (155, 13) | P27: gnd/src/main/java/com/google/android/gnd/ui/home/mapcontainer/MapContainerViewModel.java | R27: return MapPolygon.newBuilder() .setId(feature.getId()) .setVertices(feature.getPolygon().getVertices()) .setStyle(feature.getLayer().getDefaultStyle()) .setFeature(feature) .build(); | S27: return stream(feature.getGeoJson().getPolygons()) .map( polygon -> MapPolygon.newBuilder() .setId(feature.getId()) .setVertices(polygon.getVertices()) .setStyle(feature.getLayer().getDefaultStyle()) .setFeature(feature) .build()); | T27: polygon -> MapPolygon.newBuilder() .setId(feature.getId()) .setVertices(polygon.getVertices()) .setStyle(feature.getLayer().getDefaultStyle()) .setFeature(feature) .build()
A28: 26 | B28: mpusher_mpush | C28: https://github.com/mpusher/mpush/commit/5cd94b064e144fc6812872a7d44c742ec7dcfbd6 | D28: https://github.com/mpusher/mpush/commit/8b6d2b2e6f76025709cbd62086657bb749c90f55 | E28: java8 支持 | F28: 线程优化及日志优化 | G28: 機能削除 | H28: 5cd94b064e144fc6812872a7d44c742ec7dcfbd6 | I28: mpush-boot/src/main/java/com/mpush/bootstrap/job/ServerBoot.java | J28: (47, 9) | K28: mpush-boot/src/main/java/com/mpush/bootstrap/job/ServerBoot.java | L28: (47, 9) | M28: 8b6d2b2e6f76025709cbd62086657bb749c90f55 | N28: mpush-boot/src/main/java/com/mpush/bootstrap/job/ServerBoot.java | O28: (48, 51) | P28: mpush-boot/src/main/java/com/mpush/bootstrap/job/ServerBoot.java | R28: ThreadPoolManager.I.newThread(serverName, new Runnable() { @Override public void run() { server.init(); server.start(new Listener() { @Override public void onSuccess(Object... args) { Logs.Console.error("start " + serverName + " success listen:" + args[0]); if (node != null) { registerServerToZk(node.getZkPath(), Jsons.toJson(node)); } next(); } @Override public void onFailure(Throwable cause) { Logs.Console.error("start " + serverName + " failure, jvm exit with code -1", cause); System.exit(-1); } }); } }).start(); | S28: ThreadPoolManager.I.newThread(serverName, () -> { server.init(); server.start(new Listener() { @Override public void onSuccess(Object... args) { Logs.Console.error("start " + serverName + " success listen:" + args[0]); if (node != null) { registerServerToZk(node.getZkPath(), Jsons.toJson(node)); } next(); } @Override public void onFailure(Throwable cause) { Logs.Console.error("start " + serverName + " failure, jvm exit with code -1", cause); System.exit(-1); } }); }).start(); | T28: () -> { server.init(); server.start(new Listener() { @Override public void onSuccess(Object... args) { Logs.Console.info("start {} success listen:{}", serverName, args[0]); if (node != null) {//zk ZKRegister.build().setEphemeral(true).setNode(node).register(); Logs.Console.info("register server node={} to zk path={}", node, node.getNodePath()); } startNext(); } @Override public void onFailure(Throwable cause) { Logs.Console.error("start " + serverName + " failure, jvm exit with code -1", cause); System.exit(-1); } }); }
A29: 27 | B29: web3j_web3j | C29: https://github.com/web3j/web3j/commit/a4ab324a089fc0a5562883b8696dcd50743988e2 | D29: https://github.com/web3j/web3j/commit/408214a9a8633be786a844a3a2a291763e70a12d | E29: migrate to RxJava2 (no method or class renaming) | F29: - Updating all "3.6.0" references to "4.0.0" - Addressing some (not all) PR feedback - Regenerating code | G29: 機能変更 | H29: a4ab324a089fc0a5562883b8696dcd50743988e2 | I29: integration-tests/src/test/java/org/web3j/generated/HumanStandardToken.java | J29: (75, 9) | K29: integration-tests/src/test/java/org/web3j/generated/HumanStandardToken.java | L29: (75, 9) | M29: 408214a9a8633be786a844a3a2a291763e70a12d | N29: integration-tests/src/test/java/org/web3j/generated/HumanStandardToken.java | O29: (225, 49) | P29: integration-tests/src/test/java/org/web3j/generated/HumanStandardToken.java | R29: return web3j.ethLogObservable(filter).map(new Func1<Log, TransferEventResponse>() { @Override public TransferEventResponse call(Log log) { Contract.EventValuesWithLog eventValues = extractEventParametersWithLog(TRANSFER_EVENT, log); TransferEventResponse typedResponse = new TransferEventResponse(); typedResponse.log = log; typedResponse._from = (String) eventValues.getIndexedValues().get(0).getValue(); typedResponse._to = (String) eventValues.getIndexedValues().get(1).getValue(); typedResponse._value = (BigInteger) eventValues.getNonIndexedValues().get(0).getValue(); return typedResponse; } }); | S29: return web3j.ethLogObservable(filter).map(log -> { EventValuesWithLog eventValues = extractEventParametersWithLog(TRANSFER_EVENT, log); TransferEventResponse typedResponse = new TransferEventResponse(); typedResponse.log = log; typedResponse._from = (String) eventValues.getIndexedValues().get(0).getValue(); typedResponse._to = (String) eventValues.getIndexedValues().get(1).getValue(); typedResponse._value = (BigInteger) eventValues.getNonIndexedValues().get(0).getValue(); return typedResponse; }); | T29: log -> { Contract.EventValuesWithLog eventValues = extractEventParametersWithLog(TRANSFER_EVENT, log); TransferEventResponse typedResponse = new TransferEventResponse(); typedResponse.log = log; typedResponse._from = (String) eventValues.getIndexedValues().get(0).getValue(); typedResponse._to = (String) eventValues.getIndexedValues().get(1).getValue(); typedResponse._value = (BigInteger) eventValues.getNonIndexedValues().get(0).getValue(); return typedResponse; }
A30: 28 | B30: google_ground-android | C30: https://github.com/google/ground-android/commit/0b903a68cb0a354c189d316bcc55f49db847d8f5 | D30: https://github.com/google/ground-android/commit/bf530f0bcf45efc2a58f93eed94827bb747a580a | E30: Rx fixit for MainViewModel | F30: Do sync work in subscribe | G30: 機能変更 | H30: 0b903a68cb0a354c189d316bcc55f49db847d8f5 | I30: gnd/src/main/java/com/google/android/gnd/MainViewModel.java | J30: (110, 9) | K30: gnd/src/main/java/com/google/android/gnd/MainViewModel.java | L30: (163, 5) | M30: bf530f0bcf45efc2a58f93eed94827bb747a580a | N30: gnd/src/main/java/com/google/android/gnd/MainViewModel.java | O30: (166, 23) | P30: gnd/src/main/java/com/google/android/gnd/MainViewModel.java | R30: return userRepository.saveUser(user).doOnComplete(this::onSignedIn); | S30: return userRepository .saveUser(user) .doOnComplete(this::hideProgressDialog) .doOnComplete(() -> navigator.navigate(HomeScreenFragmentDirections.showHomeScreen())); | T30: () -> navigator.navigate(HomeScreenFragmentDirections.showHomeScreen())
A31: 29 | B31: xwiki_xwiki-platform | C31: https://github.com/xwiki/xwiki-platform/commit/3ffcfd3e337ee0832e4d130af489f9ded93799ff | D31: https://github.com/xwiki/xwiki-platform/commit/fbbe855b8a0d95622fca9ae49b29d9320b661bf7 | E31: XWIKI-6073: Browsers usually cache JS/CSS resources even if they have changed * Fix EditRightsPane to not rely anymore on a full resource URL | F31: XWIKI-6073: Browsers usually cache JS/CSS resources even if they have changed * Create a new dedicated method for attribute value in XWikiWebDriver | G31: 差し戻し | H31: 3ffcfd3e337ee0832e4d130af489f9ded93799ff | I31: xwiki-platform-core/xwiki-platform-test/xwiki-platform-test-ui/src/main/java/org/xwiki/test/ui/po/EditRightsPane.java | J31: (157, 13) | K31: xwiki-platform-core/xwiki-platform-test/xwiki-platform-test-ui/src/main/java/org/xwiki/test/ui/po/EditRightsPane.java | L31: (165, 13) | M31: fbbe855b8a0d95622fca9ae49b29d9320b661bf7 | N31: xwiki-platform-core/xwiki-platform-test/xwiki-platform-test-ui/src/main/java/org/xwiki/test/ui/po/EditRightsPane.java | O31: (165, 44) | P31: xwiki-platform-core/xwiki-platform-test/xwiki-platform-test-ui/src/main/java/org/xwiki/test/ui/po/EditRightsPane.java | R31: getDriver().waitUntilElementEndsWithAttributeValue(buttonLocator, "src", currentState.imageURL); | S31: getDriver().waitUntilCondition(webDriver -> { // starting with 11.1RC1 the resource URLs can now contain a query parameter to avoid cache issue // so we cannot rely to a full URL anymore return webDriver.findElement(buttonLocator).getAttribute("src").contains(currentState.imageURL); }); | T31: webDriver -> { // starting with 11.1RC1 the resource URLs can now contain a query parameter to avoid cache issue // so we cannot rely to a full URL anymore return webDriver.findElement(buttonLocator).getAttribute("src").contains(currentState.imageURL); }
A32: 30 | B32: ankidroid_Anki-Android | C32: https://github.com/ankidroid/Anki-Android/commit/090c130f326316a41aa1770357b239274f8639a1 | D32: https://github.com/ankidroid/Anki-Android/commit/46e8e35436c9f8d809036dd6982e0821b72241f3 | E32: Fix all deprecation, or note related github issue | F32: Readability improvements in NavigationDrawerActivity - Wrap getting current SharedPreferences in a method - Move applying a night mode change into separate function - Small reformat of comments and whitespace (automatically done by Android Studio). This is the no-op part refactoring part of PR #5686. I'd like to get it submitted separately so that the PR itself (when finished) is smaller. | G32: 誤検出 | H32: 090c130f326316a41aa1770357b239274f8639a1 | I32: AnkiDroid/src/main/java/com/ichi2/anki/NavigationDrawerActivity.java | J32: (96, 9) | K32: AnkiDroid/src/main/java/com/ichi2/anki/NavigationDrawerActivity.java | L32: (88, 9) | M32: 46e8e35436c9f8d809036dd6982e0821b72241f3 | N32: AnkiDroid/src/main/java/com/ichi2/anki/NavigationDrawerActivity.java | O32: (96, 53) | P32: AnkiDroid/src/main/java/com/ichi2/anki/NavigationDrawerActivity.java | R32: mNightModeSwitch.setOnCheckedChangeListener(new CompoundButton.OnCheckedChangeListener() { @Override public void onCheckedChanged(CompoundButton buttonView, boolean isChecked) { if (isChecked) { Timber.i("StudyOptionsFragment:: Night mode was enabled"); preferences.edit().putBoolean("invertedColors", true).commit(); } else { Timber.i("StudyOptionsFragment:: Night mode was disabled"); preferences.edit().putBoolean("invertedColors", false).commit(); } restartActivityInvalidateBackstack(NavigationDrawerActivity.this); } }); | S32: mNightModeSwitch.setOnCheckedChangeListener((buttonView, isChecked) -> { if (isChecked) { Timber.i("StudyOptionsFragment:: Night mode was enabled"); preferences.edit().putBoolean("invertedColors", true).apply(); } else { Timber.i("StudyOptionsFragment:: Night mode was disabled"); preferences.edit().putBoolean("invertedColors", false).apply(); } restartActivityInvalidateBackstack(NavigationDrawerActivity.this); }); | T32: (buttonView, isChecked) -> { if (isChecked) { Timber.i("StudyOptionsFragment:: Night mode was enabled"); preferences.edit().putBoolean("invertedColors", true).apply(); } else { Timber.i("StudyOptionsFragment:: Night mode was disabled"); preferences.edit().putBoolean("invertedColors", false).apply(); } restartActivityInvalidateBackstack(NavigationDrawerActivity.this); }
A33: 31 | B33: cloudfoundry_uaa | C33: https://github.com/cloudfoundry/uaa/commit/fc5a2c9c95569b95001d4aefdbe4c64f7edf733c | D33: https://github.com/cloudfoundry/uaa/commit/32076714cf4b702043af733d1b0ac20045bef0db | E33: Removed JWE tests and added JWS-specific test - UAA does not accept or produce JWE tokens, so no need for any specific logic for now [#161025678] https://www.pivotaltracker.com/story/show/161025678 Signed-off-by: Jaskanwal Pawar <jpawar@pivotal.io> Co-authored-by: Jaskanwal Pawar <jpawar@pivotal.io> | F33: JOSE Header defined in JWS spec should ignore all non understood parameters as defined in RFC https://tools.ietf.org/html/rfc7515#section-4 (#1709) | G33: 機能変更 | H33: fc5a2c9c95569b95001d4aefdbe4c64f7edf733c | I33: server/src/test/java/org/cloudfoundry/identity/uaa/oauth/jwt/JwtHeaderHelperTest.java | J33: (84, 13) | K33: server/src/test/java/org/cloudfoundry/identity/uaa/oauth/jwt/JwtHeaderHelperTest.java | L33: (58, 13) | M33: 32076714cf4b702043af733d1b0ac20045bef0db | N33: server/src/test/java/org/cloudfoundry/identity/uaa/oauth/jwt/JwtHeaderHelperTest.java | O33: (89, 54) | P33: server/src/test/java/org/cloudfoundry/identity/uaa/oauth/jwt/JwtHeaderHelperTest.java | R33: JwtHeaderHelper.create(asBase64(objectNode.toString())); | S33: Assertions.assertThrows(Exception.class, () -> JwtHeaderHelper.create(asBase64(objectNode.toString())) ); | T33: () -> JwtHeaderHelper.create(asBase64(objectNode.toString()))
... A57: 55 | B57: google_ground-android | C57: https://github.com/google/ground-android/commit/34465bb2b296f207358cd45564353ba1a6a6a6bd | D57: https://github.com/google/ground-android/commit/7012d3787bb7c0d9566dd96679d152fae2d7a49a | E57: Load from db if firestore is unavailable | F57: WIP project activation flow cleanup and ideas | G57: 機能変更 | H57: 34465bb2b296f207358cd45564353ba1a6a6a6bd | I57: gnd/src/main/java/com/google/android/gnd/repository/DataRepository.java | J57: (150, 5) | K57: gnd/src/main/java/com/google/android/gnd/repository/DataRepository.java | L57: (148, 5) | M57: 7012d3787bb7c0d9566dd96679d152fae2d7a49a | N57: gnd/src/main/java/com/google/android/gnd/repository/DataRepository.java | O57: (152, 13) | P57: gnd/src/main/java/com/google/android/gnd/repository/DataRepository.java | R57: return loadProjects(user) .map(Persistable::loaded) .onErrorReturn(Persistable::error) .toObservable() .startWith(Persistable.loading()); | S57: return remoteDataStore .loadProjectSummaries(user) .onErrorResumeNext( throwable -> { if (throwable instanceof FirebaseFirestoreException) { return localDataStore.getProjects(); } return Single.error(throwable); }) .map(Persistable::loaded) .onErrorReturn(Persistable::error) .toObservable() .startWith(Persistable.loading()); | T57: throwable -> { if (throwable instanceof FirebaseFirestoreException) { return localDataStore.getProjects(); } return Single.error(throwable); }
A58: 56 | B58: xwiki_xwiki-platform | C58: https://github.com/xwiki/xwiki-platform/commit/d12e21704e31a2ff7790cd2c368ec89202371511 | D58: https://github.com/xwiki/xwiki-platform/commit/4c8f709efaa10e435d7631c863f5d94108a6dd76 | E58: [misc] Improve codestyle | F58: XCOMMONS-800: Find a way to cache Velocity "AST" * refactor support for macros.vm | H58: d12e21704e31a2ff7790cd2c368ec89202371511 | I58: xwiki-platform-core/xwiki-platform-oldcore/src/main/java/com/xpn/xwiki/render/DefaultVelocityManager.java | J58: (300, 29) | K58: xwiki-platform-core/xwiki-platform-oldcore/src/main/java/com/xpn/xwiki/render/DefaultVelocityManager.java | L58: (297, 29) | M58: 4c8f709efaa10e435d7631c863f5d94108a6dd76 | N58: xwiki-platform-core/xwiki-platform-oldcore/src/main/java/com/xpn/xwiki/render/DefaultVelocityManager.java | O58: (296, 54) | P58: xwiki-platform-core/xwiki-platform-oldcore/src/main/java/com/xpn/xwiki/render/DefaultVelocityManager.java | R58: this.suExecutor.call(new Callable<XDOM>() { @Override public XDOM call() throws Exception { finalVelocityEngine.evaluate(new VelocityContext(), NullWriter.NULL_WRITER, "", template.getContent().getContent()); return null; } }, template.getContent().getAuthorReference()); | S58: this.suExecutor.call(() -> { finalVelocityEngine.evaluate(new VelocityContext(), NullWriter.NULL_WRITER, "", template.getContent().getContent()); return null; }, template.getContent().getAuthorReference()); | T58: () -> { finalVelocityEngine.evaluate(new XWikiVelocityContext(), NullWriter.NULL_WRITER, "", template.getContent().getContent()); return null; }
A59: 57 | B59: mpusher_mpush | C59: https://github.com/mpusher/mpush/commit/79f965810348651140e7c0fcbf36e2a003e2ad68 | D59: https://github.com/mpusher/mpush/commit/8b6d2b2e6f76025709cbd62086657bb749c90f55 | E59: 增加支持单台机器启动多个实例 | F59: 线程优化及日志优化 | H59: 79f965810348651140e7c0fcbf36e2a003e2ad68 | I59: mpush-client/src/main/java/com/mpush/client/gateway/connection/GatewayUDPConnectionFactory.java | J59: (94, 13) | K59: mpush-client/src/main/java/com/mpush/client/gateway/connection/GatewayUDPConnectionFactory.java | L59: (95, 9) | M59: 8b6d2b2e6f76025709cbd62086657bb749c90f55 | N59: mpush-client/src/main/java/com/mpush/client/gateway/connection/GatewayUDPConnectionFactory.java | O59: (96, 26) | P59: mpush-client/src/main/java/com/mpush/client/gateway/connection/GatewayUDPConnectionFactory.java | R59: holder.set(recipient); | S59: creator.compose(this::getConnection) .andThen(message -> (T) message.setRecipient(recipient)) .andThen(sender) .apply(hostAndPort); | T59: message -> (T) message.setRecipient(recipient)
A60: 58 | B60: cloudfoundry_uaa | C60: https://github.com/cloudfoundry/uaa/commit/ec42a0c112a54109450251542666f7e0a4c0ac7e | D60: https://github.com/cloudfoundry/uaa/commit/3be909be79ffe796e07d5100bd48b646326bb61c | E60: Migrate to Junit 5 # Conflicts: # server/src/test/java/org/cloudfoundry/identity/uaa/db/DbMigrationIntegrationTestParent.java # server/src/test/java/org/cloudfoundry/identity/uaa/db/HsqlDbMigrationIntegrationTest.java # server/src/test/java/org/cloudfoundry/identity/uaa/db/MySqlDbMigrationIntegrationTest.java # server/src/test/java/org/cloudfoundry/identity/uaa/db/PostgresDbMigrationIntegrationTest.java # server/src/test/java/org/cloudfoundry/identity/uaa/db/TableAndColumnNormalizationTest.java | F60: Migrate to AssertJ # Conflicts: # uaa/src/test/java/org/cloudfoundry/identity/uaa/integration/feature/LdapLoginIT.java # uaa/src/test/java/org/cloudfoundry/identity/uaa/mock/providers/IdentityProviderEndpointsMockMvcTests.java # Conflicts: # uaa/src/test/java/org/cloudfoundry/identity/uaa/mock/audit/AuditCheckMockMvcTests.java | H60: ec42a0c112a54109450251542666f7e0a4c0ac7e | I60: model/src/test/java/org/cloudfoundry/identity/uaa/oauth/client/http/OAuth2ErrorHandlerTests.java | J60: (159, 9) | K60: model/src/test/java/org/cloudfoundry/identity/uaa/oauth/client/http/OAuth2ErrorHandlerTests.java | L60: (156, 9) | M60: 3be909be79ffe796e07d5100bd48b646326bb61c | N60: model/src/test/java/org/cloudfoundry/identity/uaa/oauth/client/http/OAuth2ErrorHandlerTests.java | O60: (156, 54) | P60: model/src/test/java/org/cloudfoundry/identity/uaa/oauth/client/http/OAuth2ErrorHandlerTests.java | R60: expected.expect(HttpServerErrorException.class); | S60: assertThrows(HttpServerErrorException.class, () -> { HttpHeaders headers = new HttpHeaders(); ClientHttpResponse response = new TestClientHttpResponse(headers, 500); handler.handleError(response); }); | T60: () -> { HttpHeaders headers = new HttpHeaders(); ClientHttpResponse response = new TestClientHttpResponse(headers, 500); handler.handleError(response); }
A61: 59 | B61: xwiki_xwiki-platform | C61: https://github.com/xwiki/xwiki-platform/commit/68ddf40a36cad52ea18eaa826f1680ad0ce88296 | D61: https://github.com/xwiki/xwiki-platform/commit/6650b55349e33ca8051cf6f488d19eaeaa06a08e | E61: XWIKI-8286: Upgrade to Hibernate 5.4.0 * Upgrade to Hibernate 4.0.1.Final. * Use the new hibernate package names. * Replace the 'session.connection()' with either the 'session.doWork()' method or by directly creating an sql query. * Adapt the DBCPConnectionProvider using C3P0ConnectionProvider as a model. | F61: XWIKI-8286: Upgrade to Hibernate 5.4.1 | H61: 68ddf40a36cad52ea18eaa826f1680ad0ce88296 | I61: xwiki-platform-core/xwiki-platform-oldcore/src/main/java/com/xpn/xwiki/store/XWikiHibernateBaseStore.java | J61: (401, 13) | K61: xwiki-platform-core/xwiki-platform-oldcore/src/main/java/com/xpn/xwiki/store/XWikiHibernateBaseStore.java | L61: (397, 13) | M61: 6650b55349e33ca8051cf6f488d19eaeaa06a08e | N61: xwiki-platform-core/xwiki-platform-oldcore/src/main/java/com/xpn/xwiki/store/XWikiHibernateBaseStore.java | O61: (403, 28) | P61: xwiki-platform-core/xwiki-platform-oldcore/src/main/java/com/xpn/xwiki/store/XWikiHibernateBaseStore.java | R61: meta = new DatabaseMetadata(connection, this.store.getDialect()); | S61: session.doWork(connection -> { DatabaseMetadata meta = new DatabaseMetadata(connection, this.store.getDialect()); schemaSQL.set(config.generateSchemaUpdateScript(this.store.getDialect(), meta)); // In order to circumvent a bug in Hibernate (See the javadoc of XWHS#createHibernateSequenceIfRequired // for details), we need to ensure that Hibernate will create the "hibernate_sequence" sequence. createHibernateSequenceIfRequired(schemaSQL.get(), contextSchema, session); }); | T61: connection -> { config. MetadataSources metadata = new MetadataSources(new StandardServiceRegistryBuilder().); schemaSQL.set(config.generateSchemaUpdateScript(this.store.getDialect(), meta)); // In order to circumvent a bug in Hibernate (See the javadoc of XWHS#createHibernateSequenceIfRequired // for details), we need to ensure that Hibernate will create the "hibernate_sequence" sequence. createHibernateSequenceIfRequired(schemaSQL.get(), contextSchema, session); }
A62: 60 | B62: google_ground-android | C62: https://github.com/google/ground-android/commit/71bcbc0de7f929f889cb2898b10dcef77cc200b0 | D62: https://github.com/google/ground-android/commit/67a88a320ed374ab1b638f071931e41ee64e3061 | E62: Ensure photo results are only processed once | F62: Handle photo result in appropriate VM | H62: 71bcbc0de7f929f889cb2898b10dcef77cc200b0 | I62: gnd/src/main/java/com/google/android/gnd/ui/editobservation/EditObservationFragment.java | J62: (331, 5) | K62: gnd/src/main/java/com/google/android/gnd/ui/editobservation/EditObservationFragment.java | L62: (332, 5) | M62: 67a88a320ed374ab1b638f071931e41ee64e3061 | N62: gnd/src/main/java/com/google/android/gnd/ui/editobservation/EditObservationFragment.java | O62: (337, 20) | P62: gnd/src/main/java/com/google/android/gnd/ui/editobservation/EditObservationFragment.java | R62: viewModel .getLastPhotoResult() .as(autoDisposable(getViewLifecycleOwner())) .subscribe(fieldViewModel::onPhotoResult); | S62: viewModel .getLastPhotoResult() .as(autoDisposable(getViewLifecycleOwner())) .subscribe(event -> event.ifUnhandled(fieldViewModel::onPhotoResult)); | T62: event -> event.ifUnhandled(fieldViewModel::onPhotoResult)
A63: 61 | B63: ankidroid_Anki-Android | C63: https://github.com/ankidroid/Anki-Android/commit/090c130f326316a41aa1770357b239274f8639a1 | D63: https://github.com/ankidroid/Anki-Android/commit/8a571eeae104f8cd0ffb11d549b0b06325f3a56c | E63: Fix all deprecation, or note related github issue | F63: Refactor no-browser adaptations to AnkiActivity, apply for TTS * NF DeckPicker: Extract openHelpUrl * Fix exception on opening help URL * NF ReadText: extract openTtsHelpUrl * openTtsHelpUrl: avoid no browser crash * Extract no web browser logic to openUrl Refactoring - reduces code and ensures we don't miss any instances | H63: 090c130f326316a41aa1770357b239274f8639a1 | I63: AnkiDroid/src/main/java/com/ichi2/anki/MyAccount.java | J63: (170, 17) | K63: AnkiDroid/src/main/java/com/ichi2/anki/MyAccount.java | L63: (153, 9) | M63: 8a571eeae104f8cd0ffb11d549b0b06325f3a56c | N63: AnkiDroid/src/main/java/com/ichi2/anki/MyAccount.java | O63: (159, 45) | P63: AnkiDroid/src/main/java/com/ichi2/anki/MyAccount.java | R63: openUrl(Uri.parse(getResources().getString(R.string.register_url))); | S63: signUpButton.setOnClickListener(v -> openUrl(Uri.parse(getResources().getString(R.string.register_url)))); | T63: v -> openUrl(Uri.parse(getResources().getString(R.string.register_url)))
A64: 62 | B64: web3j_web3j | C64: https://github.com/web3j/web3j/commit/a4ab324a089fc0a5562883b8696dcd50743988e2 | D64: https://github.com/web3j/web3j/commit/408214a9a8633be786a844a3a2a291763e70a12d | E64: migrate to RxJava2 (no method or class renaming) | F64: - Updating all "3.6.0" references to "4.0.0" - Addressing some (not all) PR feedback - Regenerating code | H64: a4ab324a089fc0a5562883b8696dcd50743988e2 | I64: core/src/main/java/org/web3j/ens/contracts/generated/ENS.java | J64: (73, 9) | K64: core/src/main/java/org/web3j/ens/contracts/generated/ENS.java | L64: (71, 9) | M64: 408214a9a8633be786a844a3a2a291763e70a12d | N64: core/src/main/java/org/web3j/ens/contracts/generated/ENS.java | O64: (72, 49) | P64: core/src/main/java/org/web3j/ens/contracts/generated/ENS.java | R64: return web3j.ethLogObservable(filter).map(new Func1<Log, NewOwnerEventResponse>() { @Override public NewOwnerEventResponse call(Log log) { EventValues eventValues = extractEventParameters(event, log); NewOwnerEventResponse typedResponse = new NewOwnerEventResponse(); typedResponse.node = (byte[]) eventValues.getIndexedValues().get(0).getValue(); typedResponse.label = (byte[]) eventValues.getIndexedValues().get(1).getValue(); typedResponse.owner = (String) eventValues.getNonIndexedValues().get(0).getValue(); return typedResponse; } }); | S64: return web3j.ethLogObservable(filter).map(log -> { EventValues eventValues = extractEventParameters(event, log); NewOwnerEventResponse typedResponse = new NewOwnerEventResponse(); typedResponse.node = (byte[]) eventValues.getIndexedValues().get(0).getValue(); typedResponse.label = (byte[]) eventValues.getIndexedValues().get(1).getValue(); typedResponse.owner = (String) eventValues.getNonIndexedValues().get(0).getValue(); return typedResponse; }); | T64: log -> { EventValues eventValues = extractEventParameters(event, log); NewOwnerEventResponse typedResponse = new NewOwnerEventResponse(); typedResponse.node = (byte[]) eventValues.getIndexedValues().get(0).getValue(); typedResponse.label = (byte[]) eventValues.getIndexedValues().get(1).getValue(); typedResponse.owner = (String) eventValues.getNonIndexedValues().get(0).getValue(); return typedResponse; }
A65: 63 | B65: obiba_magma | C65: https://github.com/obiba/magma/commit/c86274dbe4eb4606506caa15c0748239197cf8ed | D65: https://github.com/obiba/magma/commit/8cccdc90e4698a270ea7a306db79e67a25e94646 | E65: java8itifation | F65: Entities paging with views | H65: c86274dbe4eb4606506caa15c0748239197cf8ed | I65: magma-api/src/main/java/org/obiba/magma/views/JoinTable.java | J65: (195, 7) | K65: magma-api/src/main/java/org/obiba/magma/views/JoinTable.java | L65: (178, 5) | M65: 8cccdc90e4698a270ea7a306db79e67a25e94646 | N65: magma-api/src/main/java/org/obiba/magma/views/JoinTable.java | O65: (205, 30) | P65: magma-api/src/main/java/org/obiba/magma/views/JoinTable.java | R65: entities.addAll(table.getVariableEntities()); | S65: getTables().parallelStream().forEach(table -> entities.addAll(table.getVariableEntities())); | T65: table -> table.getVariableEntities().stream().filter(e -> !entities.contains(e)).forEach(entities::add)
A66: 64 | B66: games647_FastLogin | C66: https://github.com/games647/FastLogin/commit/f40e787b559b60918600f6fe6376b3011525e06d | D66: https://github.com/games647/FastLogin/commit/a3bf8759764bf4654ee00a96edfaae97dfb61805 | E66: Delay force action until PlayerJoinEvent is fired Fixes Paper async chunk loading -> delayed PlayerJoinEvent (Related #331) | F66: Encapsulate floodgate hooks Related #619 Related #620 | H66: f40e787b559b60918600f6fe6376b3011525e06d | I66: bukkit/src/main/java/com/github/games647/fastlogin/bukkit/listener/ConnectionListener.java | J66: (41, 9) | K66: bukkit/src/main/java/com/github/games647/fastlogin/bukkit/listener/ConnectionListener.java | L66: (43, 9) | M66: a3bf8759764bf4654ee00a96edfaae97dfb61805 | N66: bukkit/src/main/java/com/github/games647/fastlogin/bukkit/listener/ConnectionListener.java | O66: (71, 52) | P66: bukkit/src/main/java/com/github/games647/fastlogin/bukkit/listener/ConnectionListener.java | R66: removeBlacklistStatus(player); | S66: Bukkit.getScheduler().runTaskLater(plugin, () -> { // session exists so the player is ready for force login // cases: Paper (firing BungeeCord message before PlayerJoinEvent) or not running BungeeCord and already // having the login session from the login process BukkitLoginSession session = plugin.getSession(player.getAddress()); if (session != null) { Runnable forceLoginTask = new ForceLoginTask(plugin.getCore(), player, session); Bukkit.getScheduler().runTaskAsynchronously(plugin, forceLoginTask); } plugin.getBungeeManager().markJoinEventFired(player); // delay the login process to let auth plugins initialize the player // Magic number however as there is no direct event from those plugins }, DELAY_LOGIN); | T66: () -> { // session exists so the player is ready for force login // cases: Paper (firing BungeeCord message before PlayerJoinEvent) or not running BungeeCord and already // having the login session from the login process BukkitLoginSession session = plugin.getSession(player.getAddress()); boolean isFloodgateLogin = false; if (Bukkit.getServer().getPluginManager().isPluginEnabled("floodgate")) { FloodgatePlayer floodgatePlayer = FloodgateApi.getInstance().getPlayer(player.getUniqueId()); if (floodgatePlayer != null) { isFloodgateLogin = true; Runnable floodgateAuthTask = new FloodgateAuthTask(plugin.getCore(), player, floodgatePlayer); Bukkit.getScheduler().runTaskAsynchronously(plugin, floodgateAuthTask); } } if (!isFloodgateLogin) { if (session == null) { String sessionId = plugin.getSessionId(player.getAddress()); plugin.getLog().info("No on-going login session for player: {} with ID {}", player, sessionId); } else { Runnable forceLoginTask = new ForceLoginTask(plugin.getCore(), player, session); Bukkit.getScheduler().runTaskAsynchronously(plugin, forceLoginTask); } } plugin.getBungeeManager().markJoinEventFired(player); // delay the login process to let auth plugins initialize the player // Magic number however as there is no direct event from those plugins }
A67: 65 | B67: kitodo_kitodo-production | C67: https://github.com/kitodo/kitodo-production/commit/f26fd645cd910cc0f047727dcbb4a681dbca17ac | D67: https://github.com/kitodo/kitodo-production/commit/6b86cbd998ef2dedd11e5ea458a1764bec0821dc | E67: Add and improve tests in Data Management module | F67: Use high level rest client in Data Management module | H67: f26fd645cd910cc0f047727dcbb4a681dbca17ac | I67: Kitodo-DataManagement/src/test/java/org/kitodo/data/elasticsearch/search/SearcherIT.java | J67: (133, 9) | K67: Kitodo-DataManagement/src/test/java/org/kitodo/data/elasticsearch/search/SearcherIT.java | L67: (86, 9) | M67: 6b86cbd998ef2dedd11e5ea458a1764bec0821dc | N67: Kitodo-DataManagement/src/test/java/org/kitodo/data/elasticsearch/search/SearcherIT.java | O67: (87, 13) | P67: Kitodo-DataManagement/src/test/java/org/kitodo/data/elasticsearch/search/SearcherIT.java | R67: count = jsonObject.getJsonNumber("value").longValue(); | S67: await().untilAsserted( () -> assertEquals("Incorrect result - count doesn't match to given number!", 4, searcher.aggregateDocuments(SearcherIT.query, aggregation).getJsonObject("count").getJsonNumber("value").longValue())); | T67: () -> assertEquals("Incorrect result - count doesn't match to given number!", 4, searcher.aggregateDocuments(SearcherIT.query, aggregation).getJsonObject("count").getJsonNumber("value").longValue())
A68: 66 | B68: epam_JDI | C68: https://github.com/epam/JDI/commit/094cceb2ec9d49f5be19fb0e6cfb927cc3451081 | D68: https://github.com/epam/JDI/commit/0b7e562370b290e36803d2ea752476d4d4acbe6b | E68: Correct verify layout feature and tests | F68: Add jdi winnium | H68: 094cceb2ec9d49f5be19fb0e6cfb927cc3451081 | I68: Java/Tests/jdi-uitest-webtests/src/test/java/com/epam/jdi/uitests/testing/unittests/tests/composite/LayoutVerificationTests.java | J68: (76, 9) | K68: Java/Tests/jdi-uitest-webtests/src/test/java/com/epam/jdi/uitests/testing/unittests/tests/composite/LayoutVerificationTests.java | L68: (68, 9) | M68: 0b7e562370b290e36803d2ea752476d4d4acbe6b | N68: Java/Tests/jdi-uitest-webtests/src/test/java/com/epam/jdi/uitests/testing/unittests/tests/composite/LayoutVerificationTests.java | O68: (68, 27) | P68: Java/Tests/jdi-uitest-webtests/src/test/java/com/epam/jdi/uitests/testing/unittests/tests/composite/LayoutVerificationTests.java | R68: Assert.assertTrue(homePage.verifyElementsOnPage(imgDirPath)); | S68: Assert.assertTrue(() -> homePage.verifyElementsOnPage(imgDirPath)); | T68: () -> homePage.verifyElementsOnPage(imgDirPath)
A69: 67 | B69: cloudfoundry_uaa | C69: https://github.com/cloudfoundry/uaa/commit/2644f537be1d123a4c5db04877070d1a112963c4 | D69: https://github.com/cloudfoundry/uaa/commit/2ffb7af271717920de5e34bdceff3e899f6f9370 | E69: Rework | F69: Fix: performance issue in MySQL * Revert "Merge pull request #2704 from cloudfoundry/fix/optimize-ids-users-endpoint" * This reverts commit 1324a81f8948250e993193f4be62dc5b9854965a, reversing changes made to b8826e1456b98ae179b85cab9e5261a64edc2d25. * The original PR is suspected to cause the performance issues. We will try to bring this change back later. | H69: 2644f537be1d123a4c5db04877070d1a112963c4 | I69: server/src/test/java/org/cloudfoundry/identity/uaa/scim/endpoints/UserIdConversionEndpointsTests.java | J69: (214, 9) | K69: server/src/test/java/org/cloudfoundry/identity/uaa/scim/endpoints/UserIdConversionEndpointsTests.java | L69: (189, 9) | M69: 2ffb7af271717920de5e34bdceff3e899f6f9370 | N69: server/src/test/java/org/cloudfoundry/identity/uaa/scim/endpoints/UserIdConversionEndpointsTests.java | O69: (190, 29) | P69: server/src/test/java/org/cloudfoundry/identity/uaa/scim/endpoints/UserIdConversionEndpointsTests.java | R69: endpoints.findUsers("id sq \"foo\"", "ascending", 0, 100, false); | S69: assertThatExceptionOfType(ScimException.class) .isThrownBy(() -> endpoints.findUsers(filter, "ascending", 0, 100, false)) .withMessageStartingWith("Invalid filter '"); | T69: () -> endpoints.findUsers(filter, "ascending", 0, 100, false)
... A100: 98 | B100: commercetools_commercetools-sunrise-java | C100: https://github.com/commercetools/commercetools-sunrise-java/commit/408e8a1e7d80ab57a6fde63605312641f64be8fc | D100: https://github.com/commercetools/commercetools-sunrise-java/commit/253b834f64e76d7bc7b5abd1c739b48326dfe640 | E100: Extract i18n from YAML into a class | F100: Move i18n resolver code from custom hbs helper | H100: 408e8a1e7d80ab57a6fde63605312641f64be8fc | I100: common/app/common/templates/CustomI18nHelper.java | J100: (54, 9) | K100: common/app/common/templates/CustomI18nHelper.java | L100: (31, 9) | M100: 253b834f64e76d7bc7b5abd1c739b48326dfe640 | N100: common/app/common/templates/CustomI18nHelper.java | O100: (34, 28) | P100: common/app/common/templates/CustomI18nHelper.java | R100: return (containsPlural) ? Optional.ofNullable(resolve(language, bundle, key + "_plural")).orElseGet(() -> resolve(language, bundle, key)) : resolve(language, bundle, key); | S100: return resolvePluralMessage(options, languageTag, i18nIdentifier) .orElseGet(() -> i18nUtils.resolve(languageTag, i18nIdentifier.bundle, i18nIdentifier.key).orElse(null)); | T100: () -> i18n.get(locales, i18nIdentifier.bundle, i18nIdentifier.key) .orElse(null)
A101: 99 | B101: cloudfoundry_uaa | C101: https://github.com/cloudfoundry/uaa/commit/de537f84a3cad98a6cd98613649bc074498f000a | D101: https://github.com/cloudfoundry/uaa/commit/208a340f5925336606dff571280c5aaa614ff092 | E101: Authenticate with external oauth provider with client context Signed-off-by: Madhura Bhave <mbhave@pivotal.io> | H101: de537f84a3cad98a6cd98613649bc074498f000a | I101: server/src/test/java/org/cloudfoundry/identity/uaa/config/IdentityProviderBootstrapTest.java | J101: (256, 13) | K101: server/src/test/java/org/cloudfoundry/identity/uaa/config/IdentityProviderBootstrapTest.java | L101: (260, 13) | M101: 208a340f5925336606dff571280c5aaa614ff092 | N101: server/src/test/java/org/cloudfoundry/identity/uaa/config/IdentityProviderBootstrapTest.java | O101: (376, 75) | P101: server/src/test/java/org/cloudfoundry/identity/uaa/config/IdentityProviderBootstrapTest.java | R101: assertEquals(oauthProvider, bootstrapOauthProvider.getConfig()); | S101: assertThat(oauthProviderConfig.values(), PredicateMatcher.<AbstractXOAuthIdentityProviderDefinition>has(c -> c.equals(bootstrapOauthProvider.getConfig()))); | T101: c -> c.equals(bootstrapOauthProvider.getConfig())
A102: 100 | B102: commercetools_commercetools-sunrise-java | C102: https://github.com/commercetools/commercetools-sunrise-java/commit/12e5799c4954cabdcb4b1703b4f9106922a89b73 | D102: https://github.com/commercetools/commercetools-sunrise-java/commit/77b7f40bf0babb0cf2eb24ece1b45edd6b1a64a5 | E102: Initialize context at the start of the test. And keep session clean after each test. | F102: Remove context for each test and use consumer. | H102: 12e5799c4954cabdcb4b1703b4f9106922a89b73 | I102: test/controllers/CountryOperationsTest.java | J102: (49, 9) | K102: test/controllers/CountryOperationsTest.java | L102: (67, 9) | M102: 77b7f40bf0babb0cf2eb24ece1b45edd6b1a64a5 | N102: test/controllers/CountryOperationsTest.java | O102: (62, 50) | P102: test/controllers/CountryOperationsTest.java | R102: setUp(configWithAvailableCountries("DE", "AT")); | S102: init(configWithAvailableCountries("DE", "AT"), Optional.empty(), () -> assertThat(operations.defaultCountry()).isEqualTo(DE) ); | T102: () -> assertThat(operations.defaultCountry()).isEqualTo(DE)
A103: 101 | B103: McJtyMods_RFToolsPower | C103: https://github.com/McJtyMods/RFToolsPower/commit/c7e7b22aabe51b581131fae7c95c4bd5ea2dd692 | D103: https://github.com/McJtyMods/RFToolsPower/commit/8d6866c553777c6cd45d4ee575fafe6461cb9083 | E103: Big cleanup on how GenericItemHandler instances are created. WIP | F103: More refactoring on GenericItemHandler | H103: c7e7b22aabe51b581131fae7c95c4bd5ea2dd692 | I103: src/main/java/mcjty/rftoolspower/modules/endergenic/blocks/PearlInjectorTileEntity.java | J103: (48, 5) | K103: src/main/java/mcjty/rftoolspower/modules/endergenic/blocks/PearlInjectorTileEntity.java | L103: (48, 5) | M103: 8d6866c553777c6cd45d4ee575fafe6461cb9083 | N103: src/main/java/mcjty/rftoolspower/modules/endergenic/blocks/PearlInjectorTileEntity.java | O103: (49, 97) | P103: src/main/java/mcjty/rftoolspower/modules/endergenic/blocks/PearlInjectorTileEntity.java | R103: @Cap(type = CapType.ITEMS_AUTOMATION) private final GenericItemHandler items = createItemHandler(); | S103: @Cap(type = CapType.ITEMS_AUTOMATION) private final GenericItemHandler items = GenericItemHandler.create(this, CONTAINER_FACTORY, (slot, stack) -> stack.getItem() == Items.ENDER_PEARL); | T103: (slot, stack) -> stack.getItem() == Items.ENDER_PEARL
A104: 102 | B104: xwiki_xwiki-platform | C104: https://github.com/xwiki/xwiki-platform/commit/103650db89d9c924abede07e4fc4246890f052cc | D104: https://github.com/xwiki/xwiki-platform/commit/dfba8556a4f8ff9b167ba4e4034e16195fd97d0a | E104: XWIKI-21880: Cannot delete user defined filters (#2881) * Refactor DefaultNotificationFilterPreferenceManager to never throw immediately an exception thrown by a provider, but to only do it if all providers failed * Provide a new test covering this behaviour * Small test improvment * Improve a bit the logic to use standard exception if there's only one provider | F104: XWIKI-22211: Deprecate NotificationFilterPreferenceProvider (#2882) * Deprecate and legacify NotificationFilterPreferenceProvider and NotificationFilterPreference#getProviderHint * Clean up all code relying on it simplifying a lot the implem of NotificationFilterPreference * Only valid usage of the providerHint was for checking if a filter preference was stored or not: replaced it with checking the ID of the filter * Fix bad prefix in filters internal ids * Fix typos | H104: 103650db89d9c924abede07e4fc4246890f052cc | I104: xwiki-platform-core/xwiki-platform-notifications/xwiki-platform-notifications-filters/xwiki-platform-notifications-filters-api/src/main/java/org/xwiki/notifications/filters/internal/DefaultNotificationFilterPreferenceManager.java | J104: (184, 17) | K104: xwiki-platform-core/xwiki-platform-notifications/xwiki-platform-notifications-filters/xwiki-platform-notifications-filters-api/src/main/java/org/xwiki/notifications/filters/internal/DefaultNotificationFilterPreferenceManager.java | L104: (236, 9) | M104: dfba8556a4f8ff9b167ba4e4034e16195fd97d0a | N104: xwiki-platform-core/xwiki-platform-notifications/xwiki-platform-notifications-filters/xwiki-platform-notifications-filters-api/src/main/java/org/xwiki/notifications/filters/internal/DefaultNotificationFilterPreferenceManager.java | O104: (236, 39) | P104: xwiki-platform-core/xwiki-platform-notifications/xwiki-platform-notifications-filters/xwiki-platform-notifications-filters-api/src/main/java/org/xwiki/notifications/filters/internal/DefaultNotificationFilterPreferenceManager.java | R104: provider.deleteFilterPreferences(user, filterPreferenceIds); | S104: this.providerExceptionWrapper(provider -> provider.deleteFilterPreferences(user, filterPreferenceIds), String.format("Error when trying to remove filter preferences %s for user [%s]", filterPreferenceIds, user)); | T104: provider -> provider.deleteFilterPreferences(user, filterPreferenceIds)
A105: 103 | B105: mpusher_mpush | C105: https://github.com/mpusher/mpush/commit/76aa1107551813285d546e538dff1a3bf60309c8 | D105: https://github.com/mpusher/mpush/commit/d0eb910c134b78ba10234787e4e1f25f7848f618 | E105: 增加Netty write-buffer-water-mark 配置 | F105: 增加PushCenter消息流转时间线, 方便监控消息的各个生命周期的耗时PushClient -> GatewayClient -> GatewayServer -> PushCenter -> ConnServer -> Client | H105: 76aa1107551813285d546e538dff1a3bf60309c8 | I105: mpush-core/src/main/java/com/mpush/core/push/GatewayPushListener.java | J105: (56, 13) | K105: mpush-core/src/main/java/com/mpush/core/push/GatewayPushListener.java | L105: (57, 13) | M105: d0eb910c134b78ba10234787e4e1f25f7848f618 | N105: mpush-core/src/main/java/com/mpush/core/push/GatewayPushListener.java | O105: (57, 40) | P105: mpush-core/src/main/java/com/mpush/core/push/GatewayPushListener.java | R105: OkMessage .from(message) .setData(message.userId + ',' + message.clientType) .sendRaw(); | S105: message.runInRequestThread(() -> OkMessage .from(message) .setData(message.userId + ',' + message.clientType) .sendRaw() ); | T105: () -> OkMessage .from(message) .setData(message.userId + ',' + message.clientType) .sendRaw()
A106: 104 | B106: NOVA-Team_NOVA-Core | C106: https://github.com/NOVA-Team/NOVA-Core/commit/547d3781082b18179d6ae67b66da13152b84605b | D106: https://github.com/NOVA-Team/NOVA-Core/commit/cf28661e2f2ceec2c2bc42e9d065c98a21b7f292 | E106: Remove FWNBTTagCompound | F106: Improvements to capabilities and world handling | H106: 547d3781082b18179d6ae67b66da13152b84605b | I106: minecraft/1.11.2/src/main/java/nova/core/wrapper/mc/forge/v1_11_2/wrapper/item/forward/IFWItem.java | J106: (53, 3) | K106: minecraft/1.11.2/src/main/java/nova/core/wrapper/mc/forge/v1_11_2/wrapper/item/forward/IFWItem.java | L106: (53, 3) | M106: cf28661e2f2ceec2c2bc42e9d065c98a21b7f292 | N106: minecraft/1.11.2/src/main/java/nova/core/wrapper/mc/forge/v1_11_2/wrapper/item/forward/IFWItem.java | O106: (53, 72) | P106: minecraft/1.11.2/src/main/java/nova/core/wrapper/mc/forge/v1_11_2/wrapper/item/forward/IFWItem.java | R106: Item item = (nbt instanceof FWNBTTagCompound ? ((FWNBTTagCompound)nbt).getItem() : ItemConverter.instance().toNova(stack)); | S106: Item item = ItemConverter.instance().popNativeConversion().orElseGet(() -> ItemConverter.instance().toNova(stack)); | T106: () -> ItemConverter.instance().toNova(stack)
A107: 105 | B107: cloudfoundry_uaa | C107: https://github.com/cloudfoundry/uaa/commit/ec42a0c112a54109450251542666f7e0a4c0ac7e | D107: https://github.com/cloudfoundry/uaa/commit/3be909be79ffe796e07d5100bd48b646326bb61c | E107: Migrate to Junit 5 # Conflicts: # server/src/test/java/org/cloudfoundry/identity/uaa/db/DbMigrationIntegrationTestParent.java # server/src/test/java/org/cloudfoundry/identity/uaa/db/HsqlDbMigrationIntegrationTest.java # server/src/test/java/org/cloudfoundry/identity/uaa/db/MySqlDbMigrationIntegrationTest.java # server/src/test/java/org/cloudfoundry/identity/uaa/db/PostgresDbMigrationIntegrationTest.java # server/src/test/java/org/cloudfoundry/identity/uaa/db/TableAndColumnNormalizationTest.java | F107: Migrate to AssertJ # Conflicts: # uaa/src/test/java/org/cloudfoundry/identity/uaa/integration/feature/LdapLoginIT.java # uaa/src/test/java/org/cloudfoundry/identity/uaa/mock/providers/IdentityProviderEndpointsMockMvcTests.java # Conflicts: # uaa/src/test/java/org/cloudfoundry/identity/uaa/mock/audit/AuditCheckMockMvcTests.java | H107: ec42a0c112a54109450251542666f7e0a4c0ac7e | I107: server/src/test/java/org/cloudfoundry/identity/uaa/oauth/provider/token/DefaultTokenServicesWithInMemoryTests.java | J107: (90, 9) | K107: server/src/test/java/org/cloudfoundry/identity/uaa/oauth/provider/token/DefaultTokenServicesWithInMemoryTests.java | L107: (76, 9) | M107: 3be909be79ffe796e07d5100bd48b646326bb61c | N107: server/src/test/java/org/cloudfoundry/identity/uaa/oauth/provider/token/DefaultTokenServicesWithInMemoryTests.java | O107: (76, 53) | P107: server/src/test/java/org/cloudfoundry/identity/uaa/oauth/provider/token/DefaultTokenServicesWithInMemoryTests.java | R107: expected.expect(AccountExpiredException.class); | S107: assertThrows(AccountExpiredException.class, () -> { OAuth2Authentication expectedAuthentication = new OAuth2Authentication(RequestTokenFactory.createOAuth2Request( "id", false, Collections.singleton("read")), new TestAuthentication("test2", false)); getTokenServices().setAuthenticationManager(new AuthenticationManager() { @Override public Authentication authenticate(Authentication authentication) throws AuthenticationException { throw new AccountExpiredException("Not valid"); } }); DefaultOAuth2AccessToken firstAccessToken = (DefaultOAuth2AccessToken) getTokenServices().createAccessToken( expectedAuthentication); assertNotNull(firstAccessToken.getRefreshToken()); TokenRequest tokenRequest = new TokenRequest(Collections.singletonMap("client_id", "id"), "id", null, null); getTokenServices().refreshAccessToken(firstAccessToken.getRefreshToken().getValue(), tokenRequest); }); | T107: () -> { OAuth2Authentication expectedAuthentication = new OAuth2Authentication(RequestTokenFactory.createOAuth2Request( "id", false, Collections.singleton("read")), new TestAuthentication("test2", false)); getTokenServices().setAuthenticationManager(new AuthenticationManager() { @Override public Authentication authenticate(Authentication authentication) throws AuthenticationException { throw new AccountExpiredException("Not valid"); } }); DefaultOAuth2AccessToken firstAccessToken = (DefaultOAuth2AccessToken) getTokenServices().createAccessToken( expectedAuthentication); assertNotNull(firstAccessToken.getRefreshToken()); TokenRequest tokenRequest = new TokenRequest(Collections.singletonMap("client_id", "id"), "id", null, null); getTokenServices().refreshAccessToken(firstAccessToken.getRefreshToken().getValue(), tokenRequest); }
A108: 106 | B108: commercetools_commercetools-sunrise-data | C108: https://github.com/commercetools/commercetools-sunrise-data/commit/4f16ae737d2f28dc7695e15a03f16a7bf9398cfb | D108: https://github.com/commercetools/commercetools-sunrise-data/commit/0be7add638b38be46a07e80c35e5b8b868f5cc5c | E108: Initial Test to check that reader restart on the last product with joyride channel | F108: Improve and clean code for AvailabilityPricesImportJob and its test | H108: 4f16ae737d2f28dc7695e15a03f16a7bf9398cfb | I108: importApp/src/test/java/com/commercetools/dataimport/joyrideavailability/AvailabilityPricesImportJobIntegrationTest.java | J108: (70, 9) | K108: importApp/src/test/java/com/commercetools/dataimport/joyrideavailability/AvailabilityPricesImportJobIntegrationTest.java | L108: (57, 9) | M108: 0be7add638b38be46a07e80c35e5b8b868f5cc5c | N108: importApp/src/test/java/com/commercetools/dataimport/joyrideavailability/AvailabilityPricesImportJobIntegrationTest.java | O108: (59, 51) | P108: importApp/src/test/java/com/commercetools/dataimport/joyrideavailability/AvailabilityPricesImportJobIntegrationTest.java | R108: sphereClient.executeBlocking(ChannelDeleteCommand.of(joyrideChannel)); | S108: withPriceWithJoyrideChannel(sphereClient, priceDraft -> { final AddPrice addPrice = AddPrice.of(product.getMasterData().getCurrent().getMasterVariant().getId(), priceDraft); Product updatedProduct = sphereClient.executeBlocking(ProductUpdateCommand.of(product, asList(addPrice, Publish.of()))); final Optional<ProductProjection> lastProductWithJoyrideChannel = findLastProductWithJoyrideChannel(sphereClient, 0L, productsCount - 1); assertThat(lastProductWithJoyrideChannel).isPresent(); assertThat(lastProductWithJoyrideChannel.get().getMasterVariant().getSku()).isEqualTo(product.getMasterData().getCurrent().getMasterVariant().getSku()); final Product productToDelete = sphereClient.executeBlocking(ProductUpdateCommand.of(updatedProduct, Unpublish.of())); sphereClient.executeBlocking(ProductDeleteCommand.of(productToDelete)); }); | T108: priceDraft -> { final AddPrice addPrice = AddPrice.of(product.getMasterData().getCurrent().getMasterVariant().getId(), priceDraft); Product updatedProduct = sphereClient.executeBlocking(ProductUpdateCommand.of(product, asList(addPrice, Publish.of()))); final Optional<ProductProjection> lastProductWithJoyrideChannel = findLastProductWithJoyrideChannel(sphereClient, 0L, productsCount - 1); assertThat(lastProductWithJoyrideChannel).isPresent(); assertThat(lastProductWithJoyrideChannel.get().getMasterVariant().getSku()).isEqualTo(product.getMasterData().getCurrent().getMasterVariant().getSku()); final Product productToDelete = sphereClient.executeBlocking(ProductUpdateCommand.of(updatedProduct, Unpublish.of())); sphereClient.executeBlocking(ProductDeleteCommand.of(productToDelete)); }
A109: 107 | B109: epam_JDI | C109: https://github.com/epam/JDI/commit/422deb9c767f09c1d07a5063f8cf8ce9d9184417 | D109: https://github.com/epam/JDI/commit/f1c6c47e44a1d4704627ecc8e027c3fe348f6ad8 | E109: Correct kill driver functionality | F109: fix issues | H109: 422deb9c767f09c1d07a5063f8cf8ce9d9184417 | I109: Java/JDI/jdi-uitest-web/src/main/java/com/epam/jdi/uitests/web/selenium/driver/WebDriverUtils.java | J109: (42, 17) | K109: Java/JDI/jdi-uitest-web/src/main/java/com/epam/jdi/uitests/web/selenium/driver/WebDriverUtils.java | L109: (37, 9) | M109: f1c6c47e44a1d4704627ecc8e027c3fe348f6ad8 | N109: Java/JDI/jdi-uitest-web/src/main/java/com/epam/jdi/uitests/web/selenium/driver/WebDriverUtils.java | O109: (57, 29) | P109: Java/JDI/jdi-uitest-web/src/main/java/com/epam/jdi/uitests/web/selenium/driver/WebDriverUtils.java | R109: WindowsUtils.killByName("geckodriver.exe"); | S109: asserter.ignore(() -> killByName("geckodriver.exe")); | T109: () -> killByName("geckodriver.exe")
A110: 108 | B110: wallabag_android-app | C110: https://github.com/wallabag/android-app/commit/1426843663255e1cdaa6b30c948db929102060c9 | D110: https://github.com/wallabag/android-app/commit/d99f03dbabb36719d25ed78f5ca8277cc35ed7aa | E110: Fix some obvious TTS warnings (no changes in logic) | F110: TTS: use MediaControllerCompat at least for callbacks | H110: 1426843663255e1cdaa6b30c948db929102060c9 | I110: app/src/main/java/fr/gaulupeau/apps/Poche/tts/TtsFragment.java | J110: (204, 9) | K110: app/src/main/java/fr/gaulupeau/apps/Poche/tts/TtsFragment.java | L110: (197, 9) | M110: d99f03dbabb36719d25ed78f5ca8277cc35ed7aa | N110: app/src/main/java/fr/gaulupeau/apps/Poche/tts/TtsFragment.java | O110: (211, 46) | P110: app/src/main/java/fr/gaulupeau/apps/Poche/tts/TtsFragment.java | R110: btnTTSFastForward.setOnClickListener(new View.OnClickListener() { @Override public void onClick(View v) { if (ttsService != null) { ttsService.fastForwardCmd(); } } }); | S110: btnTTSFastForward.setOnClickListener(v -> { if (ttsService != null) { ttsService.fastForwardCmd(); } }); | T110: v -> { if (ttsService != null) { ttsService.fastForwardCmd(); } }
A111: 109 | B111: TEAMMATES_teammates | C111: https://github.com/TEAMMATES/teammates/commit/e3f37427a10567edc89e97bcba936dfa5d290ee2 | D111: https://github.com/TEAMMATES/teammates/commit/298adc92bc9f307191c5b9304f737a5992cd5eaf | E111: [#8216] Java: Use Java 8 map.forEach to iterate through map entries (#8223) | F111: [#2776] Instructor: MCQ questions (single answer): support attaching weights to options (#8860) [#2776] Instructor: MCQ questions (single answer): support attaching weights to options (#8860) | H111: e3f37427a10567edc89e97bcba936dfa5d290ee2 | I111: src/main/java/teammates/common/datatransfer/questions/FeedbackMcqQuestionDetails.java | J111: (469, 13) | K111: src/main/java/teammates/common/datatransfer/questions/FeedbackMcqQuestionDetails.java | L111: (416, 9) | M111: 298adc92bc9f307191c5b9304f737a5992cd5eaf | N111: src/main/java/teammates/common/datatransfer/questions/FeedbackMcqQuestionDetails.java | O111: (415, 33) | P111: src/main/java/teammates/common/datatransfer/questions/FeedbackMcqQuestionDetails.java | R111: fragments.append(SanitizationHelper.sanitizeForCsv(entry.getKey())).append(',') .append(entry.getValue().toString()).append(',') .append(df.format(100 * (double) entry.getValue() / responses.size())).append(Const.EOL); | S111: answerFrequency.forEach((key, value) -> fragments.append(Templates.populateTemplate(FormTemplates.MCQ_RESULT_STATS_OPTIONFRAGMENT, Slots.MCQ_CHOICE_VALUE, SanitizationHelper.sanitizeForHtml(key), Slots.COUNT, value.toString(), Slots.PERCENTAGE, df.format(100 * (double) value / responses.size())))); | T111: (key, value) -> fragments.append(Templates.populateTemplate(FormTemplates.MCQ_RESULT_STATS_OPTIONFRAGMENT, Slots.MCQ_CHOICE_VALUE, SanitizationHelper.sanitizeForHtml(key), Slots.COUNT, value.toString(), Slots.PERCENTAGE, df.format(100 * (double) value / responses.size())))
A112: 110 | B112: vert-x3_vertx-mail-client | C112: https://github.com/vert-x3/vertx-mail-client/commit/37b4f864f9c66e569546f55b8e3c495b187a53f5 | D112: https://github.com/vert-x3/vertx-mail-client/commit/11ea6338a0f44dfa4c47197112b334f50283b6d2 | E112: properly added close handler pool.close method, changed the unit tests to use that for the most part changed comment line length limit in vertx-codestyle file Signed-off-by: alexlehm <alexlehm@gmail.com> | F112: added asserts about pool size to most tests using the pool | H112: 37b4f864f9c66e569546f55b8e3c495b187a53f5 | I112: vertx-mail-client/src/test/java/io/vertx/ext/mail/impl/SMTPConnectionPoolDummySMTPTest.java | J112: (56, 9) | K112: vertx-mail-client/src/test/java/io/vertx/ext/mail/impl/SMTPConnectionPoolDummySMTPTest.java | L112: (55, 9) | M112: 11ea6338a0f44dfa4c47197112b334f50283b6d2 | N112: vertx-mail-client/src/test/java/io/vertx/ext/mail/impl/SMTPConnectionPoolDummySMTPTest.java | O112: (55, 20) | P112: vertx-mail-client/src/test/java/io/vertx/ext/mail/impl/SMTPConnectionPoolDummySMTPTest.java | R112: async.complete(); | S112: pool.close(v -> async.complete()); | T112: v -> async.complete()
A113: 111 | B113: web3j_web3j | C113: https://github.com/web3j/web3j/commit/a4ab324a089fc0a5562883b8696dcd50743988e2 | D113: https://github.com/web3j/web3j/commit/408214a9a8633be786a844a3a2a291763e70a12d | E113: migrate to RxJava2 (no method or class renaming) | F113: - Updating all "3.6.0" references to "4.0.0" - Addressing some (not all) PR feedback - Regenerating code | H113: a4ab324a089fc0a5562883b8696dcd50743988e2 | I113: core/src/main/java/org/web3j/ens/contracts/generated/ENS.java | J113: (173, 9) | K113: core/src/main/java/org/web3j/ens/contracts/generated/ENS.java | L113: (162, 9) | M113: 408214a9a8633be786a844a3a2a291763e70a12d | N113: core/src/main/java/org/web3j/ens/contracts/generated/ENS.java | O113: (163, 49) | P113: core/src/main/java/org/web3j/ens/contracts/generated/ENS.java | R113: return web3j.ethLogObservable(filter).map(new Func1<Log, NewTTLEventResponse>() { @Override public NewTTLEventResponse call(Log log) { EventValues eventValues = extractEventParameters(event, log); NewTTLEventResponse typedResponse = new NewTTLEventResponse(); typedResponse.node = (byte[]) eventValues.getIndexedValues().get(0).getValue(); typedResponse.ttl = (BigInteger) eventValues.getNonIndexedValues().get(0).getValue(); return typedResponse; } }); | S113: return web3j.ethLogObservable(filter).map(log -> { EventValues eventValues = extractEventParameters(event, log); NewTTLEventResponse typedResponse = new NewTTLEventResponse(); typedResponse.node = (byte[]) eventValues.getIndexedValues().get(0).getValue(); typedResponse.ttl = (BigInteger) eventValues.getNonIndexedValues().get(0).getValue(); return typedResponse; }); | T113: log -> { EventValues eventValues = extractEventParameters(event, log); NewTTLEventResponse typedResponse = new NewTTLEventResponse(); typedResponse.node = (byte[]) eventValues.getIndexedValues().get(0).getValue(); typedResponse.ttl = (BigInteger) eventValues.getNonIndexedValues().get(0).getValue(); return typedResponse; }
... A135: 133 | B135: scenerygraphics_sciview | C135: https://github.com/scenerygraphics/sciview/commit/51800cc3236d760b722a096ef1dd521ffac3423f | D135: https://github.com/scenerygraphics/sciview/commit/4347e4ed2ab51a29ecb16734b3e31063e875785e | E135: SciView: apply code style formatter | F135: Enable multiple mouse controls without switching (#116) * Add controls for node and camera translation, arcball and fps at same time * Re-add floor logic fixes (overlooked during an ugly merge) * Add centerOnNode to SciView, utilize in all demos * Clean up commented and redundant code * Get javadoc to succeed | H135: 51800cc3236d760b722a096ef1dd521ffac3423f | I135: src/main/java/sc/iview/SciView.java | J135: (552, 13) | K135: src/main/java/sc/iview/SciView.java | L135: (597, 13) | M135: 4347e4ed2ab51a29ecb16734b3e31063e875785e | N135: src/main/java/sc/iview/SciView.java | O135: (594, 39) | P135: src/main/java/sc/iview/SciView.java | R135: Collections.sort( result, new Comparator<SelectResult>() { @Override public int compare( SelectResult lhs, SelectResult rhs ) { return lhs.getDistance() > rhs.getDistance() ? -1 : lhs.getDistance() < rhs.getDistance() ? 1 : 0; } } ); | S135: Collections.sort( result, ( lhs, rhs ) -> lhs.getDistance() > rhs.getDistance() ? -1 : lhs.getDistance() < rhs.getDistance() ? 1 : 0 ); | T135: ( lhs, rhs ) -> lhs.getDistance() > rhs.getDistance() ? -1 : lhs.getDistance() < rhs.getDistance() ? 1 : 0
A136: 134 | B136: cloudfoundry_uaa | C136: https://github.com/cloudfoundry/uaa/commit/5082fb81a17d1799e0ba23ee34d726b5f96b7917 | D136: https://github.com/cloudfoundry/uaa/commit/208a340f5925336606dff571280c5aaa614ff092 | E136: Simplify automatic IDP redirect [#117270251] https://www.pivotaltracker.com/story/show/117270251 Signed-off-by: Priyata Agrawal <pagrawal@pivotal.io> Signed-off-by: Jonathan Lo <jlo@us.ibm.com> | H136: 5082fb81a17d1799e0ba23ee34d726b5f96b7917 | I136: server/src/test/java/org/cloudfoundry/identity/uaa/login/LoginInfoEndpointTests.java | J136: (495, 9) | K136: server/src/test/java/org/cloudfoundry/identity/uaa/login/LoginInfoEndpointTests.java | L136: (494, 9) | M136: 208a340f5925336606dff571280c5aaa614ff092 | N136: server/src/test/java/org/cloudfoundry/identity/uaa/login/LoginInfoEndpointTests.java | O136: (728, 57) | P136: server/src/test/java/org/cloudfoundry/identity/uaa/login/LoginInfoEndpointTests.java | R136: assertEquals("my-client-awesome-idp1", clientIdp.getIdpEntityAlias()); | S136: assertThat(idpDefinitions, PredicateMatcher.<SamlIdentityProviderDefinition>has(c -> c.getIdpEntityAlias().equals("my-client-awesome-idp1"))); | T136: c -> c.getIdpEntityAlias().equals("my-client-awesome-idp1")
A137: 135 | B137: wallabag_android-app | C137: https://github.com/wallabag/android-app/commit/1426843663255e1cdaa6b30c948db929102060c9 | D137: https://github.com/wallabag/android-app/commit/d99f03dbabb36719d25ed78f5ca8277cc35ed7aa | E137: Fix some obvious TTS warnings (no changes in logic) | F137: TTS: use MediaControllerCompat at least for callbacks | H137: 1426843663255e1cdaa6b30c948db929102060c9 | I137: app/src/main/java/fr/gaulupeau/apps/Poche/tts/TtsFragment.java | J137: (194, 9) | K137: app/src/main/java/fr/gaulupeau/apps/Poche/tts/TtsFragment.java | L137: (190, 9) | M137: d99f03dbabb36719d25ed78f5ca8277cc35ed7aa | N137: app/src/main/java/fr/gaulupeau/apps/Poche/tts/TtsFragment.java | O137: (204, 45) | P137: app/src/main/java/fr/gaulupeau/apps/Poche/tts/TtsFragment.java | R137: btnTTSFastRewind.setOnClickListener(new View.OnClickListener() { @Override public void onClick(View v) { if (ttsService != null) { ttsService.rewindCmd(); } } }); | S137: btnTTSFastRewind.setOnClickListener(v -> { if (ttsService != null) { ttsService.rewindCmd(); } }); | T137: v -> { if (ttsService != null) { ttsService.rewindCmd(); } }
A138: 136 | B138: mpusher_mpush | C138: https://github.com/mpusher/mpush/commit/76aa1107551813285d546e538dff1a3bf60309c8 | D138: https://github.com/mpusher/mpush/commit/d0eb910c134b78ba10234787e4e1f25f7848f618 | E138: 增加Netty write-buffer-water-mark 配置 | F138: 增加PushCenter消息流转时间线, 方便监控消息的各个生命周期的耗时PushClient -> GatewayClient -> GatewayServer -> PushCenter -> ConnServer -> Client | H138: 76aa1107551813285d546e538dff1a3bf60309c8 | I138: mpush-core/src/main/java/com/mpush/core/push/GatewayPushListener.java | J138: (68, 13) | K138: mpush-core/src/main/java/com/mpush/core/push/GatewayPushListener.java | L138: (70, 13) | M138: d0eb910c134b78ba10234787e4e1f25f7848f618 | N138: mpush-core/src/main/java/com/mpush/core/push/GatewayPushListener.java | O138: (70, 40) | P138: mpush-core/src/main/java/com/mpush/core/push/GatewayPushListener.java | R138: OkMessage .from(message) .sendRaw(); | S138: message.runInRequestThread(() -> OkMessage .from(message) .sendRaw() ); | T138: () -> OkMessage .from(message) .sendRaw()
A139: 137 | B139: apache_jmeter | C139: https://github.com/apache/jmeter/commit/ffb2be0997bb10c18a46922da9d5b24e47c3b0d0 | D139: https://github.com/apache/jmeter/commit/f8b86b539b9c87ee6a4cee2cd078f660fc09d491 | E139: Sonar : Fix errors and code smells git-svn-id: https://svn.apache.org/repos/asf/jmeter/trunk@1775519 13f79535-47bb-0310-9956-ffa450edef68 Former-commit-id: d6198cdb07746ae94c0fa6a70b35559053721b63 | F139: Bug 58757 - Fix deprecated methods of HTTPCLIENT after migration to httpclient-4.5.X Also fix Bug 61664 Bug 61664 - HTTP Authorization Manager : Digest works only with legacy RFC 2069 , RFC 2617 is not implemented Contributed by UbikLoadPack Support Bugzilla Id: 58757 git-svn-id: https://svn.apache.org/repos/asf/jmeter/trunk@1825269 13f79535-47bb-0310-9956-ffa450edef68 Former-commit-id: 2ea4e5284754707b00b94923188662cedc7bc3e2 | H139: ffb2be0997bb10c18a46922da9d5b24e47c3b0d0 | I139: src/protocol/http/org/apache/jmeter/protocol/http/sampler/HTTPHC4Impl.java | J139: (190, 5) | K139: src/protocol/http/org/apache/jmeter/protocol/http/sampler/HTTPHC4Impl.java | L139: (186, 5) | M139: f8b86b539b9c87ee6a4cee2cd078f660fc09d491 | N139: src/protocol/http/org/apache/jmeter/protocol/http/sampler/HTTPHC4Impl.java | O139: (228, 68) | P139: src/protocol/http/org/apache/jmeter/protocol/http/sampler/HTTPHC4Impl.java | R139: private static final HttpRequestInterceptor METRICS_RESETTER = new HttpRequestInterceptor() { @Override public void process(HttpRequest request, HttpContext context) throws HttpException, IOException { HttpConnectionMetrics metrics = ((HttpConnection) context.getAttribute(HttpCoreContext.HTTP_CONNECTION)).getMetrics(); metrics.reset(); } }; | S139: private static final HttpRequestInterceptor METRICS_RESETTER = (HttpRequest request, HttpContext context) -> { HttpConnectionMetrics metrics = ((HttpConnection) context.getAttribute(HttpCoreContext.HTTP_CONNECTION)).getMetrics(); metrics.reset(); }; | T139: (HttpRequest request, HttpContext context) -> { HttpConnectionMetrics metrics = ((HttpConnection) context.getAttribute(HttpCoreContext.HTTP_CONNECTION)).getMetrics(); metrics.reset(); }
A140: 138 | B140: ankidroid_Anki-Android | C140: https://github.com/ankidroid/Anki-Android/commit/1aedc0a9cd8fab7302d25c93839dc96d161d27a8 | D140: https://github.com/ankidroid/Anki-Android/commit/78beef4bc78a9bbea9cf51e30f24a9a42e577c19 | E140: NF: Refactor to FunctionalInterfaces.Consumer | F140: NF: extract repositionCardsNoValidation Useful for testing | H140: 1aedc0a9cd8fab7302d25c93839dc96d161d27a8 | I140: AnkiDroid/src/main/java/com/ichi2/anki/CardBrowser.java | J140: (1019, 25) | K140: AnkiDroid/src/main/java/com/ichi2/anki/CardBrowser.java | L140: (1016, 17) | M140: 78beef4bc78a9bbea9cf51e30f24a9a42e577c19 | N140: AnkiDroid/src/main/java/com/ichi2/anki/CardBrowser.java | O140: (1170, 50) | P140: AnkiDroid/src/main/java/com/ichi2/anki/CardBrowser.java | R140: DeckTask.launchDeckTask(DeckTask.TASK_TYPE_DISMISS_MULTI, mRepositionCardHandler, new DeckTask.TaskData(new Object[] {cardIds, Collection.DismissType.REPOSITION_CARDS, this.getInt()})); | S140: repositionDialog.setCallbackRunnable(days -> DeckTask.launchDeckTask(DeckTask.TASK_TYPE_DISMISS_MULTI, mRepositionCardHandler, new DeckTask.TaskData(new Object[] {cardIds, Collection.DismissType.REPOSITION_CARDS, days})) ); | T140: days -> CollectionTask.launchCollectionTask(DISMISS_MULTI, repositionCardHandler(), new TaskData(new Object[] {cardIds, Collection.DismissType.REPOSITION_CARDS, days}))
A141: 139 | B141: jbellis_jamm | C141: https://github.com/jbellis/jamm/commit/f123f2f607a516603a80df1533c94527aceb9c72 | D141: https://github.com/jbellis/jamm/commit/66bedf27a330b9cd99fe1017a3c1e725fb96dd4c | E141: Refactor jamm for a huge performance win (~10x) * Bump min Java version + mvn plugins * Refactor to builder-pattern * Refactor to distinct implementations and save the switch() call for every measure*() invocation * Deprecate spec + unsafe * Add missing method for C* * Add specialized sizeOfArray(any[]) methods * Refactor memory-meter builder to use a "ByteBuffer mode" and introduce 'byteBuffersHeapOnlyNoSlice' | F141: Revert "Merge pull request #41 from snazy/perf-10x" This reverts commit 435e61f1c7e75e17cb430c125b1dfcad500b0dcd, reversing changes made to 21ea49a7be5046002407141316ab15e4df8a4950. | H141: f123f2f607a516603a80df1533c94527aceb9c72 | I141: test/org/github/jamm/GuessTest.java | J141: (133, 25) | K141: test/org/github/jamm/GuessTest.java | L141: (156, 13) | M141: 66bedf27a330b9cd99fe1017a3c1e725fb96dd4c | N141: test/org/github/jamm/GuessTest.java | O141: (156, 37) | P141: test/org/github/jamm/GuessTest.java | R141: System.err.println(String.format("%s of length %d. Guessed %d, instrumented %d", obj.getClass(), Array.getLength(obj), guessed, instrumented)); | S141: results.add(EXEC.submit(() -> { Object obj = Array.newInstance(TYPES[rnd.nextInt(TYPES.length)].clazz, rnd.nextInt(1000)); long instrumented = instrument.measure(obj); long guessed = guess.measure(obj); if (!verify(instrumented, guessed, "%s of length %d. Guessed %d, instrumented %d for %s", obj.getClass(), Array.getLength(obj), guessed, instrumented, guess)) return Boolean.FALSE; return Boolean.TRUE; })); | T141: () -> { Object obj = Array.newInstance(TYPES[rnd.nextInt(TYPES.length)].clazz, rnd.nextInt(1000)); long instrumented = instrument.measure(obj); long guessed = guess.measure(obj); if (!verify(instrumented, guessed, "%s of length %d. Guessed %d, instrumented %d for %s", obj.getClass(), Array.getLength(obj), guessed, instrumented, guess)) return Boolean.FALSE; return Boolean.TRUE; }
A142: 140 | B142: ankidroid_Anki-Android | C142: https://github.com/ankidroid/Anki-Android/commit/678f4496bc30b10138f8cc1c88bf5adc030939b3 | D142: https://github.com/ankidroid/Anki-Android/commit/422ccf9bc76704c5a0dcec6f5cf9093f33850309 | E142: Block file import if no storage permissions This displayed a dialog before we requested permissions, clicking "Add" crashes, as we had no storage permissions. We could do it better in the DeckPicker handler and persist the operation, but we're somewhat constrained for time, and asking the user to perform the operation again isn't a huge ask Fixes #6157 | F142: Allow File Import without Storage Permission During File Import, the contents of the selected file are read using ContentResolver's openInputStream(), which doesn't require storage permission to be granted | H142: 678f4496bc30b10138f8cc1c88bf5adc030939b3 | I142: AnkiDroid/src/main/java/com/ichi2/anki/IntentHandler.java | J142: (34, 13) | K142: AnkiDroid/src/main/java/com/ichi2/anki/IntentHandler.java | L142: (40, 13) | M142: 422ccf9bc76704c5a0dcec6f5cf9093f33850309 | N142: AnkiDroid/src/main/java/com/ichi2/anki/IntentHandler.java | O142: (62, 49) | P142: AnkiDroid/src/main/java/com/ichi2/anki/IntentHandler.java | R142: handleFileImport(intent, reloadIntent, action); | S142: runIfStoragePermissions.consume(() -> handleFileImport(intent, reloadIntent, action)); | T142: () -> handleFileImport(intent, reloadIntent, action)
A143: 141 | B143: web3j_web3j | C143: https://github.com/web3j/web3j/commit/a4ab324a089fc0a5562883b8696dcd50743988e2 | D143: https://github.com/web3j/web3j/commit/79a467011163eaffb53a1b33e880a437cba16cfb | E143: migrate to RxJava2 (no method or class renaming) | F143: Changing the generated code to be Java-6 compatible. | H143: a4ab324a089fc0a5562883b8696dcd50743988e2 | I143: core/src/main/java/org/web3j/ens/contracts/generated/PublicResolver.java | J143: (144, 9) | K143: core/src/main/java/org/web3j/ens/contracts/generated/PublicResolver.java | L143: (136, 9) | M143: 79a467011163eaffb53a1b33e880a437cba16cfb | N143: core/src/main/java/org/web3j/ens/contracts/generated/PublicResolver.java | O143: (130, 49) | P143: core/src/main/java/org/web3j/ens/contracts/generated/PublicResolver.java | R143: return web3j.ethLogObservable(filter).map(new Func1<Log, NameChangedEventResponse>() { @Override public NameChangedEventResponse call(Log log) { EventValues eventValues = extractEventParameters(event, log); NameChangedEventResponse typedResponse = new NameChangedEventResponse(); typedResponse.node = (byte[]) eventValues.getIndexedValues().get(0).getValue(); typedResponse.name = (String) eventValues.getNonIndexedValues().get(0).getValue(); return typedResponse; } }); | S143: return web3j.ethLogObservable(filter).map(log -> { EventValues eventValues = extractEventParameters(event, log); NameChangedEventResponse typedResponse = new NameChangedEventResponse(); typedResponse.node = (byte[]) eventValues.getIndexedValues().get(0).getValue(); typedResponse.name = (String) eventValues.getNonIndexedValues().get(0).getValue(); return typedResponse; }); | T143: log -> { EventValues eventValues = extractEventParameters(event, log); NameChangedEventResponse typedResponse = new NameChangedEventResponse(); typedResponse.node = (byte[]) eventValues.getIndexedValues().get(0).getValue(); typedResponse.name = (String) eventValues.getNonIndexedValues().get(0).getValue(); return typedResponse; }
A144: 142 | B144: mpusher_mpush | C144: https://github.com/mpusher/mpush/commit/76aa1107551813285d546e538dff1a3bf60309c8 | D144: https://github.com/mpusher/mpush/commit/d0eb910c134b78ba10234787e4e1f25f7848f618 | E144: 增加Netty write-buffer-water-mark 配置 | F144: 增加PushCenter消息流转时间线, 方便监控消息的各个生命周期的耗时PushClient -> GatewayClient -> GatewayServer -> PushCenter -> ConnServer -> Client | H144: 76aa1107551813285d546e538dff1a3bf60309c8 | I144: mpush-core/src/main/java/com/mpush/core/push/GatewayPushListener.java | J144: (79, 13) | K144: mpush-core/src/main/java/com/mpush/core/push/GatewayPushListener.java | L144: (82, 13) | M144: d0eb910c134b78ba10234787e4e1f25f7848f618 | N144: mpush-core/src/main/java/com/mpush/core/push/GatewayPushListener.java | O144: (82, 40) | P144: mpush-core/src/main/java/com/mpush/core/push/GatewayPushListener.java | R144: ErrorMessage .from(message) .setErrorCode(PUSH_CLIENT_FAILURE) .setData(message.userId + ',' + message.clientType) .sendRaw(); | S144: message.runInRequestThread(() -> ErrorMessage .from(message) .setErrorCode(PUSH_CLIENT_FAILURE) .setData(message.userId + ',' + message.clientType) .sendRaw() ); | T144: () -> ErrorMessage .from(message) .setErrorCode(PUSH_CLIENT_FAILURE) .setData(message.userId + ',' + message.clientType) .sendRaw()
A145: 143 | B145: web3j_web3j | C145: https://github.com/web3j/web3j/commit/9d56f9cee2b67c5a8a8828502da536ce1bc3c2f7 | D145: https://github.com/web3j/web3j/commit/408214a9a8633be786a844a3a2a291763e70a12d | E145: Fixing compilation issues arising from merge | F145: - Updating all "3.6.0" references to "4.0.0" - Addressing some (not all) PR feedback - Regenerating code | H145: 9d56f9cee2b67c5a8a8828502da536ce1bc3c2f7 | I145: integration-tests/src/test/java/org/web3j/generated/HumanStandardToken.java | J145: (229, 9) | K145: integration-tests/src/test/java/org/web3j/generated/HumanStandardToken.java | L145: (225, 9) | M145: 408214a9a8633be786a844a3a2a291763e70a12d | N145: integration-tests/src/test/java/org/web3j/generated/HumanStandardToken.java | O145: (225, 49) | P145: integration-tests/src/test/java/org/web3j/generated/HumanStandardToken.java | R145: return web3j.ethLogObservable(filter).map(new Func1<Log, TransferEventResponse>() { @Override public TransferEventResponse call(Log log) { Contract.EventValuesWithLog eventValues = extractEventParametersWithLog(TRANSFER_EVENT, log); TransferEventResponse typedResponse = new TransferEventResponse(); typedResponse.log = log; typedResponse._from = (String) eventValues.getIndexedValues().get(0).getValue(); typedResponse._to = (String) eventValues.getIndexedValues().get(1).getValue(); typedResponse._value = (BigInteger) eventValues.getNonIndexedValues().get(0).getValue(); return typedResponse; } }); | S145: return web3j.ethLogObservable(filter).map(log -> { Contract.EventValuesWithLog eventValues = extractEventParametersWithLog(TRANSFER_EVENT, log); TransferEventResponse typedResponse = new TransferEventResponse(); typedResponse.log = log; typedResponse._from = (String) eventValues.getIndexedValues().get(0).getValue(); typedResponse._to = (String) eventValues.getIndexedValues().get(1).getValue(); typedResponse._value = (BigInteger) eventValues.getNonIndexedValues().get(0).getValue(); return typedResponse; } ); | T145: log -> { Contract.EventValuesWithLog eventValues = extractEventParametersWithLog(TRANSFER_EVENT, log); TransferEventResponse typedResponse = new TransferEventResponse(); typedResponse.log = log; typedResponse._from = (String) eventValues.getIndexedValues().get(0).getValue(); typedResponse._to = (String) eventValues.getIndexedValues().get(1).getValue(); typedResponse._value = (BigInteger) eventValues.getNonIndexedValues().get(0).getValue(); return typedResponse; }
A146: 144 | B146: ankidroid_Anki-Android | C146: https://github.com/ankidroid/Anki-Android/commit/b96e0eed677a101a5e3a2608cd503f7edd7e37f6 | D146: https://github.com/ankidroid/Anki-Android/commit/a18fc25f8babb93ba73abcd9f30c6ab172793026 | E146: Converted void methods to executeInTransaction This ensures that the endTransaction behaviour is correct Fixes some of 7265 | F146: NF: Split Dismiss task This avoid a huge case that is not even exhaustive, far more readable as each class concentrate on what matters | H146: b96e0eed677a101a5e3a2608cd503f7edd7e37f6 | I146: AnkiDroid/src/main/java/com/ichi2/async/CollectionTask.java | J146: (711, 13) | K146: AnkiDroid/src/main/java/com/ichi2/async/CollectionTask.java | L146: (698, 13) | M146: a18fc25f8babb93ba73abcd9f30c6ab172793026 | N146: AnkiDroid/src/main/java/com/ichi2/async/CollectionTask.java | O146: (497, 50) | P146: AnkiDroid/src/main/java/com/ichi2/async/CollectionTask.java | R146: col.getDb().getDatabase().beginTransaction(); | S146: col.getDb().executeInTransaction(() -> { sched.deferReset(); switch (type) { case BURY_CARD: // collect undo information Undoable buryCard = revertToProvidedState(BURY_CARD, card); col.markUndo(buryCard); // then bury sched.buryCards(new long[] { card.getId() }); break; case BURY_NOTE: // collect undo information Undoable buryNote = revertToProvidedState(BURY_NOTE, card); col.markUndo(buryNote); // then bury sched.buryNote(note.getId()); break; case SUSPEND_CARD: // collect undo information Card suspendedCard = card.clone(); Undoable suspendCard = new UndoSuspendCard(suspendedCard); col.markUndo(suspendCard); // suspend card if (card.getQueue() == Consts.QUEUE_TYPE_SUSPENDED) { sched.unsuspendCards(new long[] { card.getId() }); } else { sched.suspendCards(new long[] { card.getId() }); } break; case SUSPEND_NOTE: { // collect undo information ArrayList<Card> cards = note.cards(); long[] cids = new long[cards.size()]; for (int i = 0; i < cards.size(); i++) { cids[i] = cards.get(i).getId(); } col.markUndo(revertToProvidedState(SUSPEND_NOTE, card)); // suspend note sched.suspendCards(cids); break; } case DELETE_NOTE: { // collect undo information ArrayList<Card> allCs = note.cards(); Undoable deleteNote = new UndoDeleteNote(note, allCs, card); col.markUndo(deleteNote); // delete note col.remNotes(new long[] { note.getId() }); break; } } // With sHadCardQueue set, getCard() resets the scheduler prior to getting the next card publishProgress(new TaskData(col.getSched().getCard(), 0)); }); | T146: () -> { sched.deferReset(); switch (type) { case BURY_CARD: // collect undo information col.markUndo(revertToProvidedState(BURY_CARD, card)); // then bury sched.buryCards(new long[] {card.getId()}); break; case BURY_NOTE: // collect undo information col.markUndo(revertToProvidedState(BURY_NOTE, card)); // then bury sched.buryNote(note.getId()); break; case SUSPEND_CARD: // collect undo information Card suspendedCard = card.clone(); col.markUndo(new UndoSuspendCard(suspendedCard)); // suspend card if (card.getQueue() == Consts.QUEUE_TYPE_SUSPENDED) { sched.unsuspendCards(new long[] {card.getId()}); } else { sched.suspendCards(new long[] {card.getId()}); } break; case SUSPEND_NOTE: { // collect undo information ArrayList<Card> cards = note.cards(); long[] cids = new long[cards.size()]; for (int i = 0; i < cards.size(); i++) { cids[i] = cards.get(i).getId(); } col.markUndo(revertToProvidedState(SUSPEND_NOTE, card)); // suspend note sched.suspendCards(cids); break; } case DELETE_NOTE: { // collect undo information ArrayList<Card> allCs = note.cards(); col.markUndo(new UndoDeleteNote(note, allCs, card)); // delete note col.remNotes(new long[] {note.getId()}); break; } } // With sHadCardQueue set, getCard() resets the scheduler prior to getting the next card collectionTask.doProgress(col.getSched().getCard()); }
A147: 145 | B147: web3j_web3j | C147: https://github.com/web3j/web3j/commit/a4ab324a089fc0a5562883b8696dcd50743988e2 | D147: https://github.com/web3j/web3j/commit/79a467011163eaffb53a1b33e880a437cba16cfb | E147: migrate to RxJava2 (no method or class renaming) | F147: Changing the generated code to be Java-6 compatible. | H147: a4ab324a089fc0a5562883b8696dcd50743988e2 | I147: core/src/main/java/org/web3j/ens/contracts/generated/PublicResolver.java | J147: (211, 9) | K147: core/src/main/java/org/web3j/ens/contracts/generated/PublicResolver.java | L147: (197, 9) | M147: 79a467011163eaffb53a1b33e880a437cba16cfb | N147: core/src/main/java/org/web3j/ens/contracts/generated/PublicResolver.java | O147: (187, 49) | P147: core/src/main/java/org/web3j/ens/contracts/generated/PublicResolver.java | R147: return web3j.ethLogObservable(filter).map(new Func1<Log, PubkeyChangedEventResponse>() { @Override public PubkeyChangedEventResponse call(Log log) { EventValues eventValues = extractEventParameters(event, log); PubkeyChangedEventResponse typedResponse = new PubkeyChangedEventResponse(); typedResponse.node = (byte[]) eventValues.getIndexedValues().get(0).getValue(); typedResponse.x = (byte[]) eventValues.getNonIndexedValues().get(0).getValue(); typedResponse.y = (byte[]) eventValues.getNonIndexedValues().get(1).getValue(); return typedResponse; } }); | S147: return web3j.ethLogObservable(filter).map(log -> { EventValues eventValues = extractEventParameters(event, log); PubkeyChangedEventResponse typedResponse = new PubkeyChangedEventResponse(); typedResponse.node = (byte[]) eventValues.getIndexedValues().get(0).getValue(); typedResponse.x = (byte[]) eventValues.getNonIndexedValues().get(0).getValue(); typedResponse.y = (byte[]) eventValues.getNonIndexedValues().get(1).getValue(); return typedResponse; }); | T147: log -> { EventValues eventValues = extractEventParameters(event, log); PubkeyChangedEventResponse typedResponse = new PubkeyChangedEventResponse(); typedResponse.node = (byte[]) eventValues.getIndexedValues().get(0).getValue(); typedResponse.x = (byte[]) eventValues.getNonIndexedValues().get(0).getValue(); typedResponse.y = (byte[]) eventValues.getNonIndexedValues().get(1).getValue(); return typedResponse; }
A148: 146 | B148: ankidroid_Anki-Android | C148: https://github.com/ankidroid/Anki-Android/commit/436a044cbae40203d4f6b058077d8cb5a6af8a19 | D148: https://github.com/ankidroid/Anki-Android/commit/44aea97c2d8c69834a64967c40be59d7d05cc0db | E148: Loading models after GUI is shown My AnkiDroid is really slow to start. According to profiling, the slowest part is reading the database content. In particular, reading the json configurations. Those are JSON files which may easily takes more than a MB and does not fit into the cursor. Note type are not required to show the GUI. So I ensure they are loaded asynchronously. Furthermore, since loading is database heavy, I ensure it get done only once the GUI thread has accessed everything it needs. In order to ensure that the models are accessed only once they are loaded, I create a private class, ModelLoader, which will be required to accessed the models. It ensures that models are returned only once it's loaded. This diminish the risk that a future edition tries to access models while they are actually not ready to be used. This was first push as the Pull Request https://github.com/ankidroid/Anki-Android/pull/5929 Given the number of change, I am creating a new branch and a new Pull Request, so if it does not please ankidroid mainteneurs, the previous work is not lost | F148: Revert "Loading models after GUI is shown" This reverts commit 436a044cbae40203d4f6b058077d8cb5a6af8a19. | H148: 436a044cbae40203d4f6b058077d8cb5a6af8a19 | I148: AnkiDroid/src/main/java/com/ichi2/libanki/Collection.java | J148: (269, 9) | K148: AnkiDroid/src/main/java/com/ichi2/libanki/Collection.java | L148: (2061, 13) | M148: 44aea97c2d8c69834a64967c40be59d7d05cc0db | N148: AnkiDroid/src/main/java/com/ichi2/libanki/Collection.java | O148: (2064, 51) | P148: AnkiDroid/src/main/java/com/ichi2/libanki/Collection.java | R148: mModels.load(loadColumn("models")); | S148: mFutureTask = new FutureTask<Models> (() -> new Models(mCol).load(loadColumn("models"))); | T148: () -> new Models(mCol).load(loadColumn("models"))
... A173: 171 | B173: camel-tooling_camel-idea-plugin | C173: https://github.com/camel-tooling/camel-idea-plugin/commit/d88b0a82c277733fafddf575e6d69d05ff79003d | D173: https://github.com/camel-tooling/camel-idea-plugin/commit/0842f6c4bd98faf415224e601118d3b142eb459c | E173: Fixed to not use deprecated api reported by idea plugin report checker | F173: Support IDEA 2020 | H173: d88b0a82c277733fafddf575e6d69d05ff79003d | I173: camel-idea-plugin/src/main/java/com/github/cameltooling/idea/gutter/BeanInjectLineMarkerProvider.java | J173: (73, 17) | K173: camel-idea-plugin/src/main/java/com/github/cameltooling/idea/gutter/BeanInjectLineMarkerProvider.java | L173: (74, 17) | M173: 0842f6c4bd98faf415224e601118d3b142eb459c | N173: camel-idea-plugin/src/main/java/com/github/cameltooling/idea/gutter/BeanInjectLineMarkerProvider.java | O173: (74, 105) | P173: camel-idea-plugin/src/main/java/com/github/cameltooling/idea/gutter/BeanInjectLineMarkerProvider.java | R173: builder.setTargets(new NotNullLazyValue<Collection<? extends PsiElement>>() { @NotNull @Override protected Collection<? extends PsiElement> compute() { return wrapInCollection(reference.resolve()); } }); | S173: builder.setTargets(NotNullLazyValue.lazy((Computable<Collection<? extends PsiElement>>) () -> wrapInCollection(reference.resolve()))); | T173: () -> wrapInCollection(reference.resolve())

Sheet javascript_shuffle
B1: name_with_owner | C1: insert url | D1: delete url | E1: replacement_msg | F1: delete_msg | G1: coding | H1: insert commit | I1: insert src file | J1: insert src start pos | K1: insert dst file | L1: insert dst start pos | M1: delete commit | N1: delete src file | O1: delete src start pos | P1: delete dst file | Q1: delete dst start pos | R1: insert src file content | S1: insert dst file content | T1: delete src file content
A2: 0 | B2: Vaeb_VaeBot | C2: https://github.com/Vaeb/VaeBot/commit/cc96a86d57101bb604479e870ef2f21545173181 | D2: https://github.com/Vaeb/VaeBot/commit/f18ecc19fbcb57b3f10f1b99d295f1db04e20055 | E2: Formatting change (for einstein) | F2: Changed to functions | H2: cc96a86d57101bb604479e870ef2f21545173181 | I2: Util.js | J2: (441, 1) | K2: Util.js | L2: (439, 1) | M2: f18ecc19fbcb57b3f10f1b99d295f1db04e20055 | N2: Util.js | O2: (439, 22) | P2: Util.js | R2: exports.capitalize = function (strParam) { let str = strParam; str = String(str); return str.charAt(0).toUpperCase() + str.slice(1); }; | S2: exports.capitalize = (strParam) => { let str = strParam; str = String(str); return str.charAt(0).toUpperCase() + str.slice(1); }; | T2: (strParam) => { let str = strParam; str = String(str); return str.charAt(0).toUpperCase() + str.slice(1); }
A3: 1 | B3: RanvierMUD_ranviermud | C3: https://github.com/RanvierMUD/ranviermud/commit/6e06527f8bed055b268f9a21a9d1762f247d6f2d | D3: https://github.com/RanvierMUD/ranviermud/commit/5d1c4a99e08e5492fa481b9c72aa98af74b90357 | E3: Trying to fix cleaver wielding, also put meetsPrereqs back into the Feats module as its own export. | F3: WHY ARE ALL OF THESE THINGS HAPPENING. | H3: 6e06527f8bed055b268f9a21a9d1762f247d6f2d | I3: src/command_util.js | J3: (84, 3) | K3: src/command_util.js | L3: (83, 3) | M3: 5d1c4a99e08e5492fa481b9c72aa98af74b90357 | N3: src/command_util.js | O3: (83, 5) | P3: src/command_util.js | R3: let thing = CommandUtil.parseDot(lookString, being.getInventory(), function(item) { return item.hasKeyword(this.keyword, being.getLocale()); }); | S3: let thing = CommandUtil.parseDot(lookString, being.getInventory(), item => item.hasKeyword(this.keyword, being.getLocale()) ); | T3: item => item.hasKeyword(this.keyword, being.getLocale())
A4: 2 | B4: RanvierMUD_ranviermud | C4: https://github.com/RanvierMUD/ranviermud/commit/36779ce96c558a9189496409fd22fd20666278fc | D4: https://github.com/RanvierMUD/ranviermud/commit/9225f7ea44a13d866cc3e7122c6c3d798baf03e0 | E4: Fix load function, improve organization of npc methods. | F4: Fix commands config. | H4: 36779ce96c558a9189496409fd22fd20666278fc | I4: src/npcs.js | J4: (216, 3) | K4: src/npcs.js | L4: (226, 3) | M4: 9225f7ea44a13d866cc3e7122c6c3d798baf03e0 | N4: src/npcs.js | O4: (256, 21) | P4: src/npcs.js | R4: self.getEffects = function (aff) { if (aff) { return typeof self.effects[aff] !== 'undefined' ? self.effects[aff] : false; } return self.effects; }; | S4: self.getEffects = eff => { if (eff) { return self.effects[eff] ? self.effects[eff] : false; } return self.effects; }; | T4: eff => { if (eff) { return self.effects[eff] ? self.effects[eff] : false; } return self.effects; }
A5: 3 | B5: alphasp_pxview | C5: https://github.com/alphasp/pxview/commit/da6612babeb871db07446b360448299fb29aa7b8 | D5: https://github.com/alphasp/pxview/commit/0fc0942ecae1581c32ba926f912e1971506dd3a4 | E5: converting react-navigation in progress | F5: clean up | H5: da6612babeb871db07446b360448299fb29aa7b8 | I5: src/containers/Search.js | J5: (93, 11) | K5: src/containers/Search.js | L5: (162, 11) | M5: 0fc0942ecae1581c32ba926f912e1971506dd3a4 | N5: src/containers/Search.js | O5: (161, 22) | P5: src/containers/Search.js | R5: Actions.searchResult({ word: word, type: ActionConst.REPLACE }); | S5: setTimeout(() => navigate('SearchResult', { word }), 0) | T5: () => navigate('SearchResult', { word })
A6: 4 | B6: winstonjs_winston | C6: https://github.com/winstonjs/winston/commit/852337e51f0df03fec85f955aa6b4e9833b3bd00 | D6: https://github.com/winstonjs/winston/commit/e61f84425204ed5788cfe17d96e19c855bb8b199 | E6: [refactor] Move code base to es6 and setup for api documentation. @indexzero might be interested in this. | F6: Change arrow functions to normal functions to support ES5 with transpiling. | H6: 852337e51f0df03fec85f955aa6b4e9833b3bd00 | I6: lib/winston/transports/file.js | J6: (381, 3) | K6: lib/winston/transports/file.js | L6: (379, 5) | M6: e61f84425204ed5788cfe17d96e19c855bb8b199 | N6: lib/winston/transports/file.js | O6: (368, 20) | P6: lib/winston/transports/file.js | R6: this._stream.end(function () { // eslint-disable-next-line callback-return if (cb) cb(); self.emit('flush'); self.emit('closed'); }); | S6: this._stream.end(() => { if (cb) { cb(); // eslint-disable-line callback-return } this.emit('flush'); this.emit('closed'); }); | T6: () => { if (cb) cb(); this.emit('flush'); this.emit('closed'); }
A7: 5 | B7: winstonjs_winston | C7: https://github.com/winstonjs/winston/commit/852337e51f0df03fec85f955aa6b4e9833b3bd00 | D7: https://github.com/winstonjs/winston/commit/e61f84425204ed5788cfe17d96e19c855bb8b199 | E7: [refactor] Move code base to es6 and setup for api documentation. @indexzero might be interested in this. | F7: Change arrow functions to normal functions to support ES5 with transpiling. | H7: 852337e51f0df03fec85f955aa6b4e9833b3bd00 | I7: lib/winston/transports/file.js | J7: (361, 7) | K7: lib/winston/transports/file.js | L7: (359, 9) | M7: e61f84425204ed5788cfe17d96e19c855bb8b199 | N7: lib/winston/transports/file.js | O7: (348, 28) | P7: lib/winston/transports/file.js | R7: return self._incFile(function () { self.stat(callback); }); | S7: return this._incFile(() => this.stat(callback)); | T7: () => this.stat(callback)
A8: 6 | B8: MaslowCNC_Maslow-Create | C8: https://github.com/MaslowCNC/Maslow-Create/commit/d67baac58420d2f62144cfd0478bac3770356b03 | D8: https://github.com/MaslowCNC/Maslow-Create/commit/c105901b99bfb4e86d526d3bd6af16392641d9a7 | E8: Shrinkwrap works but for 3D shapes now | F8: Shrinkwrap working 3d but only in test | H8: d67baac58420d2f62144cfd0478bac3770356b03 | I8: src/js/molecules/shrinkwrap.js | J8: (30, 9) | K8: src/js/molecules/shrinkwrap.js | L8: (30, 9) | M8: c105901b99bfb4e86d526d3bd6af16392641d9a7 | N8: src/js/molecules/shrinkwrap.js | O8: (36, 31) | P8: src/js/molecules/shrinkwrap.js | R8: this.codeBlock = GlobalVariables.api.hull(GlobalVariables.api.cube().translate([4,4,1]), GlobalVariables.api.sphere()); | S8: this.children.forEach( io => { if(io.connectors.length > 0){ inputs.push(io.getValue()); } }); | T8: io => { if(io.type == "input"){ if(numberOfElements > 0){ arrayOfChildrenString = arrayOfChildrenString + ", "; } numberOfElements += 1; arrayOfChildrenString = arrayOfChildrenString + io.getValue(); } }
A9: 7 | B9: marcelklehr_floccus | C9: https://github.com/marcelklehr/floccus/commit/d1b0d5cd46eca982beaa3879b71defa1c7f8604b | D9: https://github.com/marcelklehr/floccus/commit/9ddbb1673339006d7148f223539f6a2332a3f2be | E9: Introduce typescript typings | F9: Build: Speed up webpack recompile | H9: d1b0d5cd46eca982beaa3879b71defa1c7f8604b | I9: gulpfile.js | J9: (129, 3) | K9: gulpfile.js | L9: (129, 3) | M9: 9ddbb1673339006d7148f223539f6a2332a3f2be | N9: gulpfile.js | O9: (61, 24) | P9: gulpfile.js | R9: webpack(devConfig).watch({}, console.log) | S9: webpack(devConfig).watch({}, (err, stats) => { if (err) { console.log(err) } console.log(stats.toString({ chunks: false, colors: true })) }) | T9: (err, stats) => { if (err) console.log('Webpack', err) console.log( stats.toString({ /* stats options */ }) ) resolve() }
A10: 8 | B10: Vaeb_VaeBot | C10: https://github.com/Vaeb/VaeBot/commit/cc96a86d57101bb604479e870ef2f21545173181 | D10: https://github.com/Vaeb/VaeBot/commit/f18ecc19fbcb57b3f10f1b99d295f1db04e20055 | E10: Formatting change (for einstein) | F10: Changed to functions | H10: cc96a86d57101bb604479e870ef2f21545173181 | I10: Util.js | J10: (1185, 1) | K10: Util.js | L10: (1183, 1) | M10: f18ecc19fbcb57b3f10f1b99d295f1db04e20055 | N10: Util.js | O10: (1184, 17) | P10: Util.js | R10: exports.write = function (content, name) { FileSys.writeFile(name, content); }; | S10: exports.write = (content, name) => { FileSys.writeFile(name, content); }; | T10: (content, name) => { FileSys.writeFile(name, content); }
A11: 9 | B11: Vaeb_VaeBot | C11: https://github.com/Vaeb/VaeBot/commit/cc96a86d57101bb604479e870ef2f21545173181 | D11: https://github.com/Vaeb/VaeBot/commit/f18ecc19fbcb57b3f10f1b99d295f1db04e20055 | E11: Formatting change (for einstein) | F11: Changed to functions | H11: cc96a86d57101bb604479e870ef2f21545173181 | I11: Util.js | J11: (894, 1) | K11: Util.js | L11: (892, 1) | M11: f18ecc19fbcb57b3f10f1b99d295f1db04e20055 | N11: Util.js | O11: (893, 21) | P11: Util.js | R11: exports.getAvatar = function (user, outStr) { if (user != null && exports.isObject(user)) { return (user.displayAvatarURL || (user.user ? user.user.displayAvatarURL : null)); } return (outStr === true ? 'null' : null); }; | S11: exports.getAvatar = (user, outStr) => { if (user != null && exports.isObject(user)) { return (user.displayAvatarURL || (user.user ? user.user.displayAvatarURL : null)); } return (outStr === true ? 'null' : null); }; | T11: (user, outStr) => { if (user != null && exports.isObject(user)) { return (user.displayAvatarURL || (user.user ? user.user.displayAvatarURL : null)); } return (outStr === true ? 'null' : null); }
A12: 10 | B12: LearnersGuild_echo | C12: https://github.com/LearnersGuild/echo/commit/eb1f41ad597efcefd7fa01be4134fa7b008940bf | D12: https://github.com/LearnersGuild/echo/commit/ccfd615ed527e4c3aba19fb393139f64e76c6dd1 | E12: when getting vote results, use latest cycle (and bug fix) - Voting results don't need a cycle in the `GOAL_SELECTION` state; they could just as easily show voting results that are "closed". - BUG FIX: When getting a list of cycles in a certain state for a chapter, the callers all look at index 0 to find the "current" cycle. As such, those results should be ordered by `startTimestamp` _descending_. | F12: allow moderators to view votes | H12: eb1f41ad597efcefd7fa01be4134fa7b008940bf | I12: server/graphql/models/Vote/query.js | J12: (28, 9) | K12: server/graphql/models/Vote/query.js | L12: (28, 9) | M12: ccfd615ed527e4c3aba19fb393139f64e76c6dd1 | N12: server/graphql/models/Vote/query.js | O12: (32, 19) | P12: server/graphql/models/Vote/query.js | R12: let cycle | S12: const cycle = args.cycleId ? await getCycleById(args.cycleId) : await getPlayerById(currentUser.id, true) .default(customQueryError('You are not a player in the game.')) .then(player => getLatestCycleForChapter(player.chapter.id)) | T12: player => getLatestCycleForChapter(player.chapterId, {mergeChapter: true})
A13: 11 | B13: canalplus_react-keys | C13: https://github.com/canalplus/react-keys/commit/95eb868b8966a1a442e47380c6ab0af2ed8e2965 | D13: https://github.com/canalplus/react-keys/commit/0af1e44ebe7b47d4c09bda1163a038994ebe62a7 | E13: V3.x (#84) * first commit * fix redux action * wip * wip priority * totally new fucking mounting system * fix selector targeting * add current handling * mount binder on adding only if active * add sleep behavior * add selector for current and press * massive ut fixes * fix Binder.jsx unit tests * rather not use .push here * 3.0.0-beta.1 * [getCurrentBinder] give binderId to finderBinder function instead of selectedId * 3.0.0-beta.2 * [reducer] add fresh priority on binder mounting * 3.0.0-beta.3 * [README] update * [testConfig] update * [tests] update and fix warnings * Binder: Update priority before compute binders * 3.0.0-beta.4 * [listener] copy listeners table to prevent unwanted updating * 3.0.0-beta.5 * [Binder] delete prevDir on refresh all the time to block flipflop * [Binder] only enter is triggered on touch release * 3.0.0-beta.6 * [tech] use forEach instead of for...of * 3.0.0-beta.7 * [fix] use translateX instead of marginLeft * 3.0.0-beta.8 * [fix] use latest node version * [fix] deploy last dist * 3.0.0-beta.9 * [fix] install rimraf before use it * 3.0.0-beta.10 * Fix error in updateBinder doc (Readme.md) * Binder: Calc diff on wrapper in refreshState (#86) * Binder: Calc diff on wrapper in refreshState * Listener: Change push to unshift for keys listener * Add direction property on binder for calc wrapper diff * Fix return value hasWrapperDiff * Check elements length with hasWrapperDiff function * 3.0.0-beta.11 * [fix] compare system failed if filtered content * 3.0.0-beta.12 * [fix] unsleep memory binder if not mean to be mounted on mounting * 3.0.0-beta.13 * [feature] expose removeBinder * 3.0.0-beta.14 * [fix] ensure no bug if binder already removed * 3.0.0-beta.15 * [fix] make enterstrategy mirror work * 3.0.0-beta.16 * [fix] do nothing if binder state is undefined * 3.0.0-beta.17 * [breaking-change] update API for binder * [refacto] split Binder code * [rename] strategy const * [fix] mount another expected binder when remove one * [perf] improve actions calling * [fix] package json * [fix] compatibility typo * 3.0.0-rc1 * [fix] enterTo instead fo execCb * 3.0.0-rc2 * [fix] propTypes on Carousel * 3.0.0-rc3 * [fix] on enter callback for Carousel * 3.0.0-rc4 * [fix] binder ensure element not empty * [feature] add visibility prop to elements * 3.0.0-rc5 * [fix] always update binder on mount * 3.0.0-rc6 * [feature] add memory options on carousel * [dev] add 1B file * use LTS version of node * 3.0.0-rc7 * [fix] refresh nextEl with fresh visibility * 3.0.0-rc8 * [feature] add selector getBinders * 3.0.0-rc9 * [tools] use presets prettier and jest * [tools] use babel-minify * [tools] exclude useless files for coverage * 3.0.0-rc10 * [feature] add priority for keys * 3.0.0-rc11 * Front(Carousel): Fix positions gap when jumping several children (#87) * V3.x optim binder (#89) * Optimize update binder method * Dispatch only one action for active binder method * Fix bug undefined binder while reset * 3.0.0-rc12 * Fix bug active unknown binder (#90) * 3.0.0-rc13 * bump packages * update README | F13: Bump react-dom version | H13: 95eb868b8966a1a442e47380c6ab0af2ed8e2965 | I13: dist/reactKeys.js | J13: (1, 9601) | K13: dist/reactKeys.js | L13: (439, 13) | M13: 0af1e44ebe7b47d4c09bda1163a038994ebe62a7 | N13: dist/reactKeys.js | O13: (439, 33) | P13: dist/reactKeys.js | R13: f[e]&&(u=i.find(function(t){return t.id===f[e]})),u.id!==f.id&&(o=!0,a=f,l=e),s={hasMoved:o,nextEl:u,prevEl:a,prevDir:l} | S13: n[t] && (l = d.find(r => r.id === n[t])), l.id !== n.id && ((o = !0), (s = n), (a = t)), (p = { hasMoved: o, nextEl: l, prevEl: s, prevDir: a }); | T13: r => r.id === n[t]
... A184: 182 | B184: winstonjs_winston | C184: https://github.com/winstonjs/winston/commit/852337e51f0df03fec85f955aa6b4e9833b3bd00 | D184: https://github.com/winstonjs/winston/commit/e61f84425204ed5788cfe17d96e19c855bb8b199 | E184: [refactor] Move code base to es6 and setup for api documentation. @indexzero might be interested in this. | F184: Change arrow functions to normal functions to support ES5 with transpiling. | H184: 852337e51f0df03fec85f955aa6b4e9833b3bd00 | I184: lib/winston/transports/file.js | J184: (419, 3) | K184: lib/winston/transports/file.js | L184: (451, 5) | M184: e61f84425204ed5788cfe17d96e19c855bb8b199 | N184: lib/winston/transports/file.js | O184: (405, 24) | P184: lib/winston/transports/file.js | R184: return this._incFile(function () { self.open(); }); | S184: return this._incFile(() => { this.open(); }); | T184: () => this.open()

Sheet php_shuffle
B1: name_with_owner | C1: insert url | D1: delete url | E1: replacement_msg | F1: delete_msg | G1: coding | H1: insert commit | I1: insert src file | J1: insert src start pos | K1: insert dst file | L1: insert dst start pos | M1: delete commit | N1: delete src file | O1: delete src start pos | P1: delete dst file | Q1: delete dst start pos | R1: insert src file content | S1: insert dst file content | T1: delete src file content
A2: 0 | B2: FriendsOfPHP_PHP-CS-Fixer | C2: https://github.com/FriendsOfPHP/PHP-CS-Fixer/commit/287c45b0f49c4e5fecaa26caa3b267bc38efc68b | D2: https://github.com/FriendsOfPHP/PHP-CS-Fixer/commit/f87756dca974f86dc88ff84be40be044a6f3ff21 | E2: DX: enable `UseArrowFunctionsFixer` for the codebase (#7194) | F2: DX: remove Prophecy (#7509) | H2: 287c45b0f49c4e5fecaa26caa3b267bc38efc68b | I2: tests/Cache/FileCacheManagerTest.php | J2: (81, 9) | K2: tests/Cache/FileCacheManagerTest.php | L2: (79, 9) | M2: f87756dca974f86dc88ff84be40be044a6f3ff21 | N2: tests/Cache/FileCacheManagerTest.php | O2: (79, 48) | P2: tests/Cache/FileCacheManagerTest.php | R2: $handlerProphecy->write(Argument::that(static function (CacheInterface $cache) use ($signature): bool { return $cache->getSignature() === $signature; }))->shouldBeCalled(); | S2: $handlerProphecy->write(Argument::that(static fn (CacheInterface $cache): bool => $cache->getSignature() === $signature))->shouldBeCalled(); | T2: static fn (CacheInterface $cache): bool => $cache->getSignature() === $signature
A3: 1 | B3: FriendsOfPHP_PHP-CS-Fixer | C3: https://github.com/FriendsOfPHP/PHP-CS-Fixer/commit/287c45b0f49c4e5fecaa26caa3b267bc38efc68b | D3: https://github.com/FriendsOfPHP/PHP-CS-Fixer/commit/f65e6a20c9ef30f2fc93d8c3e1bf6aa3bd910192 | E3: DX: enable `UseArrowFunctionsFixer` for the codebase (#7194) | F3: fix: parsing mixed `&` and `|` in `TypeExpression` (#8210) | H3: 287c45b0f49c4e5fecaa26caa3b267bc38efc68b | I3: src/DocBlock/Annotation.php | J3: (230, 9) | K3: src/DocBlock/Annotation.php | L3: (230, 9) | M3: f65e6a20c9ef30f2fc93d8c3e1bf6aa3bd910192 | N3: src/DocBlock/Annotation.php | O3: (231, 33) | P3: src/DocBlock/Annotation.php | R3: $normalized = array_map(static function (string $type): string { return strtolower($type); }, $this->getTypes()); | S3: $normalized = array_map(static fn (string $type): string => strtolower($type), $this->getTypes()); | T3: static fn (string $type): string => strtolower($type)
A4: 2 | B4: amphp_file | C4: https://github.com/amphp/file/commit/3e012f9e786250298cc3513bc850be6faf8ee168 | D4: https://github.com/amphp/file/commit/742d9303d0446e7485c88a24d00e2956afc03b37 | E4: Refactor for Amp v3 | F4: Use Revolt and update for Amp changes | H4: 3e012f9e786250298cc3513bc850be6faf8ee168 | I4: test/AsyncFileTest.php | J4: (53, 9) | K4: test/AsyncFileTest.php | L4: (52, 9) | M4: 742d9303d0446e7485c88a24d00e2956afc03b37 | N4: test/AsyncFileTest.php | O4: (52, 27) | P4: test/AsyncFileTest.php | R4: $promise1 = $handle->write($data); | S4: $promise1 = async(fn() => $handle->write($data)); | T4: fn() => $handle->write($data)
